Workbook

Sheet Dashboard
A1: Dashboard
A3: Stage 2: Rubrics Average Score based on Languages
A5: Linguistic Quality Ratings by Language
A6: Language | B6: Accuracy / Completeness | C6: Translation Accuracy | D6: Grammar and Fluency | E6: Language Purity
A7: Telugu | B7: =average('Stage 2_Telugu'!E3:E246) -> 3.1 | C7: =average('Stage 2_Telugu'!I3:I246) -> 2.8 | D7: =average('Stage 2_Telugu'!J3:J246) -> 3.2333333 | E7: =average('Stage 2_Telugu'!K3:K246) -> 3.0666667
A8: Assamese | B8: =average('Stage 2_Assamese'!E3:E2476) -> 3.6333333 | C8: =average('Stage 2_Assamese'!I4:I247) -> 3.9666667 | D8: =average('Stage 2_Assamese'!J4:J247) -> 4 | E8: =average('Stage 2_Assamese'!K4:K247) -> 3.4
A9: Bengali | B9: =average('Stage 2_Bengali'!E4:E2477) -> 3.3666667 | C9: =average('Stage 2_Bengali'!I5:I248) -> 4 | D9: =average('Stage 2_Bengali'!J5:J248) -> 4 | E9: =average('Stage 2_Bengali'!K5:K248) -> 2.9333333
A10: Gujarati | B10: =average('Stage 2_Gujarati'!E5:E2478) -> 3.4 | C10: =average('Stage 2_Gujarati'!I6:I34) -> 4 | D10: =average('Stage 2_Gujarati'!J6:J34) -> 4 | E10: =average('Stage 2_Gujarati'!K6:K34) -> 3.2758621
A11: Kannada | B11: =average('Stage 2_Kannada'!E6:E2479) -> 3.5172414 | C11: =average('Stage 2_Kannada'!I7:I250) -> 3.8928571 | D11: =average('Stage 2_Kannada'!J7:J250) -> 3.9285714 | E11: =average('Stage 2_Kannada'!K7:K250) -> 3.3928571
A12: Malayalam | B12: =average('Stage 2_Malayalam'!E7:E2480) -> 3.6071429 | C12: =average('Stage 2_Malayalam'!I8:I251) -> 3.2962963 | D12: =average('Stage 2_Malayalam'!J8:J251) -> 3.5925926 | E12: =average('Stage 2_Malayalam'!K8:K251) -> 3.8518519
A13: Marathi | B13: =average('Stage 2_Marathi'!E8:E2481) -> 3.1851852 | C13: =average('Stage 2_Marathi'!I9:I252) -> 3.9615385 | D13: =average('Stage 2_Marathi'!J9:J252) -> 3.6923077 | E13: =average('Stage 2_Marathi'!K9:K252) -> 3.6153846
A14: Tamil | B14: =average('Stage 2_Tamil'!E9:E2482) -> 3.5769231 | C14: =average('Stage 2_Tamil'!I10:I253) -> 4 | D14: =average('Stage 2_Tamil'!J10:J253) -> 4 | E14: =average('Stage 2_Tamil'!K10:K253) -> 4
A17: Functional & Factual Grounding Pass Rates by Language
A18: Language | B18: Actionability | C18: Conversation Closure | D18: Source Data Comprehensiveness | E18: No Fabrication | F18: Citation Accuracy
A19: Telugu | B19: 1 | C19: 1 | D19: 1 | E19: 0.91666667 | F19: 0.875
A20: Assamese | B20: 0.86666667 | C20: 1 | D20: 0.83333333 | E20: 0.86206897 | F20: 0.55172414
A21: Bengali | B21: 1 | C21: 0.96666667 | D21: 1 | E21: 0.91666667 | F21: 0.95833333
A22: Gujarati | B22: 0.93103448 | C22: 1 | D22: 0.72413793 | E22: 0.82608696 | F22: 0.7826087
A23: Kannada | B23: 0.96428571 | C23: 1 | D23: 0.82142857 | E23: 0.90909091 | F23: 0.81818182
A24: Malayalam | B24: 0.92592593 | C24: 1 | D24: 0.88888889 | E24: 0.86956522 | F24: 0.86956522
A25: Marathi | B25: 1 | C25: 0.96153846 | D25: 0.73076923 | E25: 0.95 | F25: 0.8
A26: Tamil | B26: 1 | C26: 1 | D26: 0.64 | E26: 0.78947368 | F26: 0.68421053
A29: Total | B29: 240 | C29: 🟢 Completed | D29: 240 | E29: 🟡 In Progress | F29: 0 | G29: 🔴 Not Started | H29: 0 | I29: Completion % | J29: 1
A31: Language | B31: Total | C31: Completed | D31: In Progress | E31: Not Started | F31: Completion Percentage
A32: Stage 2_Telugu | B32: 30 | C32: 30 | D32: 0 | E32: 0 | F32: 1
A33: Stage 2_Assamese | B33: 30 | C33: 30 | D33: 0 | E33: 0 | F33: 1
A34: Stage 2_Bengali | B34: 30 | C34: 30 | D34: 0 | E34: 0 | F34: 1
A35: Stage 2_Gujarathi | B35: 30 | C35: 30 | D35: 0 | E35: 0 | F35: 1
A36: Stage 2_Kannada | B36: 30 | C36: 30 | D36: 0 | E36: 0 | F36: 1
A37: Stage 2_Malayalam | B37: 30 | C37: 30 | D37: 0 | E37: 0 | F37: 1
A38: Stage 2_Marathi | B38: 30 | C38: 30 | D38: 0 | E38: 0 | F38: 1
A39: Stage 2_Tamil | B39: 30 | C39: 30 | D39: 0 | E39: 0 | F39: 1
A40: TOTAL | B40: 240 | C40: 240 | D40: 0 | E40: 0 | F40: 1

Sheet Stage 2_Telugu
C1: Whenever you select a score, its definition will appear here. Please review it before submitting your evaluation. | E1: Select a score to see the scoring description.
A3: EVALUATION CATEGORY | E3: RESPONSE USEFULNESS | I3: LINGUISTIC QUALITY | L3: The response should contain the exact attribute values from the source. This verifies that the model has not fabricated, modified, or omitted any source information. | M3: FACTUAL GROUNDING | O3: Please add any required corrections and a detailed overall remarks based on scores provided. | P3: Status | Q3: QC Feedback | T3: Evaluator response to reviewer Feedback
A4: ID | B4: question_id | C4: Prompt | D4: Response | E4: Accuracy / Completeness (1-4) | F4: Actionability (0/1) | G4: Conversation Closure (0/1) | H4: Source Data Comprehensiveness (0/1) | I4: Translation Accuracy (1-4) | J4: Grammar and Fluency (1-4) | K4: Language Purity (1-4) | L4: Tool Source data | M4: No Fabrication (0/1) Note: Verify response with tool source data | N4: Citation Accuracy (0/1) Note: Verify response with tool source data | Q4: Score | R4: Status | S4: Detailed Remarks
A5: 1 | B5: 1-1 | C5: ముంబై మాండి లో ఈ రోజు ఆల్ మిర్చి ధరలు ఏమిటి? | D5: ముంబై మాండిలో ఎర్ర మిర్చికి సంబంధించిన ధరల సమాచారం ప్రస్తుతం అందుబాటులో లేదు. **మూలం: మండి ధరలు** మీకు వేరే పంట ధరల గురించి లేదా ఇతర ప్రాంతాల ధరల గురించి తెలియాలా? | E5: 4 | F5: 1 | G5: 1 | H5: 1 | I5: 2 | J5: 3 | K5: 3 | L5: [tool:get_mandi_prices] **Mandi Price Discovery** [Today's Date: Monday, 25 May 2026] No mandi price data found for the requested location and commodity. [tool:search_commodity] ### Commodity matches for `all mirchi` | Commodity | Matched Term (Score) | Code | |---|---|---| | **Chili Red** | lal mirchi (95%) | `26` | | **Round Chilli** | gol mirchi (89%) | `520` | | **Black pepper** | kali mirch (84%) | `34` | | **Chilly Capsicum** | mirchi (80%) | `74` | | **Pepper ungarbled** | mirchi (80%) | `94` | [tool:forward_geocode] Mumbai, Mumbai Suburban, Maharashtra, India (Latitude: 19.055, Longitude: 72.869) | M5: 1 | N5: 0 | O5: In promt it said all prices of mirchi in Mumbai mandi , but in the response it said red mirchi prices are not available for Mumbai location instead of giving information about all kind of mirchi | P5: Completed | Q5: 2 | R5: Needs Re-evaluation | S5: Stage 2 correctly flipped Citation Accuracy to 0 due to untranslated numbers. | T5: updated
A6: 2 | B6: 2-1 | C6: పార్భణి ప్రాంతంలో పంట బీమా పథకానికి అవసరమైన పత్రాలు ఏమిటి? | D6: పిఎం ఫసల్ బీమా యోజన (PMFBY) కింద పంట బీమా కోసం ఈ క్రింది పత్రాలు అవసరం: * ఆధార్ కార్డు * భూమి రికార్డులు లేదా లీజు ఒప్పంద పత్రం (అద్దెకు తీసుకున్న రైతులకు) * బ్యాంకు ఖాతా వివరాలు * పట్వారీ లేదా వ్యవసాయ అధికారి నుండి పొందిన పంట సాగు ధృవీకరణ పత్రం * పంట నష్టం సంభవించినప్పుడు, పంట ఫోటోలు (క్లెయిమ్ కోసం) **మూలం: ప్రభుత్వ పథక సమాచారం** మీరు ఇప్పటికే ఈ పథకానికి దరఖాస్తు చేసుకున్నారా లేదా కొత్తగా దరఖాస్తు చేయాలనుకుంటున్నారా? | E6: 4 | F6: 1 | G6: 1 | H6: 1 | I6: 4 | J6: 4 | K6: 4 | L6: [tool:get_scheme_info] **Source:** PM Fasal Bima Yojana (PMFBY) ## Introduction Pradhan Mantri Fasal Bima Yojana (PMFBY) was launched in January 2016 as a comprehensive crop insurance scheme replacing the earlier National Agricultural Insurance Scheme (NAIS). It provides financial support to farmers suffering crop loss or damage due to unforeseen events like natural calamities, pests, and diseases. ## Benefits Coverage for crop losses due to non-preventable natural risks, prevented sowing, post-harvest losses, and localized calamities. Premium rates are very low: 2% for Kharif crops, 1.5% for Rabi crops, 5% for commercial/horticultural crops. Government pays the balance premium. Sum insured based on Scale of Finance declared by the state. Claims settled within 2 months of harvest. ## Eligibility All farmers including sharecroppers and tenant farmers growing notified crops in notified areas are eligible. Both loanee farmers (mandatory coverage for those with crop loans from banks) and non-loanee farmers (voluntary) can enrol. Aadhaar is mandatory for registration. ## How to Apply Loanee farmers are enrolled automatically by their bank at time of crop loan. Non-loanee farmers can apply through: (1) Banks (nationalised, cooperative, Regional Rural Banks), (2) Common Service Centres (CSC), (3) Insurance company agents, (4) Pradhan Mantri Fasal Bima Yojana portal (pmfby.gov.in). Applications must be submitted before the cutoff date for each season. ## Documents Required Aadhaar card, land records or lease agreement (for tenant farmers), bank account details, crop sowing certificate from Patwari/Agriculture Officer, photograph of standing crop before loss (for post-harvest claims). | M6: 1 | N6: 1 | P6: Completed | Q6: 3 | R6: Accept with Minor Corrections | S6: The overall evaluation is correct and the core findings are valid. Minor 1-point score variances exist between stages, primarily in Accuracy/Completeness. These minor corrections do not impact the overall validity and can be accepted with minor updates. | T6: updated
A7: 3 | B7: 3-1 | C7: సంగ్లీ జిల్లాలో మక్కా పంట కోతకు వాతావరణం అనుకూలంగా ఉందా? | D7: సంగ్లీ జిల్లాలో ప్రస్తుతం మరియు రాబోయే రోజుల్లో తేలికపాటి వర్షాలు మరియు పిడుగులు పడే అవకాశం ఉంది, కాబట్టి మక్కా పంట కోతకు వాతావరణం అంత అనుకూలంగా లేదు. ముఖ్యంగా ఈ రోజు మరియు రేపు వర్ష సూచన ఉన్నందున, కోత పనులను వాయిదా వేయడం మంచిది. మే ౨౬నాడు ఆకాశం పాక్షికంగా మేఘావృతమై ఉంటుంది, కాబట్టి అప్పుడు వాతావరణాన్ని బట్టి నిర్ణయం తీసుకోండి. **మూలం: వాతావరణ సూచన (IMD)** మీకు మక్కా పంట నిల్వ పద్ధతుల గురించి సమాచారం కావాలా? | E7: 4 | F7: 1 | G7: 1 | H7: 1 | I7: 4 | J7: 2 | K7: 2 | L7: [tool:weather_forecast] **Weather Forecast Data** [Today's Date: Monday, 25 May 2026] Responses: Catalog: Weather Catalog for Weather-Forecast-Mausamgram Providers: Provider: Mausamgram Weather Forecast Categories: - Weather Forecast Fulfillments: Fulfillment ID: f1 Stops: - Lat: 16.85, Lon: 74.595 Items: **Item:** Weather Report for Lat: 16.85, Lon: 74.595 Short: Mausamgram Forecast Tags: Today: Location: Lat: 16.85, Lon: 74.595 Date: 2026-05-24 Rainfall: 8.13 mm Min Temp: 24.24 °C Max Temp: 33.5 °C Min Humidity: 50.79 % Max Humidity: 80.42 % Wind Speed: 4.86 m/s Wind Direction: Westerly Weather Condition: Generally Cloudy Sky with possibility of Light Rainfall or Thunderstorm Day_2: Location: Lat: 16.85, Lon: 74.595 Date: 2026-05-25 Rainfall: 3.8 mm Min Temp: 25.5 °C Max Temp: 35.04 °C Min Humidity: 40.37 % Max Humidity: 83.95 % Wind Speed: 4.5 m/s Wind Direction: Westerly Weather Condition: Generally Cloudy Sky with possibility of Light Rainfall or Thunderstorm Day_3: Location: Lat: 16.85, Lon: 74.595 Date: 2026-05-26 Rainfall: 0.77 mm Min Temp: 25.1 °C Max Temp: 34.6 °C Min Humidity: 41.66 % Max Humidity: 84.24 % Wind Speed: 4.05 m/s Wind Direction: Westerly Weather Condition: Partly Cloudy Sky Day_4: Location: Lat: 16.85, Lon: 74.595 Date: 2026-05-27 Rainfall: 3.65 mm Min Temp: 25.5 °C Max Temp: 35.3 °C Min Humidity: 40.57 % Max Humidity: 83.96 % Wind Speed: 4.16 m/s Wind Direction: Westerly Weather Condition: Partly Cloudy Sky with possibility of Light Rainfall or Thunderstorm Day_5: Location: Lat: 16.85, Lon: 74.595 Date: 2026-05-28 Rainfall: 0.12 mm Min Temp: 24.8 °C Max Temp: 35.4 °C Min Humidity: 39.4 % Max Humidity: 82.71 % Wind Speed: 4.83 m/s Wind Direction: Westerly Weather Condition: Mainly Clear Sky [tool:forward_geocode] Sangli, Miraj, Maharashtra, India (Latitude: 16.85, Longitude: 74.595) | M7: 1 | N7: 1 | O7: In response there is word called "may nadu" which looks like not translated well | P7: Completed | Q7: 2 | R7: Needs Re-evaluation | S7: In QID 3-1, concerning maize harvest weather in Sangli, the response contains an untranslated term ('may nadu') and raw numerical values. Stage 2 flipped it to 0 due to language purity and translation flaws. This unaddressed scoring flip requires a Score of 2 (Needs Re-evaluation). Re-evaluate Language Purity, Grammar & Fluency, and Citation Accuracy. | T7: updated
A8: 4 | B8: 4-1 | C8: వర్ధా జిల్లాలో డ్రిప్ ఇరిగేషన్ పథకానికి ఎలా దరఖాస్తు చేయాలి? | D8: డ్రిప్ ఇరిగేషన్ (బిందు సేద్యం) కోసం 'ప్రతి చుక్క ఎక్కువ పంట' (PDMC) పథకం కింద మీరు దరఖాస్తు చేసుకోవచ్చు. దీనికి దరఖాస్తు చేసే విధానం ఇక్కడ ఉంది: **దరఖాస్తు విధానం:** * జిల్లా వ్యవసాయ లేదా ఉద్యానవన శాఖ కార్యాలయం ద్వారా దరఖాస్తు చేసుకోవచ్చు. * రాష్ట్ర ప్రభుత్వ పి.ఎం.కే.ఎస్.వై-పి.డి.ఎం.సి (PMKSY-PDMC) పోర్టల్ ద్వారా ఆన్‌లైన్‌లో దరఖాస్తు చేయవచ్చు. * ప్రభుత్వ గుర్తింపు పొందిన డ్రిప్/స్ప్రింక్లర్ పరికరాల తయారీదారులు లేదా డీలర్ల ద్వారా కూడా దరఖాస్తు చేసుకోవచ్చు. **అవసరమైన పత్రాలు:** * భూమి రికార్డులు (ఖతానంబర్, విస్తీర్ణం). * ఆధార్ కార్డు. * బ్యాంకు ఖాతా వివరాలు. * గుర్తింపు పొందిన వెండర్ నుండి పొందిన కొటేషన్. * నీటి వనరుల లభ్యతకు సంబంధించిన ఆధారాలు. * పొలం యొక్క జియో-ట్యాగ్డ్ ఫోటో. **మూలం: ప్రభుత్వ పథక సమాచారం** మీకు ఈ పథకానికి సంబంధించి అర్హత వివరాలు లేదా సబ్సిడీ మొత్తాల గురించి మరింత సమాచారం కావాలా? | E8: 4 | F8: 1 | G8: 1 | H8: 1 | I8: 4 | J8: 4 | K8: 4 | L8: [tool:get_scheme_info] **Source:** Per Drop More Crop (PDMC) ## Introduction Per Drop More Crop (PDMC) is a component of PM Krishi Sinchayee Yojana (PMKSY) focused exclusively on micro-irrigation — drip and sprinkler systems — to enhance water use efficiency at the farm level. The scheme promotes efficient on-farm water management practices and reduces water wastage while improving crop productivity. ## Benefits Subsidy on drip irrigation systems: 55% for small/marginal farmers (land ≤ 2 ha), 45% for other farmers. Subsidy on sprinkler systems: 55% for small/marginal, 45% for others. Water savings of 40-50% compared to flood irrigation. Yield improvement of 20-50% depending on crop. Also covers secondary storage structures, water-carrying pipes, and fertigation equipment. ## Eligibility All farmers with a minimum of 0.5 acre of agricultural land. Farmers with access to a reliable water source (borewell, canal, river, tank). One-time benefit per farmer per land parcel (subsidy not available if availed within last 7 years). SC/ST and women farmers may get additional state-level benefits. ## How to Apply Apply through: (1) District Agriculture/Horticulture Office, (2) State government PMKSY-PDMC portal, (3) Registered drip/sprinkler equipment manufacturers/dealers. Select empanelled vendor, get installation quote. Submit application with documents. After approval, purchase and install system. Subsidy released after field verification. ## Documents Required Land records (Khasra number, area), Aadhaar card, bank account details, quotation from empanelled/registered vendor, water source availability proof (borewell registration / water permission), geo-tagged photograph of field, caste certificate (for SC/ST farmers). | M8: 1 | N8: 1 | P8: Completed | Q8: 3 | R8: Accept with Minor Corrections | S8: The overall evaluation is correct and the core findings are valid. Minor 1-point score variances exist between stages, primarily in Accuracy/Completeness. These minor corrections do not impact the overall validity and can be accepted with minor updates. | T8: updated
A9: 5 | B9: 5-1 | C9: బుల్ధానా ప్రాంతంలో కాలీఫ్లవర్‌తో ఏ మధ్యపంటలు వేయాలి? | D9: క్షమించండి, బుల్ధానా ప్రాంతంలో కాలీఫ్లవర్‌తో కలిపి వేయవలసిన నిర్దిష్ట మధ్యపంటల (intercrops) గురించి నా వద్ద ఉన్న అధికారిక డేటాలో సమాచారం అందుబాటులో లేదు. మీకు సహాయపడటానికి, మీ పొలంలోని మట్టి ఆరోగ్యం మరియు ప్రస్తుత పరిస్థితుల ఆధారంగా సరైన పంటల ఎంపిక కోసం మీ స్థానిక వ్యవసాయ అధికారిని లేదా కృషి విజ్ఞాన కేంద్రం (కె.వి.కె) ను సంప్రదించవలసిందిగా సూచిస్తున్నాను. మీకు మరేదైనా పంట సలహాలు లేదా ప్రభుత్వ పథకాల గురించి సమాచారం కావాలా? | E9: 1 | F9: 1 | G9: 1 | H9: 1 | I9: 1 | J9: 3 | K9: 2 | L9: [tool:search_documents] > Search Results for `intercropping crops with cauliflower in Buldhana Maharashtra` **ICAR Kharif Agro-Advisories for Farmers** ``` FRUIT CROPS Pomegranate [अनार] The preferred variety is Bhagwa, planted at a spacing [अंतर] of 3.2 x 2.6 meters with a planting density of 1200 plants per hectare between June to September. Propagation [प्रजनन] is done through air layering [गुट्टी कलम] and tissue culture [ऊतक संवर्धन], with cuttings [कटिंग] treated using 5000 ppm IBA. Intercropping [अंतरफसल] with cowpea [लोबिया], cucumber [खीरा], cabbage [पत्ता गोभी], onion [प्याज], and pea [मटर] is practiced during the first 5-6 years. Fertilizer [उर्वरक] dose is 197:99:99 NPK kg/ha. Borax [बोरैक्स] is applied at 1 g/L of water. Drip irrigation [ड्रिप सिंचाई] is scheduled at 11 L/day during rainy season, 12 L/day in winter, and 22 L/day in summer. Herbicides [शाकनाशी] such as Diuron (1 kg/ha in nursery [नर्सरी]) and Nephromide (2 kg/ha in the main orchard) are used for weed control [खरपतवार नियंत्रण]. Pomegranate [अनार] is prone to several diseases like bacterial blight [झुलसा], anthracnose [फफूंदजनित रोग], fruit rot [फल सड़न], Cercospora leaf spot [सर्कोस्पोरा पत्ती धब्बा], Alternaria fruit spot, and Fusarium wilt [फ्यूजेरियम मुरझान रोग]. Management includes fungicide [फफूंदनाशी] sprays (e.g., Dithane M-45, Captan, Bavistin), sanitation, and orchard hygiene. Pest [कीट] issues include the anar butterfly (fruit borer [फल बेधक कीट]), bark-eating caterpillars, whiteflies, aphids, mealy bugs, and fruit flies. Integrated Pest Management [समेकित कीट प्रबंधन] (IPM) practices include cultural sanitation, pruning [फ枝剪ाई], biological agents like Trichogramma [ट्राइकोग्रामा], neem-based products, polythene bagging, and chemical treatments like malathion. Grape ``` ---- **ICAR Kharif Agro-Advisories for Farmers** ``` Maharashtra The Kharif season, stretching from June to October, is a crucial agricultural period for the state of Maharashtra, significantly influencing the livelihoods of millions of farmers. Characterized by the onset of the southwest monsoon [मानसून], this season supports the cultivation of key crops such as rice [चावल], cotton [कपास], soybeans, pulses, and millets. However, climate [जलवायु] variability, erratic rainfall, and changing weather [मौसम] patterns pose continuous challenges to sustainable agriculturalproduction. Inthelightofthesechallenges, the Kharif 2025 Agro-Advisoryaims to provide timely, region-specific, and science-based recommendations to empower farmerswiththeknowledgeneededtomakeinformeddecisions. REGIONAL ADVISORY Maharashtra is divided into several agroclimatic zones, each with unique characteristics influencing crop selection [फसल चयन], sowing [बुवाई] windows, and input management. The following region-wise advisories aim to support farmers with tailored recommendations for improved productivity and resilience. VIDARBHA REGION The Vidarbha region of Maharashtra is composed of Bhandara, Chandrapur, Gondia Gadchiroli, Nagpur, Amravati, Akola, Yavatmal, Buldhana, Wardha, Washim and possesses state agricultural university viz., Dr. Panjabrao Deshmukh Krishi Vidyapeeth, Akola. Soil Testing [मृदा परीक्षण] & Preparation (All Crops) Soil testing [मृदा परीक्षण] is crucial for effective fertilizer management [उर्वरक प्रबंधन], optimizing input use, and maintaining soil fertility [मृदा उर्वरता]. For proper soil sampling [मृदा नमूना लेना], the recommended depths are 15- 20 cm for crops like sorghum [ज्वार], rice [चावल], groundnut [मूंगफली], and wheat [गेहूं]; 30 cm for cotton [कपास], sugarcane [गन्ना], and banana [केला]; and 30 cm for fruit trees, sampled from a distance of 1-1.5 feet from the trunk. Additionally, applying decomposers to crop [फसल] residues like straw and leaves enhances organic matter content [जैविक पदार्थ की मात्रा], improves soil structure [मृदा संरचना], and boosts water retention [पानी धारण क्षमता], contributing to sustainable agricultural practices [कृषि पद्धतियाँ]. ICAR Kharif Agro-Advisory [कृषि सलाह] 2025 CEREALS CROPS Paddy ``` ---- **ICAR Rabi Agro-Advisories for Farmers 2025** ``` # VIDARBHA Vidarbha, located in eastern Maharashtra, comprises the districts of Nagpur, Amravati, Akola, Yavatmal, Buldhana, Wardha, Chandrapur, Gadchiroli, and Washim. The region receives moderate to high rainfall ranging from 800 to 1200 mm, and has varied soil [मिट्टी] types, including black cotton [कपास] soils and red loamy soils. Major Rabi crops [रबी फसलें] grown in Vidarbha include chickpea [चना], wheat [गेहूं], mustard [सरसों], and orange [संतरा]. # Cereal [अनाज] crops ## Wheat [गेहूं] For Rabi wheat [गेहूं] in Vidarbha, sowing [बुवाई] under irrigated conditions should be completed between 15th and 30th November. Recommended varieties include AKAW-5100, AKW-1071 (Purna), AKW-3722 (Vimal), PDKV Sardar, HD-2189, and HD-2380. Use a seed rate [बीज दर] of 100-125 kg/ha with row spacing [पंक्तियों के बीच दूरी] of 15-22.5 cm. Before sowing [बुवाई], treat seeds with carbendazim (2 g/kg) or thiram (3 g/kg) to prevent bacterial diseases, followed by biofertilizers [जैव उर्वरक] Farmer [किसान] Wheat [गेहूं] plot Var. Phule Samadhan (Azotobacter 250 g + PSB 250 g/10 kg seed [बीज]). Apply a basal dose [प्रारंभिक मात्रा (उर्वरक की)] of NPK fertilizer [उर्वरक] (80-120:40-50:40-50 kg/ha), with 50% nitrogen [नाइट्रोजन] as basal and the remainder split at crown root [मुकुट जड़] initiation 181 ``` ---- **ICAR Rabi Agro-Advisories for Farmers 2025** ``` ### Sesame [तिल] VRI(Sv) 2, TMV 7, VRI 3, and VRI 4. Seed treatment [बीज उपचार] with Trichoderma [ट्राइकोडर्मा] @ 4 g/kg of seed [बीज], Bacillus subtilis @ 2 g/kg seed [बीज], or NSKE 4%. Intercropping [अंतरफसल] of sesamum + redgram (6:1) for additional net returns. Apply 35:23:23 kg N:P₂O₅:K₂O/ha and TNAU micronutrient [सूक्ष्म पोषक तत्व] mixture @ 12.5 kg/ha as enriched FYM. Thinning [间दाई करना] of excess seedlings is to be done to induce basal branching. Application of six packets of azophos (1200 g/ha) ### Sugarcane [गन्ना] COC 671, COC 92061, COC 6304, COC 22, CO 86032, 83 R 23, CO 18009. Other varieties by SBI are Co 11015 (Atulya), Co 14012, and Co 18009. Apply 275:62.5:112.5 kg N:P₂O₅:K₂O/ha. Intercrop with dhaincha/sunnhemp in wider rows and incorporate. Use a power weeder [निराई करने वाली मशीन] for weeding [निराई करना] and earthing up [मिट्टी चढ़ाना] with a ridger to save the cost of cultivation [खेती की लागत]. Trash mulching [मल्चिंग] to avoid the incidence of early shoot borer [शिखर छेदक कीट]. Foliar spray [पत्तियों पर छिड़काव] of Sugarcane [गन्ना] booster. ## Horticultural crops ### Fruit crops #### Banana [केला] ``` ---- **ICAR Rabi Agro-Advisories for Farmers 2025** ``` ICAR Rabi Agro-Advisory [कृषि सलाह] 2025 # Livestock [पशुधन] ## Dairy [दुग्ध व्यवसाय] Cattle Timely vaccination (FMD, HS, BQ) and deworming are essential in the Rabi season, along with protection from mastitis, pneumonia, and lumpy skin disease [रोग] in cold, damp months. They should be fed green fodder [हरा चारा] like berseem and oats, supplemented with dry fodder [सूखा चारा], concentrates, and warm water, while sheds must be kept clean, dry, and windproof with bedding or blankets for calves ## Goat Goats require vaccination (PPR, ET), regular deworming, and monitoring for ectoparasites, scabies, hoof rot, and respiratory issues. Their diet should include 0.5-2 kg green fodder [हरा चारा], 200-400 g concentrate, and tree leaves, with warm water during winter. Housing should be dry, elevated, and windproof to protect kids from the cold. ## Poultry [पोल्ट्री पालन] Poultry [पोल्ट्री पालन] must be vaccinated (Ranikhet, IBD, Fowl Pox) and protected from coccidiosis, avian influenza, and respiratory stress. They need high-energy feed with calcium [कैल्शियम] and vitamins, grit, and electrolytes during cold stress [ठंड के कारण होने वाला तनाव], while coops should be insulated, well-ventilated, dry, and biosecure. Overall, the focus is on disease [रोग] prevention, warmth, energy-rich feeding, and gradual transition to summer care by February-March. # VIDARBHA Vidarbha, located in eastern Maharashtra, comprises the districts of Nagpur, Amravati, Akola, Yavatmal, Buldhana, Wardha, Chandrapur, Gadchiroli, and Washim. The region receives moderate to high rainfall ranging from 800 to 1200 mm, and has varied soil [मिट्टी] types, including black cotton [कपास] soils and red loamy soils. Major Rabi crops [रबी फसलें] grown in Vidarbha include chickpea [चना], wheat [गेहूं], mustard [सरसों], and orange [संतरा]. # Cereal [अनाज] crops ## Wheat [गेहूं] ``` ---- **ICAR Kharif Agro-Advisories for Farmers** ``` 1. Follow crop rotation [फसल चक्र] avoid cotton [कपास] sowing [बुवाई] followed by tomato [टमाटर], chickpea [चना], etc. 2. Sowing [बुवाई] of intercrop or mixed crop [फसल] like maize [मक्का], cowpea [लोबिया], Black gram [उड़द], green gram [मूंग] and use of trap crop [फंदा फसल] like marigold, castor [अरंडी], etc. 3. Sowing [बुवाई] of okra [भिंडी] as a trap crop [फंदा फसल] in cotton [कपास] for the control of Pink Bollworm [गुलाबी सुंडी]. 4. Avoid plant growth promoters and pesticides during first three months and use botanical pesticides or biopesticides [जैव कीटनाशी] 5. Spray of 5 % NSKE at 60 DAS 6. Install 40 pheromone traps [फेरोमोन जाल] per ha for mass trapping [सामूहिक फंदा] of pink bollworm [गुलाबी सुंडी]. Maharashtra PULSE [दाल] CROPS Soybean [सोयाबीन] The own seed [बीज] of Soybean [सोयाबीन] should be used for next Kharif season after testing its germination [अंकुरण] to save money as well as it will help to face the situation of seed [बीज] shortage in the market. Seed germination [बीज अंकुरण] should be tested before sowing [बुवाई] and good quality seed [गुणवत्तापूर्ण बीज] with more than 70 % germination [अंकुरण] should be used for sowing [बुवाई] only. Improved varieties like MAUS-162, MAUS-612, MAUS-725, Phule Durva, Phule Kimaya, PDKV Yellow Gold, PDKV Amba should be used for sowing [बुवाई]. Soybean [सोयाबीन] seed [बीज] should be treated with Thiram @ 3 g/kg or Trichoderma [ट्राइकोडर्मा] @ 4 g/kg of seed [बीज] and inoculated with Rhizobium [राइजोबियम] and PSB @ 100 ml/10 kg of seed [बीज] before sowing [बुवाई]. Sowing [बुवाई] of soybean [सोयाबीन] should be avoided in the fields where soybean [सोयाबीन] seed production [बीज उत्पादन] was taken in the last summer season. Follow IPM package for the control of pests and diseases in soybean [सोयाबीन] as give below: - 1. Sowing [बुवाई] should be completed before 15’n July to avoid pest infestation [कीट प्रकोप]. 2. Seed treatment [बीज उपचार] of Thiram @2-3 g per kg or Trichoderma [ट्राइकोडर्मा] @5 g per kg of seed [बीज]. 3. Seed treatment [बीज उपचार] with Thiamethoxam 30 % @ 10 ml per kg of seed [बीज] for management of stem fly. ``` ---- **ICAR Kharif Agro-Advisories for Farmers** ``` Black gram [उड़द] The recommended seed rate [बीज दर] is 15-20 kg/ha with a spacing [अंतर] of 30×10 cm. Seeds should be treated with Trichoderma [ट्राइकोडर्मा] at 5 g/kg along with Rhizobium [राइजोबियम] and PSB at 25 g/kg each. Apply fertilizers at a rate of 20:40 kg N:P per hectare. Intercropping [अंतरफसल] with pigeon pea [अरहर] and other kharif crops [खरीफ फसलें] is advised for better resource utilization. Irrigation [सिंचाई] should be provided at critical stages such as flowering and pod [फली] filling to ensure healthy growth and yield [उत्पादन]. FRUIT & VEGETABLE CROPS Pomegranate [अनार] (Mrig Bahar) Pomegranate [अनार] cultivation during Mrig Bahar requires pruning [फ枝剪ाई] to remove diseased branches, followed by an application of 1% Bordeaux mix. Pre- flowering fertilization [फलधारण] includes 700 g urea [यूरिया], 1600 g SSP, and 400 g MOP per tree. Dusting with 4% copper [तांबा] dust or bleaching powder helps in disease [रोग] prevention. Regular pest control [कीट नियंत्रण] with Azadirachtin or alternate insecticides [कीटनाशक] every 15 days is crucial. At the fruiting stage, apply 500 g DAP + 100 g MOP per tree at the lemon [नींबू] size stage, and 200 g 19:19:19 + 100 g MOP at the guava [अमरूद] size stage. Maharashtra Grape After pruning [फ枝剪ाई], grapevines are treated with Hydrogen Cyanamide (30-40 ml/L) on the top 2-3 buds to encourage growth. GA sprays of 10 ppm are applied 17-18 days after pruning [फ枝剪ाई], followed by 15 ppm after 4-5 days. Mealybug [मैलिबग] control in September involves removing bark and spraying [छिड़काव] Methomyl 40 SP at 1 g/L Banana [केला] ``` ---- **ICAR Rabi Agro-Advisories for Farmers 2025** ``` For successful chickpea [चना] cultivation, farmers are advised to use high-yielding desi varieties like RVG-202, RVG-204, JG-16, JG-130, and JG-24, and for Kabuli types, varieties such as JGK-1, JGK-2, JGK-3, KAK-2, Shubhra, and Ujjwal are recommended. Sowing [बुवाई] should ideally be done between mid-October and mid-November using the ridge and furrow [मेढ़ और नाली] or raised bed [ऊँचा क्यारी] method to optimize water and seed [बीज] usage. Intercropping [अंतरफसल] with coriander [धनिया] or mustard [सरसों] with 8:2 ratios enhances resource use efficiency. The ideal spacing [अंतर] is 30×10 cm with a seed rate [बीज दर] of 75-80 kg/ha, increase the seed rate [बीज दर] by 25 kg/ha if sowing [बुवाई] is delayed beyond November 30. Before sowing [बुवाई], apply Trichoderma [ट्राइकोडर्मा] culture @ 5 kg/ha mixed with vermicompost [केंचुआ खाद] for wilt disease [मुरझाने की बीमारी] prevention. For seed treatment [बीज उपचार], use a combination of thiophanate-methyl + pyraclostrobin (2 ml), boron [बोरॉन] (1 g), molybdenum [मोलिब्डेनम] (1 g), Rhizobium [राइजोबियम] (8 g), and PSB culture (10 g)/kg of seed [बीज]. Alternatively, organic seed treatment [जैविक बीज उपचार] can be done with 5 g each of Trichoderma [ट्राइकोडर्मा], Rhizobium [राइजोबियम], and PSB @ 10 g/kg seed [बीज]. Nutrient application should include 15-20 kg N, 40 kg P₂O₅, 20 kg sulfur, 5 t of FYM, and 1 kg ammonium molybdate/ha. Though chickpea [चना] is largely a rainfed crop [फसल], irrigation [सिंचाई] at the branching stage and at pod [फली] formation significantly enhances yield [उत्पादन]. For weed management [खरपतवार प्रबंधन], apply pendimethalin (30% EC) @ 0.7-1.0 kg a.i. /ha within 48 hours of sowing [बुवाई], and follow up with one hand weeding [निराई] if needed. For pod borer [फली छेदक इल्ली] control, install 50 bird perches and 10 pheromone traps [फेरोमोन जाल] per hectare ``` ---- **ICAR Kharif Agro-Advisories for Farmers** ``` Banana [केला] In Kerala, banana [केला] cultivation during the Kharif season (June to September) begins with land preparation [भूमि तैयार करना] in May or early June. The land is ploughed or dug 2-3 times to loosen the soil [मिट्टी], and pits of size 60 x 60 x 60 cm or 45 x 45 x 45 cm are prepared. These pits are filled with topsoil mixed with 10-15 kg of farmyard manure [गोबर खाद] (FYM), 1 kg of neem cake [नीम खली], and wood ash or sand to improve soil fertility [मृदा उर्वरता] and drainage. Planting is typically done in June or July, using either healthy sword suckers or tissue-cultured plants. Common varieties cultivated during this season include Nendran, Robusta, Poovan, Grand Naine (G-9), and Red Banana [केला]. The spacing [अंतर] varies depending on the variety, with tall varieties planted at 2.5 x 2.5 m and dwarf or high-density types at 1.5 x 1.5 m or 1.8 x 1.8 m. Proper drainage is essential during the monsoon [मानसून] to prevent rhizome rot [राइजोम सड़न (तना सड़ना)]. Nutrient management [पोषक तत्व प्रबंधन] involves applying FYM at 10-20 kg per pit as a basal dose [प्रारंभिक मात्रा (उर्वरक की)]. Chemical fertilizers [रासायनिक उर्वरक] like nitrogen [नाइट्रोजन] (200 g), phosphorus [फॉस्फोरस] (60 g), and potassium [पोटाश] (200 g) per plant are applied in 3-4 splits at 1, 3, 5, and 7 months after planting. Foliar sprays of micronutrients [सूक्ष्म पोषक तत्व] such as zinc [जिंक], magnesium, and boron [बोरॉन] are also recommended. 122 Kerala Weed control [खरपतवार नियंत्रण] is achieved by mulching [मल्चिंग] with banana [केला] leaves or straw, which also helps in moisture conservation [नमी संरक्षण]. Intercropping [अंतरफसल] with legumes like cowpea [लोबिया] or groundnut [मूंगफली] is sometimes practiced. Drainage channels are constructed to avoid water stagnation [पानी का जमाव] during heavy rains. ``` ---- **ICAR Rabi Agro-Advisories for Farmers 2025** ``` ICAR Rabi Agro-Advisory [कृषि सलाह] 2025 aquaculture [जलीय कृषि], particularly shrimp farming [कृषि करना], also plays a significant role in supporting coastal livelihoods. Sustainable fishing practices such as avoiding juvenile catch, observing closed seasons, and using recommended mesh sizes are essential to conserve marine resources [समुद्री संसाधन]. Farmers engaged in aquaculture [जलीय कृषि] should adopt proper pond preparation, seed [बीज] stocking at optimal densities, regular water quality monitoring, and balanced feeding to maximize yield [उत्पादन] and profitability. Strengthening fish value chains through hygienic handling, cold storage [शीतगृह], and cooperative marketing can further enhance income opportunities for coastal communities. # WESTERN MAHARASHTRA (DESH REGION) &amp; KHANDESH REGION The Western Maharashtra (Desh region), comprising Pune, Satara, Sangli, Kolhapur, and Solapur districts &amp; Khandesh region, comprising Nashik, Dhule, Ahmednagar, Jalgaon &amp; Nandurbar Districts, Western Maharashtra receives moderate rainfall ranging from 500-900 mm annually. The soils here are predominantly black to medium black and well-drained, making them suitable for both field [खेत] and horticultural crops. Major crops grown in this region include cereals like sorghum [ज्वार] and wheat [गेहूं]; pulses such as chickpea [चना] and oilseeds like safflower [कुसुम] and linseed [अलसी]. Sugarcane [गन्ना] is an important commercial crop [फसल] widely cultivated in this zone. The region also excels in horticulture [उद्यानविद्या], producing high-value fruit crops such as pomegranate [अनार], banana [केला], and grapes [अंगूर], along with vegetables like onion [प्याज], tomato [टमाटर], and brinjal [बैंगन]. ## Cereal [अनाज] crops ### Sorghum [ज्वार] ``` [tool:search_terms] Matching Terms for `మధ్యపంటలు` Strip intercropping -> पट्टी पद्धति की अंतरफसल खेती (patti paddhati ki antarfasal kheti) [72%] Intervening crop -> मध्यवर्ती फसल (madhyavarti fasal) [70%] [tool:search_terms] Matching Terms for `కాలీఫ్లవర్` Cauliflower -> फूलगोभी (phoolgobhi) [90%] | M9: 1 | N9: 0 | O9: didn't provide required guidance for intercrop planning. And missed translation | P9: Completed | Q9: 1 | R9: Reject | S9: In QID 5-1, the response fails to provide required intercropping guidance for cauliflower in Buldhana, creating a major Accuracy/Completeness drop (4→1) between stages. The evaluator overlooked missing key information and failed to penalize Citation Accuracy and Translation Accuracy. This fundamental evaluation collapse requires a Score of 1 (Reject). Reject the review and perform a full re-evaluation across all affected rubric dimensions. | T9: updated
A10: 6 | B10: 6-1 | C10: బెంగళూరు మార్కెట్‌లో ఆపplesల ప్రస్తుత మార్కెట్ ధరలు ఏమిటి? | D10: బెంగళూరు మార్కెట్‌లో ఆపిల్ ధరలు ఈ విధంగా ఉన్నాయి: * **బెంగళూరు ఏ.పి.ఎం.సి — యార్డ్ ౧:** మోడల్ ధర ₹౭౫౫౫ ప్రతి క్వింటల్ (కనిష్ట: ₹౭౧౮౦, గరిష్ట: ₹౭౯౩౦). * **బెంగళూరు హోల్‌సేల్ హబ్:** మోడల్ ధర ₹౭౩౨౮ ప్రతి క్వింటల్ (కనిష్ట: ₹౬౮౨౧, గరిష్ట: ₹౭౮౫౦). ఈ ధరలు ౧౦ గంటల క్రితం నమోదయ్యాయి. **మూలం: మండి ధరలు** మీకు వేరే ఏదైనా పంట ధరల గురించి తెలుసుకోవాలా? | E10: 4 | F10: 1 | G10: 1 | H10: 1 | I10: 4 | J10: 3 | K10: 3 | L10: [tool:get_mandi_prices] **Mandi Price Discovery** [Today's Date: Monday, 25 May 2026] Commodity: Apple Market: Bangalore APMC — Yard 1 (mock), Bengaluru Urban, Karnataka Price: Rs./Quintal 7555 (Min: 7180, Max: 7930) 10 hours ago --- Commodity: Apple Market: Bangalore wholesale hub (mock), Bengaluru Urban, Karnataka Price: Rs./Quintal 7328 (Min: 6821, Max: 7850) 10 hours ago [tool:search_commodity] ### Commodity matches for `apples` | Commodity | Matched Term (Score) | Code | |---|---|---| | **Apple** | apple (92%) | `17` | | **Grapes** | grapes (80%) | `22` | | **Pineapple** | pineapple (76%) | `21` | | **Wood Apple** | wood apple (73%) | `428` | | **Water Apple** | water apple (70%) | `425` | [tool:forward_geocode] Bengaluru, Bangalore North, Karnataka, India (Latitude: 12.977, Longitude: 77.59) | M10: 0 | N10: 1 | O10: Number are and names are not translated completly, and incompleteness in response | P10: Completed | Q10: 1 | R10: Reject | S10: In QID 6-1, the response misinterprets 'apples' transliteration ('ఆపplesల') and leaves numerical market prices unformatted for low-literacy users. Stage 2 correctly flagged severe translation and formatting flaws affecting Accuracy/Completeness (4→3) and Translation Accuracy (4→2). This major multi-rubric evaluation conflict warrants a Score of 1 (Reject). Reject the review and re-evaluate all linguistic and accuracy rubrics. | T10: updated
A11: 7 | B11: 7-1 | C11: సాంగ్లీలో అల్లం పంటకు విత్తన పరిమాణం ఎంత? | D11: సాంగ్లీలో అల్లం పంటకు హెక్టారుకు ౧౮౦౦ నుండి ౨౦౦౦ కి.గ్రా విత్తన పరిమాణం అవసరమవుతుంది. మీరు సుప్రభ, సురుచి మరియు సురవి వంటి సరైన రకాలను ఎంచుకోవాలని సిఫార్సు చేయబడింది. **మూలం: ఐ.సి.ఎ.ఆర్. ఖరీఫ్ అగ్రో-అడ్వైజరీస్** అల్లం విత్తన శుద్ధి మరియు నాటడం గురించి మీకు మరిన్ని వివరాలు కావాలా? | E11: 3 | F11: 1 | G11: 1 | H11: 1 | I11: 2 | J11: 3 | K11: 3 | L11: [tool:search_documents] > Search Results for `seed rate for ginger crop in Sangli Maharashtra` **ICAR Kharif Agro-Advisories for Farmers** ``` 0.5 ml/L water for three hours before transplanting [पुनः रोपाई] may be followed for better control. Fruit fly [फलों की मक्खी] in cucurbits causes great losses which can be managed by use of food bait @100 ml/bait prepared by mixture of 1 kg cucumber [खीरा] fruit pulp + 50 g gur + 100 ml cow urine + 0.5 L water, diluted in 5 L water and added with 10 ml malathion along with installation of Pheromone trap [फेरोमोन जाल] with Cuelure @ 20 nos/ ha. Sucking insect [कीट] pest [कीट] are seen in many vegetable crops for which spraying [छिड़काव] of Thiamethoxam 25% WG @ 80 g or Acetamiprid 20 SP @ 125 ml/ha will keep the population under control. During rainy season, wilting is observed in solanaceous crops which can be controlled by spraying [छिड़काव] and soil drenching [मिट्टी में घोल डालना] with 3 g Copper [तांबा] oxycloride+1 g Plantomycin per litre of water. SPICE CROPS Turmeric [हल्दी] Suitable varieties are Roma, Rashmi, Lakadong, Rajendra Sonia. Treat the rhizome [कंद] with Trichoderma [ट्राइकोडर्मा] viridae @ 10 g/kg of seed [बीज] to save the crop [फसल] from diseases. Apply bio-consortia (Azotobacter, Azospirillum & PSB) @ 12 kg/ha mixed with FYM at the time of planting for improving germination [अंकुरण] and productivity. Ginger [अदरक] Cultivate suitable ginger [अदरक] varieties- Suprabha, Suruchi and Suravi with seed rate [बीज दर] of 1800-2000 kg/ha. Select high loamy land for cultivation. Raised bed [ऊँचा क्यारी] of size 1 m width, 15 cm height and of convenient length may be adopted along with making channels for draining excess rain water. Before sowing [बुवाई] dip rhizomes in a slurry [द्रव और उसमें निलंबित ठोस पदार्थों का मिश्रण] of 1 g Carbendazim, 3 g Mancozeb and 1 g Plantomycin for half an hour and dry in the shade. Banana [केला] ``` ---- **ICAR Rabi Agro-Advisories for Farmers 2025** ``` ICAR Rabi Agro-Advisory [कृषि सलाह] 2025 aquaculture [जलीय कृषि], particularly shrimp farming [कृषि करना], also plays a significant role in supporting coastal livelihoods. Sustainable fishing practices such as avoiding juvenile catch, observing closed seasons, and using recommended mesh sizes are essential to conserve marine resources [समुद्री संसाधन]. Farmers engaged in aquaculture [जलीय कृषि] should adopt proper pond preparation, seed [बीज] stocking at optimal densities, regular water quality monitoring, and balanced feeding to maximize yield [उत्पादन] and profitability. Strengthening fish value chains through hygienic handling, cold storage [शीतगृह], and cooperative marketing can further enhance income opportunities for coastal communities. # WESTERN MAHARASHTRA (DESH REGION) &amp; KHANDESH REGION The Western Maharashtra (Desh region), comprising Pune, Satara, Sangli, Kolhapur, and Solapur districts &amp; Khandesh region, comprising Nashik, Dhule, Ahmednagar, Jalgaon &amp; Nandurbar Districts, Western Maharashtra receives moderate rainfall ranging from 500-900 mm annually. The soils here are predominantly black to medium black and well-drained, making them suitable for both field [खेत] and horticultural crops. Major crops grown in this region include cereals like sorghum [ज्वार] and wheat [गेहूं]; pulses such as chickpea [चना] and oilseeds like safflower [कुसुम] and linseed [अलसी]. Sugarcane [गन्ना] is an important commercial crop [फसल] widely cultivated in this zone. The region also excels in horticulture [उद्यानविद्या], producing high-value fruit crops such as pomegranate [अनार], banana [केला], and grapes [अंगूर], along with vegetables like onion [प्याज], tomato [टमाटर], and brinjal [बैंगन]. ## Cereal [अनाज] crops ### Sorghum [ज्वार] ``` ---- **ICAR Kharif Agro-Advisories for Farmers** ``` 163 ICAR Kharif Agro-Advisory [कृषि सलाह] 2025 60 kg N, 30 kg P₂O₅, and 30 kg K₂O per hectare for optimal crop nutrition [फसल पोषण]. Millets can be intercropped with soybean [सोयाबीन]. Conduct three hoeings with a hand hoe [खुरपी] during early growth stages for eﬀective weed suppression. Spray Mancozeb (0.2%) at early crop [फसल] stages if Blast [झुलसा], Brown Spot, or Rust [गेरू रोग] symptoms appear. Rogue out diseased plants to manage spread and for armyworms, cutworms, and leaf-scraping beetles, apply Thiamethoxam @ 5 g/15 litres of water for eﬀective protection. PULSE [दाल] CROPS Blackgram Conduct deep summer ploughing [जुताई] to expose and destroy the eggs, larvae, and pupae of major pests like pod borer [फली छेदक इल्ली], c a t e r p i l l a r s , a n d w e e v i l s . M i x FYM/compost [कम्पोस्ट] into the soil [मिट्टी] 10-15 days before sowing [बुवाई]. Ensure the field [खेत] is free from weeds [खरपतवार] for optimal crop [फसल] growth. Use high-yielding varieties like PU 31 and LBG-20 (Teja). PU 31 is tolerant to Yellow Mosaic Virus [पीला मोज़ेक विषाणु रोग] (YMV) and well- suited for Kharif cultivation, while LBG- Varietal demonstration in blackgram 20 performs well in all seasons. Use a seed rate [बीज दर] of 10-15 kg/ha (or 2.5-3.75 kg/sangam). Sowing [बुवाई] can be done by broadcasting or dibbling [छिद्र बोवाई विधि] at a spacing [अंतर] of 15 cm ``` ---- **ICAR Kharif Agro-Advisories for Farmers** ``` For weed management [खरपतवार प्रबंधन], Pendimethalin is applied pre-emergence [अंकुरण] and Imazethapyr post-emergence [अंकुरण], along with hand weeding [निराई] at 20 and 40 days after sowing [बुवाई] (DAS). To manage sucking pests, seed treatment [बीज उपचार] with Imidacloprid is eﬀective, while collar rot [मूल तना सड़न] can be controlled by treating seeds with Fluxapyroxad or a combination of Carboxin and Thiram. In case of defoliator infestation, spraying [छिड़काव] Indoxacarb, Lambda- cyhalothrin, or a Novaluron mixture is recommended. For rust [गेरू रोग] and leaf spot [पत्तियों पर धब्बे] diseases, fungicides [फफूंदनाशी दवाएँ] like Hexaconazole or Pyraclostrobin should be applied. Additionally, 75% of the recommended dose of fertilizers (RDF) should be supplemented with 25 kg/ha of Mycorrhiza [मायकोराइजा] and Rhizobium [राइजोबियम] seed treatment [बीज उपचार] to enhance soil health [मृदा स्वास्थ्य] and crop productivity [फसल उत्पादकता]. Cotton [कपास] (Bt & Desi) Cotton [कपास] cultivation thrives best in well-drained loamy to sandy loam soils. Prior to sowing [बुवाई], deep ploughing [गहरी जुताई] is essential along with the incorporation of 10-15 t/ha of farmyard manure [गोबर खाद] (FYM) to enhance soil fertility [मृदा उर्वरता]. Sowing [बुवाई] is typically carried out in June- July under rainfed conditions and during April-May for irrigated crops. Recommended spacing [अंतर] for normal planting is 90-120 × 30-45 cm, while under high-density planting [उच्च घनता रोपण] (HDP) systems, 60 × 30 cm spacing [अंतर] is advised. Suitable varieties include Bt hybrids like G. Cot. Hy. 24 and 26, and desi types such as GADC-3 and GADC-4. The seed rate [बीज दर] varies by type, with 1.5-2 kg/ha for Bt varieties and 10-12 kg/ha for desi types. Gujarat ``` ---- **ICAR Kharif Agro-Advisories for Farmers** ``` Buffalo Allow buffalo for wallowing in water as they have fewer sweet glands compared to cattle to maintain their body's thermo-equilibrium. Water-soaked gunny bag or other cloth should kept on a body to avoid occurrence of heat stroke. Goat Animals should be vaccinated before monsoon [मानसून] season for Enterotoxaemia and Peste des petes (PPR) ruminants' diseases to avoid great losses. Improved breeds like Osmanabadi should be used for higher income. Regular deworming should be done after every month to goat kids for six months for good health and weight gain. Poultry [पोल्ट्री पालन] In the summer the poultry [पोल्ट्री पालन] shed should be kept cool. Plants more trees around the shed. The roof of the shed should be covered with grass, so that the temperature [तापमान] remains under control. Exhaust fan should be kept in the shed, so that the hot air inside shed is thrown out. Use foggers, so the shade will cool down. Improved backyard poultry [पोल्ट्री पालन] breeds like Grampriya, Shrinidhi, Kaveri, Giriraja and Vanaraja should be used to boost up the income of small and marginal farmers. WESTERN MAHARASHTRA Western Maharashtra is comprised of Ahmednagar, Pune, Satara, Sangli, Kolhapur, Solapur. The region has moderate rainfall and Black to medium black, well-drained soils. This region has state agricultural university viz., Mahatma Phule Krishi Vidyapeeth, Rahuri, Ahmednagar. CEREAL [अनाज] CROPS Rice [चावल] In Western Maharashtra, nursery [नर्सरी] sowing [बुवाई] for Kharif rice [चावल] generally begins in late May to mid-June, aligning with the onset of monsoon [मानसून]. Recommended varieties include Phule Radha, Indrayani, Sahyadri, and Kolhapur-1, chosen for local adaptability and consumer preference. About 40-50 kg of seed [बीज] per hectare of main field [खेत] is required for a nursery [नर्सरी] area of 800-1000 m². Seeds are soaked in water for 24 hours, then incubated for another 24-36 hours to promote uniform germination [अंकुरण]. Treat seeds Maharashtra ``` ---- **ICAR Kharif Agro-Advisories for Farmers** ``` SPICE CROPS Ginger [अदरक] and Turmeric [हल्दी] Farmers are advised to complete the sowing [बुवाई] of ginger [अदरक] (variety Nadia) and turmeric [हल्दी] (varieties Megha Turmeric [हल्दी] 1 or Lakadong) without delay. Use a seed rate [बीज दर] of 15-20 169 ICAR Kharif Agro-Advisory [कृषि सलाह] 2025 quintals per hectare and maintain a spacing [अंतर] of 30 cm × 30 cm. Before sowing [बुवाई], treat rhizome [कंद] seeds by dipping them in a solution of Trichoderma [ट्राइकोडर्मा] viride @ 4 g/litre of water for 5 minutes or Trichoderma [ट्राइकोडर्मा] harzianum @ 10 ml/litre to prevent rhizome rot [राइजोम सड़न (तना सड़ना)]. For already sown crops, carry out proper weeding [निराई करना] and earthing up [मिट्टी चढ़ाना] to promote healthy growth. Ensure planting in ridges and furrows with good drainage. Farmers may also opt for intercropping [अंतरफसल] with crops like soybean [सोयाबीन], rice [चावल] bean, French bean, finger millet [रागी], or maize [मक्का] for better resource use and income diversification. To conserve soil moisture [मिट्टी की नमी] and control weeds [खरपतवार], mulch the beds using dry paddy straw or green leaves. For eﬀective disease management [रोग प्रबंधन], especially soft rot, spray Trichoderma [ट्राइकोडर्मा] viride or Trichoderma [ट्राइकोडर्मा] harzianum @ 10 ml/litre or neem oil [नीम का तेल] (10,000 ppm) @ 2 ml/litre as a preventive measure. LIVESTOCK [पशुधन] Piggery ``` ---- **ICAR Rabi Agro-Advisories for Farmers 2025** ``` . Pusa 209, GNG 1969, KAK-2, Shubhra, Ujjaval, and Pusa 256 are the Kabuli type varieties. For late sowing [बुवाई]: GNG 2144 (Teej) and GNG 1488 (Sangam) are Kabuli-type varieties. Desi varieties require 70-80 kg/ha and Kabuli 80-90 kg/ha for sowing [बुवाई]. For late sowing [बुवाई], use 90-100?kg/ha, and for utera cropping, 100-120 kg/ha. Small-seeded variety 50-60 kg, medium 60-70 kg, Kabuli/bold-seeded 80-90 kg, and extra bold-seeded 100-110 kg seed [बीज] should be used. Apply 8-10 t/ha well-decomposed FYM every three years to enhance soil fertility [मृदा उर्वरता]. ``` ---- **ICAR Kharif Agro-Advisories for Farmers** ``` KHANDESH/ NORTHERN MAHARASHTRA This region of Maharashtra is comprised of Jalgaon, Dhule, Nandurbar, Nashik). Rainfall of the region is 600-900 mm and it has Medium to deep black soils. This region has state agricultural university viz., Mahatma Phule Krishi Vidyapeeth, Rahuri, Ahmednagar (M.S) COMMERCIAL CROPS Cotton [कपास] Use medium to deep black cotton [कपास] soils with good drainage for optimal crop [फसल] performance. Prepare land with 1-2 deep ploughings followed by harrowing [सुरकी चलाना]; adopt ridge [मेड़]-furrow [मेड़] or broad bed-furrow [मेड़] method. Treat seeds with Trichoderma [ट्राइकोडर्मा] viride or Carbendazim for fungal diseases and imidacloprid for sucking pest [रस चूसने वाले कीट] protection. Sow Bt cotton [बीटी कपास] hybrids like RCH-2 BG II or NCS-855 BG II from mid-June to early July, depending on monsoon [मानसून] onset. Maintain spacing [अंतर] of 120 × 60 cm for hybrids and 90 × 45 cm for varieties; use seed rate [बीज दर] of 450-500 g/acre. Apply basal dose [प्रारंभिक मात्रा (उर्वरक की)] of NPK @ 50:25:25 kg/ha based on soil test [मृदा परीक्षण]; supplement with FYM @ 5-10 t/ha. Apply zinc sulphate [जिंक सल्फेट] @ 25 kg/ha in zinc [जिंक]-deficient soils. Ensure field [खेत] has proper drainage to prevent waterlogging [पानी भराव], especially during early growth stages. Provide protective irrigation [संरक्षण सिंचाई] during long dry spells, particularly during flowering and boll development. Apply Pendimethalin @ 1.0 kg a.i./ha as pre-emergence herbicide [अंकुरण पूर्व खरपतवारनाशी]; ICAR Kharif Agro-Advisory [कृषि सलाह] 2025 follow with hand weeding [निराई] at 20-25 DAS. Monitor for sucking pests (jassids, aphids, whiteflies); control using imidacloprid 0.3 ml/l or thiamethoxam 0.25 g/l. ``` ---- **ICAR Kharif Agro-Advisories for Farmers** ``` Ginger [अदरक] Cultivate suitable ginger [अदरक] varieties- Suprabha, Suruchi and Suravi with seed rate [बीज दर] of 1800-2000 kg/ha. Select high loamy land for cultivation. Raised bed [ऊँचा क्यारी] of size 1 m width, 15 cm height and of convenient length may be adopted along with making channels for draining excess rain water. Before sowing [बुवाई] dip rhizomes in a slurry [द्रव और उसमें निलंबित ठोस पदार्थों का मिश्रण] of 1 g Carbendazim, 3 g Mancozeb and 1 g Plantomycin for half an hour and dry in the shade. Banana [केला] Banana [केला] crop [फसल] should be planted during June with receipt of rain. Tissue culture [ऊतक संवर्धन] plants and high- density planting may be followed for banana [केला] cultivation for higher productivity. In bearing plants of coconut [नारियल], make circular pit of 30 cm deep 3 ft away from the trunk, apply 60 kg compost [कम्पोस्ट], 500 g urea [यूरिया], 1 kg SSP/300 g of DAP, 1 kg MOP and 200 g borax [बोरैक्स] per bearing plant in the pit and cover with soil [मिट्टी]. LIVESTOCK [पशुधन] Don't allow domestic animals to graze outside during 11 PM to 3 PM as ambient temperature [तापमान] remains high this time. Provide sufficient clean drinking water to cattle and keep their sheds clean. Provide vaccination at regular interval. Cultivate and 189 ICAR Kharif Agro-Advisory [कृषि सलाह] 2025 supplement azolla @ 1-1.5 kg in daily ration of cattle to reduce the feed cost by 20%. Provide supplementary feeding such as broken rice [चावल], paddy, cooked rice [चावल], azolla etc. to the backyard poultry [पोल्ट्री पालन] birds during continuous rain. It is preferable to expose the feed ingredient sacks/bags under sun every week to prevent the feeds getting more moisture. Wash the cattle shed with phenyl (dilution 1:20 ratio with water) and sprinkle bleaching powder around the shed at weekly intervals. Mastitis is a common problem in high yielding cows in rainy season. Keep the cattle shed clean and dry. Clean the udder in soap water daily before milking. Apply Mastilep® ointment over the udder after each milking. ``` ---- **ICAR Kharif Agro-Advisories for Farmers** ``` VEGETABLE CROPS Farmers are advised to prepare the vegetable nursery [नर्सरी] for crops such as cucumber [खीरा], bitter gourd [करेला], ridge gourd [तोरी], bottle gourd [लौकी], chilli [मिर्च], brinjal [बैंगन], and okra [भिंडी] on raised bamboo structures, covering them with polythene to protect seedlings from heavy rain and hailstorms. Planting should be done in ridges and furrows with proper drainage channels to prevent waterlogging [पानी भराव]. It is essential to add farmyard manure [गोबर खाद] (FYM) or vermi- In-situ moisture conservation [स्थल पर नमी संरक्षण] in cabbage [पत्ता गोभी] compost [कम्पोस्ट] in the nursery [नर्सरी] for healthy seedling growth [पौधों की वृद्धि]. To conserve soil moisture [मिट्टी की नमी], prevent soil erosion [मिट्टी का कटाव], and control weeds [खरपतवार], mulching [मल्चिंग] with locally available materials like paddy straw is recommended. Farmers can also make their own compost [कम्पोस्ट] using the 18-day compost [कम्पोस्ट] method, pit method [सिचाई], or by producing vermicompost [केंचुआ खाद] to meet their manure [खाद] requirements. For pest management [कीट प्रबंधन], it is advised to make biopesticides [जैव कीटनाशी] using locally available materials such as leaves, garlic [लहसुन], and tobacco [तंबाकू]. For crops under protected cultivation, including high-value crops, frequent irrigation [सिंचाई] should be provided at 10-15 day intervals, based on the weather [मौसम] conditions. SPICE CROPS Ginger [अदरक] and Turmeric [हल्दी] Farmers are advised to complete the sowing [बुवाई] of ginger [अदरक] (variety Nadia) and turmeric [हल्दी] (varieties Megha Turmeric [हल्दी] 1 or Lakadong) without delay. Use a seed rate [बीज दर] of 15-20 169 ICAR Kharif Agro-Advisory [कृषि सलाह] 2025 ``` [tool:search_terms] Matching Terms for `అల్లం` Ginger -> अदरक (adrak) [80%] Ginger Shoot -> अदरक की कोंप (adrak ki komp) [71%] | M11: 1 | N11: 1 | O11: Number are and names are not translated completly, and incompleteness in response | P11: Completed | Q11: 2 | R11: Needs Re-evaluation | S11: In QID 7-1, regarding ginger seed quantity in Sangli, the response provides raw numerical values without necessary explanatory context or proper Telugu numeral translation. Stage 2 flagged the unreadable number formatting, leading to a Citation Accuracy flip (1→0). This scoring conflict necessitates a Score of 2 (Needs Re-evaluation). Re-evaluate Citation Accuracy and Translation Accuracy. | T11: updated
A12: 8 | B12: 8-1 | C12: కొచ్చి మార్కెట్‌లో ఆపిల్స్ ప్రస్తుత మార్కెట్ ధర ఎంత? | D12: కొచ్చి మార్కెట్‌లో ఆపిల్స్ ధరలు ఈ విధంగా ఉన్నాయి: * **కొచ్చి ఏ.పి.ఎం.సి (యార్డ్ ౧):** మోడల్ ధర ₹౫౦౩౬ ప్రతి క్వింటల్ (కనిష్ట: ₹౪౭౮౦, గరిష్ట: ₹౫౨౯౨). * **కొచ్చి హోల్ సేల్ హబ్:** మోడల్ ధర ₹౪౮౮౪ ప్రతి క్వింటల్ (కనిష్ట: ₹౪౫౪౧, గరిష్ట: ₹౫౨౩౯). ఈ ధరలు ౧౦ గంటల క్రితం నమోదయ్యాయి. **మూలం: మండి ధరలు** మీకు వేరే పంట ధరల గురించి సమాచారం కావాలా? | E12: 3 | F12: 1 | G12: 1 | H12: 1 | I12: 3 | J12: 3 | K12: 3 | L12: [tool:get_mandi_prices] **Mandi Price Discovery** [Today's Date: Monday, 25 May 2026] Commodity: Apple Market: Kochi APMC — Yard 1 (mock), Ernakulam, Kerala Price: Rs./Quintal 5036 (Min: 4780, Max: 5292) 10 hours ago --- Commodity: Apple Market: Kochi wholesale hub (mock), Ernakulam, Kerala Price: Rs./Quintal 4884 (Min: 4541, Max: 5239) 10 hours ago [tool:search_commodity] ### Commodity matches for `Apple` | Commodity | Matched Term (Score) | Code | |---|---|---| | **Apple** | apple (100%) | `17` | | **Pineapple** | pineapple (78%) | `21` | | **Coffee** | kappi (75%) | `41` | | **Ox** | kaale (75%) | `172` | | **Wood Apple** | wood apple (75%) | `428` | [tool:forward_geocode] Kochi, Kerala, India (Latitude: 9.968, Longitude: 76.244) | M12: 0 | N12: 1 | O12: Number are and names are not translated completly, and incompleteness in response | P12: Completed | Q12: 1 | R12: Reject | S12: In QID 8-1, the model response introduces an extra ungrounded market ('Kochi APMC Yard 1') and leaves numbers untranslated. Stage 2 correctly identified the untranslated numerals and hallucinated market, creating a severe scoring contradiction across stages. A Score of 1 (Reject) is necessary due to this unaddressed hallucination. Reject the review and re-evaluate No Fabrication and Citation Accuracy. | T12: updated
A13: 9 | B13: 9-1 | C13: బీడ్‌లో గోధుమ పంటలో కాండం తొలుచు పురుగు నియంత్రణకు ఏ రసాయన పురుగుమందు సూచించాలి? | D13: గోధుమ పంటలో కాండం తొలుచు పురుగు (Pink stem borer) తీవ్రత ఎక్కువగా ఉన్నప్పుడు, ఈ క్రింది రసాయన పురుగుమందులను ఉపయోగించవచ్చు: * **క్లోర్పైరిఫాస్ ౨౦% ఇ.సి. (Chlorpyriphos ౨౦% EC):** హెక్టారుకు ౨.౫ లీటర్లు. * **క్లోరాంట్రానిలిప్రోల్ ౧౮.౫% ఎస్.సి. (Chlorantraniliprole ౧౮.౫% SC):** హెక్టారుకు ౧౨౫ మి.లీ. * **ఫిప్రోనిల్ ౦.౩% జి.ఆర్. (Fipronil ౦.౩% GR):** హెక్టారుకు ౧౭.౫ కి.గ్రా. (దీనిని ౧౨౫ కి.గ్రా. ఇసుక లేదా మట్టితో కలిపి తేమగా ఉన్న పొలంలో చల్లాలి). **మూలం: జాతీయ పురుగు నిఘా వ్యవస్థ (NPSS)** మీ పంటలో పురుగు తీవ్రత ఏ స్థాయిలో ఉంది? | E13: 4 | F13: 1 | G13: 1 | H13: 1 | I13: 3 | J13: 4 | K13: 4 | L13: [tool:search_pests_diseases] > Pests & Diseases Search Results for `wheat stem borer control chemical pesticide` **NPSS Pest Advisory** ``` # Wheat [गेहूं] - Pink stem borer [तना छेदक] (Insect [कीट]) **Description**: Adult wingspan is about 28 mm. Hindwings with veins 3 and 4 from arise from the cell. Antennae of male ciliated and simple in female. Body ochreous. Forewings with a red-brown suffusion along median nervure and veins 2 to 5. A sub-marginal dark line present. Cilia paler. Hindwings are whitish. Larva smooth and shiny and lack obvious hairs or markings. Color variable but usually cream white with a distinctive pink suffusion. The head and prothoracic shield are brown. The dorsal part of the last abdominal segment bearing the anus is yellowish brown. Mature larvae are between 3040 mm long, pink with buff and pink dorsal markings and a brown head. Life cycle is completed in about 40-70 days, depending upon the climatic conditions. There are 4-6 generations in a year. The eggs are laid in clusters in several rows within the cover of the leave sheath. The eggs are rounded, pale and yellowish green in colour. The larvae after hatching bore into the stem and feed upon the tissues of the stem. A fully grown caterpillar is cylindrical with its head red-brown in colour and measures 20-25 mm in length. It pupates inside the stem itself. The egg stage lasts for about 7-10 days, larvae for 20-30 days and pupal stage for 8-10 days. The damage to the wheat [गेहूं] crop [फसल] is mainly caused by the caterpillars. The caterpillars bores into the stem and feed upon the tissues of the central shoot. The infected plant produces dead hert or white ear heads. ## Infestation Levels **Low**: Cultivate Resistant Varieties [प्रतिरोधी किस्में]. Balance use of fertilizer [उर्वरक] minimize the incidence of stem borer [तना छेदक]. The infected wheat [गेहूं] plant should be uprooted and destroyed. Install Bird Perches @10/acre to facilitate higher visit of predatory birds. Use of light [प्रकाश] traps [फंदे] for specific hours during evening time. Conserve or release Telenomeus spp and Trichogramma [ट्राइकोग्रामा] minutum @ 20,000/ha during egg stage, Apanteles flavipes, Bracon chinensis and Sturmiopsis inferens on larval population and Xanthopinpla spp and Tetrastichus aygari during pupal stage for effective biological control [जैव नियंत्रण]. Use 8-10 No's Pheromone Traps [फेरोमोन जाल] per acre. Install within 1-week crop [फसल] stage to control pest [कीट] at early stage. Trap canopy [पर्णछाया] should be placed one feet above crop canopy [फसल छत्र] to achieve optimum catch. **Medium**: Balance use of fertilizer [उर्वरक] minimize the incidence of stem borer [तना छेदक]. The infected wheat [गेहूं] plant should be uprooted and destroyed. Use of light [प्रकाश] traps [फंदे] for specific hours during evening time. Conserve or release Telenomeus spp and Trichogramma [ट्राइकोग्रामा] minutum @ 20,000/ha during egg stage, Apanteles flavipes, Bracon chinensis and Sturmiopsis inferens on larval population and Xanthopinpla sps and Tetrastichus aygari during pupal stage for effective biological control [जैव नियंत्रण]. Use 8-10 No's Pheromone Traps [फेरोमोन जाल] per acre. Use of entomopathogenic fungi [कीटनाशी फफूंदी] like M. anisopliae and B. bassiana @ 1 ml/ 30 larva useful. **High**: Conserve or release Telenomeus spp and Trichogramma [ट्राइकोग्रामा] minutum on egg stage, Apanteles flavipes, Bracon chinensis and Sturmiopsis inferens on larval population and Xanthopinpla spp and Tetrastichus aygari during pupal stage for effective biological control [जैव नियंत्रण]. Chlorpyriphos 20% EC @ 2.5l/ha, Chlorantraniliprole 18.5% SC @ 125ml/ha, Fipronil 0.3% GR @ 17.5kg/ha. mixed with 125kg. of sand / soil [मिट्टी] & apply (broadcast) in moist wheat [गेहूं] field [खेत]. ``` ---- **NPSS Pest Advisory** ``` # Wheat [गेहूं] - Shoot fly [तना मक्खी] (Insect [कीट]) **Description**: Eggs: The eggs hatch in 1 - 3 days and the maggots which are yellow in colour migrate to the dorsal surface of the leaf, enter the space between the leaf sheath [पत्ते का आवरण] and the axis and make a clean cut at the base of the leaf. The growing point of the plant dies and decays on which the maggots feed.  Larvae: The larval period lasts for 6 - 10 days.  Pupae: Pupation takes place inside the stem itself and the adults emerge in about a week.  Adults: The adult is a small dark fly. It deposits whitish eggs singly on the central surface of the leaves. Each female fly is capable of laying 30 eggs during its life time. Life cycle occupies 17 - 20 days. The adult fly lays white eggs on the leaves, and the eggs hatch in 1–3 days. The maggots then move down the leaves and cut the growing point of the plant, causing the central shoot to dry out. This is known as the dead heart symptom. The larvae develop for 6–10 days, and then pupate inside the stem. The adults emerge after about a week ## Infestation Levels **Low**: Conserve natural enemies [प्राकृतिक शत्रु].Regular field monitoring [क्षेत्र निरीक्षण] & pest [कीट] & defender population, barrier crops like mustard [सरसों] crop [फसल] around the field [खेत].  Plant tall border crops like maize [मक्का], sorghum [ज्वार] or millet [मोटा अनाज] to reduce pest [कीट] population.  For monitoring fish meal traps [फंदे] can be used. **Medium**: Conserve natural enemies [प्राकृतिक शत्रु].Regular field monitoring [क्षेत्र निरीक्षण] & pest [कीट] & defender population, barrier crops like mustard [सरसों] crop [फसल] around the field [खेत].  Plant tall border crops like maize [मक्का], sorghum [ज्वार] or millet [मोटा अनाज] to reduce pest [कीट] population. Balance use of fertilizer [उर्वरक] minimize the incidence of shoot fly [तना मक्खी]. The infected wheat [गेहूं] plant should be uprooted and destroyed. Use of light [प्रकाश] traps [फंदे] for specific hours during evening time. **High**: Apply of Cypermethrin 10 % EC@ 0.68 to 1.1 ml/lit of water (waiting period of 14 days) , ``` ---- **NPSS Pest Advisory** ``` # Wheat [गेहूं] - Army worm/cut worm (Insect [कीट]) **Description**: The wingspan is 35–50 mm. The forewings are greyish yellow with a dark-grey or reddish-yellow tinge. The round and reniform spots are light [प्रकाश] or yellowish with indistinct edges, whereas reniform spot with white point at lower margin. External wing margin blackened obliquely from top backward, with dark stroke and with a row of dark points. Hindwings are grey, with dark external margin. Antennae thread like. Eggs are spherical and milky white with a thinly reticulate surface. Larvae usually have six instars, rarely seven. It reaching 40 mm in length at its last instar. Larva has two wide black-brown and one intermediate light [प्रकाश] dorsal stripe, with black-brown lateral stripe along spiracle line. spiracles brown with black rim. Pupae are yellowish brown and shiny. ## Infestation Levels **Low**: Remove weeds [खरपतवार] and stubbles after harvesting. Avoid green manure [हरित खाद] and apply FYM to prevent cutworm [कटवर्म कीट] egg laying **Medium**: Remove weeds [खरपतवार] and stubbles after harvesting. Avoid green manure [हरित खाद] and apply FYM to prevent cutworm [कटवर्म कीट] egg laying and Pheromone traps [फेरोमोन जाल] @ 4-5/acre can be installed for monitoring fruit borer [फल बेधक कीट] activity. Replace the lures with fresh lures after every 20-25 day interval. ETL for fruit borer [फल बेधक कीट] is 8 to10 moths /day/trap.  Bird perches @ 10/ acre should be erected for facilitating field [खेत] visits of predatory birds **High**: Use of CIB&RC approved label claim pesticides ``` ---- **NPSS Pest Advisory** ``` # Potato [आलू] - Thrips [फूलकीड़े] (Insect [कीट]) **Description**: Thrips [फूलकीड़े] are very small, have elongated abdomens and are yellowish or blackish in color. They are often found on potato [आलू] plants throughout all growth stages, from sprout [अंकुर] development to tuber [कंद] maturation. Thrips [फूलकीड़े] reproduce by laying eggs. Nymphs emerge from the eggs. It takes between 7 and 12 days to develop from eggs into adult thrips [फूलकीड़े]. ## Infestation Levels **Low**: Light [प्रकाश] traps [फंदे]: Set up light trap [प्रकाश फंदा] @ 1 trap/acre 15 cm above the crop canopy [फसल छत्र] for monitoring and mass trapping [सामूहिक फंदा] insects. Light [प्रकाश] traps [फंदे] with exit option for natural enemies [प्राकृतिक शत्रु] of smaller size should be installed and operate around the dusk time **Medium**: Spray NSKE 5%. Release 1st instar larvae of green lacewing (Chrysoperla carnea) @ 4,000/acre Conserve parasitoids such as Aphidius colemani, Diaeretiella spp., Aphelinus spp. etc. Conserve predators such as ladybird beetle. **High**: Apply carbofuran [कार्बोफ्यूरान] 3% CG @ 6.64 Kg/ acre or oxydemetonmethyl 25% EC @ 0.4 l in 200- 400 l of water/acre. Thiamethoxam 25% WG @ 40 g in 200 l of water/acre. Soil drenching [मिट्टी में घोल डालना] of thiamethoxam 25% WG @ 80 g in 200 l water/ acre for aphid control [मावा नियंत्रण]. Spray carbofuran [कार्बोफ्यूरान] 3% CG @1.328 Kg/ acre for controlling leaf hopper [पत्तों का तेला]. Spray dimethoate 30% EC @ 264 ml in 200- 400 l water/acre for controlling thrips [फूलकीड़े]. Cyantraniliprole 10.26% OD @ 360 ml in 200 l water/acre. ``` ---- **NPSS Pest Advisory** ``` # Tomato [टमाटर] - Sooty mold [काजळीदार फफूंदी] (Disease [रोग]) **Description**: It is a fungal disease [फफूंदजनित रोग] developed on honeydew-like excretion secreted by aphids and scale insects. The fungus slowly covers the entire leaf area severely affecting the process of photosynthesis [प्रकाश संश्लेषण]. This results in reduced translocation [स्थानांतरण] of food to the fruits, which leads to reduction in their size. ## Infestation Levels **Low**: Spray starch solution 5% to remove the fungal growth. **Medium**: Spray starch solution 5% to remove the fungal growth. Control insects by spraying [छिड़काव] systemic insecticides [कीटनाशक]. **High**: Spray starch solution 5% to remove the fungal growth. Control insects by spraying [छिड़काव] systemic insecticides [कीटनाशक]. ``` ---- **NPSS Pest Advisory** ``` # Urad bean (Black gram [उड़द]) - Beet Armyworm [सेना की इल्ली] (Insect [कीट]) **Description**: The adult is a drab brown or grey moth with a wingspan of 2632 millimetres (11+14 in). Forewing is greyish ochreous in color, washed with dull yellow and sprinkled with black scales. Inner and outer lines are double, indistinct, filled in with pale yellowish color. A dark waved median shade visible before lower half of outer line. Cell is dark brown. Orbicular stigma [वर्तिकाग्र] is pale or bright yellow, and round, whereas reniform has a curved brown lunule in centre. The submarginal line is pale grey. There is the darker shade preceding it with dark streaks between the veins. Terminal spots are black. Hindwings semihyaline are white, with the veins dark brown. All three margins are shaded with fuscous color. Larvae are pinkish brown, clotted with black. Spiracular line pale ochreous, with dark upper edge. They are greenish-brown cutworms, soft and bulging caterpillars with dark longitudinal stripes. ## Infestation Levels **Low**: Pheromone traps [फेरोमोन जाल] and mechanical hand picking of adults and caterpillars are extensively used. Parasitoids such as Chelonus insularis, Cotesia marginiventris, Meteorus autographae, Lespesia archippivora lay eggs on the caterpillars, and their larvae feed and emerge. Predators like Orius sp., Geocoris sp., Nabis sp., Podisus maculiventris are also effective controlling measures. Pupal stages can be eliminated by introducing Solenopsis invicta to the field [खेत]. Apart from biological control [जैव नियंत्रण], many chemical pesticides [रासायनिक कीटनाशक] are extensively used. Larvae are susceptible to neem products. Eggs can be killed by using petroleum oil concentrations. Applying cottonseed oil to leaves can eliminate both eggs and larvae. (NBAIR) **Medium**: Pheromone traps [फेरोमोन जाल] and mechanical hand picking of adults and caterpillars are extensively used. Parasitoids such as Chelonus insularis, Cotesia marginiventris, Meteorus autographae, Lespesia archippivora lay eggs on the caterpillars, and their larvae feed and emerge. Predators like Orius sp., Geocoris sp., Nabis sp., Podisus maculiventris are also effective controlling measures. Pupal stages can be eliminated by introducing Solenopsis invicta to the field [खेत]. Apart from biological control [जैव नियंत्रण], many chemical pesticides [रासायनिक कीटनाशक] are extensively used. Larvae are susceptible to neem products. Eggs can be killed by using petroleum oil concentrations. Applying cottonseed oil to leaves can eliminate both eggs and larvae. (NBAIR) **High**: Pheromone traps [फेरोमोन जाल] and mechanical hand picking of adults and caterpillars are extensively used. Parasitoids such as Chelonus insularis, Cotesia marginiventris, Meteorus autographae, Lespesia archippivora lay eggs on the caterpillars, and their larvae feed and emerge. Predators like Orius sp., Geocoris sp., Nabis sp., Podisus maculiventris are also effective controlling measures. Pupal stages can be eliminated by introducing Solenopsis invicta to the field [खेत]. Apart from biological control [जैव नियंत्रण], many chemical pesticides [रासायनिक कीटनाशक] are extensively used. Larvae are susceptible to neem products. Eggs can be killed by using petroleum oil concentrations. Applying cottonseed oil to leaves can eliminate both eggs and larvae. (NBAIR) ``` ---- **NPSS Pest Advisory** ``` # Papaya [पपीता] - Sticky disease [रोग] ('meleira') (Disease [रोग]) **Description**: The most obvious sign of papaya [पपीता] sticky disease [रोग] is discharge of watery latex from undamaged green fruit. The latex is translucent and more liquid than latex from healthy fruit. The latex turns brown and hardens after contact with the air. Latex is also secreted from the edge of young leaves at the top of the plant, and leaf tips and borders turn brown. Diseased fruit tastes unpleasant. Spread : Papaya [पपीता] sticky disease [रोग] is caused by virus which is present in all parts of the plant. Two viruses can work together to cause sticky disease [रोग]. Infected seeds produce infected plants. The disease [रोग] can spread from plant to plant through pruning [फ枝剪ाई] and fruit picking. Papaya [पपीता] sticky disease [रोग] can be spread in infected tissue culture [ऊतक संवर्धन] plants. It is suspected that leafhoppers or whiteflies may also spread papaya [पपीता] sticky disease [रोग], but this has not been proved. ## Infestation Levels **Low**: * Regularly prune infected leaves and stems to remove the disease [रोग] source and prevent its spread. * Remove and destroy all fallen fruit and plant debris to eliminate potential sources of infection. * Maintain optimal soil fertility [मृदा उर्वरता] by applying balanced fertilization [संतुलित उर्वरक प्रबंधन] programs. * Avoid excessive nitrogen [नाइट्रोजन] fertilization [फलधारण], as it can promote disease [रोग] susceptibility. * Manually remove infected leaves and stems to prevent the spread of the disease [रोग]. * Dispose of infected plant parts outside the growing area to avoid re-infection. * Cover the soil [मिट्टी] with a transparent plastic tarp during hot weather [मौसम] to generate heat and kill the fungus present in the soil [मिट्टी]. Biological Control [जैव नियंत्रण] :**Trichoderma [ट्राइकोडर्मा] spp.:** These fungi are known for their antagonistic properties against a wide range of phytopathogens. They produce antimicrobial compounds that inhibit the growth and development of A. caricae. **Bacillus subtilis:** This bacterium produces antifungal enzymes and compounds that can suppress the pathogen [रोगजनक]. **Pseudomonas [स्यूडोमोनास एक सामान्य संक्रामक जीव] fluorescens:** This bacterium is a biocontrol agent [जैव नियंत्रण कारक] that competes with the pathogen [रोगजनक] for nutrients and releases antimicrobial compounds. **Beauveria bassiana [ब्यूवेरिया बासियाना]:** This entomopathogenic fungus [कीटनाशी फफूंदी] is used to control fruit flies, which are vectors of A. caricae. **Medium**: * Maintain optimal soil fertility [मृदा उर्वरता] by applying balanced fertilization [संतुलित उर्वरक प्रबंधन] programs. * Avoid excessive nitrogen [नाइट्रोजन] fertilization [फलधारण], as it can promote disease [रोग] susceptibility. * Manually remove infected leaves and stems to prevent the spread of the disease [रोग]. * Dispose of infected plant parts outside the growing area to avoid re-infection. * Cover the soil [मिट्टी] with a transparent plastic tarp during hot weather [मौसम] to generate heat and kill the fungus present in the soil [मिट्टी]. Biological Control [जैव नियंत्रण] :**Trichoderma [ट्राइकोडर्मा] spp.:** These fungi are known for their antagonistic properties against a wide range of phytopathogens. They produce antimicrobial compounds that inhibit the growth and development of A. caricae. **Bacillus subtilis:** This bacterium produces antifungal enzymes and compounds that can suppress the pathogen [रोगजनक]. **Pseudomonas [स्यूडोमोनास एक सामान्य संक्रामक जीव] fluorescens:** This bacterium is a biocontrol agent [जैव नियंत्रण कारक] that competes with the pathogen [रोगजनक] for nutrients and releases antimicrobial compounds. **Beauveria bassiana [ब्यूवेरिया बासियाना]:** This entomopathogenic fungus [कीटनाशी फफूंदी] is used to control fruit flies, which are vectors of A. caricae. **High**: Chemical Control [रासायनिक नियंत्रण] : **Copper [तांबा]-based compounds:** Copper [तांबा] fungicides [फफूंदनाशी दवाएँ] like copper [तांबा] oxychloride and copper [तांबा] hydroxide have been used traditionally to control sticky disease [रोग]. They function by inhibiting bacterial growth through disruption of cell membrane function and enzyme activity. However, they can lead to soil [मिट्टी] and water contamination, phytotoxicity [पौधों के लिए विषाक्त प्रभाव], and resistance development. ***Streptomycin:** This antibiotic [प्रतिजैविक] is effective against *Erwinia papayae* and can be applied as a foliar spray [पत्तियों पर छिड़काव]. It inhibits bacterial protein synthesis, leading to their death. However, the emergence [अंकुरण] of streptomycin-resistant strains is a growing concern. **Other antibiotics:** Some other antibiotics like tetracycline and oxytetracycline have shown some efficacy against sticky disease [रोग]. However, their use is often restricted due to concerns about antibiotic [प्रतिजैविक] resistance development and potential human health risks. **Chemical pesticides [रासायनिक कीटनाशक]:** Some pesticides with broad-spectrum activity, like organophosphates e.g. *Chlorpyrifos *Glyphosate *Malathion *Diazinon *Disulfoton *Acephate and carbamates e.g. *Carbofuran [कार्बोफ्यूरान] *Propoxur may indirectly control sticky disease [रोग] by suppressing insect [कीट] vectors that can carry the bacteria. However, their extensive use can have detrimental effects on biodiversity [जैव विविधता] and human health. ``` ---- **NPSS Pest Advisory** ``` # Cotton [कपास] - Tobacco [तंबाकू] catterpiller (Insect [कीट]) **Description**: The larvae feed gregariously on the undersurface of the leaves and skeletonize them leaving only the midrib and veins in severe cases. They also attack flowers, buds and squares causing considerable loss. Skeletonization resulting in papery appearance of leaves with only veins left out is the typical damage. Leaves defoliate and shedding of squares with feeding holes occur when larvae are in large numbers ## Infestation Levels **Low**: Installation of pheromone traps [फेरोमोन जाल] 2/acre for monitoring. Hand collection and destruction of egg masses and early instar gregarious larvae. **Medium**: Spray of biopesticides [जैव कीटनाशी] Bacillus thuringiensis [बेसिलस थुरिंजिएन्सिस] var. kurstaki 200-280 ml/ha; Bacillus thuringiensis [बेसिलस थुरिंजिएन्सिस] var. kurstaki 2.5% AS 300-400 g in 200-300L water/acre. Installation of pheromone traps [फेरोमोन जाल] 2/acre for monitoring. Hand collection and destruction of egg masses and early instar gregarious larvae. Need-based application of insecticide [कीटनाशक], Chlorpyrifos 50 % + Cypermethrin 05 % EC @400 ml in 200-400 Lwater/acre (waiting period 15 days) or chlorantraniliprole 18.5% SC@ 60 ml in 200 L of water/acre. For more details visit Major Uses of Pesticides (CIB&RC) on DPPQ&S website **High**: Spray of biopesticides [जैव कीटनाशी] Bacillus thuringiensis [बेसिलस थुरिंजिएन्सिस] var. kurstaki 200-280 ml/ha; Bacillus thuringiensis [बेसिलस थुरिंजिएन्सिस] var. kurstaki 2.5% AS 300-400 g in 200-300L water/acre. Installation of pheromone traps [फेरोमोन जाल] 2/acre for monitoring. Hand collection and destruction of egg masses and early instar gregarious larvae. Need-based application of insecticide [कीटनाशक], Chlorpyrifos 50 % + Cypermethrin 05 % EC @400 ml in 200-400 Lwater/acre (waiting period 15 days) or chlorantraniliprole 18.5% SC@ 60 ml in 200 L of water/acre. For more details visit Major Uses of Pesticides (CIB&RC) on DPPQ&S website ``` ---- **NPSS Pest Advisory** ``` # Wheat [गेहूं] - Aphid [चेपा] (Insect [कीट]) **Description**: Apterae are 1.3-3.3 mm long and the alates 1.6-2.9 mm long. Body colour ranges from yellow to green, red, purple, and brown. The dorsal cuticle is distinctly and uniformly sclerotic. Siphunculi and antennae blackish; cauda pale; legs yellow; tip of femora, tarsi and tibiae smoky; siphunculi twice as long as cauda. Alatae are similarly coloured but with more distinct intersegmental markings. First and second instar larvae have 5-segmented antennae while third and fourth instars have 6-segmented antennae. Males are generally red or reddish-brown. Most populations are anholocyclic, giving birth parthenogenetically only to asexual morphs. A female produces 20-40 nymphs which overwinter; sometimes already as apterous adults. Their life span takes about 4-10 weeks. Early yellowing of upper leaves and ears occurs under heavy infestation along with the presence of the sticky excretion known as honeydew. Affected plant parts show abnormal colors. The damage is particularly severe in years of cloudy weather [मौसम]. A heavily manured, well-irrigated and succulent crop [फसल] will harbour the pest [कीट] for a longer period and suffer greater damage. ## Infestation Levels **Low**: Regular field monitoring [क्षेत्र निरीक्षण] for pest [कीट] & defender population, barrier crops like mustard [सरसों] crop [फसल] around the field [खेत]. ? Plant tall border crops like maize [मक्का], sorghum [ज्वार] or millet [मोटा अनाज] to reduce pest [कीट] population. Avoid use excess nitrogen fertilizers [नाइट्रोजन युक्त उर्वरक]. Weed grasses (especially Poaceae) should be removed from around fields. Conserve Coccinellidae and Chrysopidae, hymenopterous parasitoids, especially of the family Braconidae and or release where ever possible for biological control [जैव नियंत्रण] of the pest [कीट]. **Medium**: Avoid use excess nitrogen fertilizers [नाइट्रोजन युक्त उर्वरक]. Weed grasses (especially Poaceae) should be removed from around fields. Conserve Coccinellidae and Chrysopidae, hymenopterous parasitoids, especially of the family Braconidae and or release where ever possible for biological control [जैव नियंत्रण] of the pest [कीट]. Use neem seed kernel extract [नीम बीज गिरी का अर्क] (NSKE) (5%) for foliar spraying [छिड़काव]. **High**: Conserve Coccinellidae and Chrysopidae, hymenopterous parasitoids, especially of the family Braconidae and or release where ever possible for biological control [जैव नियंत्रण] of the pest [कीट]. Application of CIB&RC approved pesticides: Imidacloprid 48% FS@0.35 kg/ha as a seed [बीज] dresser, Quinalphos 25 % EC @ 1-2 ml/lit of water, Thiamethoxam 70 % WS@175 gms/ha as a seed [बीज] dresser, Thiamethoxam 25 % WG@0.1 gm/lit of water (Waiting Period of 21 days) , Imidacloprid 18 + Carboxin 22.5% + Thiram 22.5 @3.4 kg/ha as a seed [बीज] dresser, Imidacloprid 18.50 % + Hexaconazole 01.50 % FS@200 gms/ha as a seed [बीज] dresser, ``` ---- **NPSS Pest Advisory** ``` # Papaya [पपीता] - Cercospora black spot (Disease [रोग]) **Description**: The disease [रोग] occurs on the leaves and on the fruits. On upper surface of leaves, characteristic symptoms consist of round, light [प्रकाश]-brown (tan) necrotic spots, encircled by a yellow halo. On the lower surface of the leaves, in the areas corresponding to the spots, the powdery growth of the fungus of gray to black color can be observed .In some cases, over these, a pale mycelium produced by a fungal hyperparasite of the pathogen [रोगजनक] may be observed. When it occurs, coalescence of the lesions is a common cause of leaf senescence [पत्तों का वृद्धावस्था] and defoliation [पत्तों का झड़ना] of the plants. Abundant spotting causes defoliation [पत्तों का झड़ना] and over 50% leaf fall can occur. Young leaves generally do not present symptoms. In the fruits, the presence of circular areas of watery aspect are observed initially, that, with evolution of the disease [रोग] become brown in color, prominent, with pale,points, and that may attain 5mm of diameter . These lesions generally are epidermal and do not reach the pulp of the fruit, causing only a hardening of the skin of the part affected. ## Infestation Levels **Low**: * Avoid overhead irrigation [ऊपर से सिंचाई], especially during periods of high humidity [आर्द्रता], as it promotes leaf wetness and favors disease [रोग] development. Instead, use drip irrigation [ड्रिप सिंचाई] or mulching [मल्चिंग] techniques to maintain soil moisture [मिट्टी की नमी] without creating favorable conditions for the pathogen [रोगजनक]. * Regularly inspect plants for early signs of CBS and physically remove infected leaves by hand or with pruning shears [छंटाई कैंची]. This is an effective method for controlling low levels * Hand scrubbing of leaf surfaces with a mild abrasive material, such as a fine-bristled brush, can remove fungal spores and reduce infection severity. This method is particularly well-suited for small-scale operations or situations where chemical control [रासायनिक नियंत्रण] is not feasible. * Selective pruning [फ枝剪ाई] of infected leaves and branches helps to remove sources of inoculum and improve air circulation within the canopy [पर्णछाया]. By removing diseased tissues, pruning [फ枝剪ाई] creates a less conducive environment for the fungus to thrive and reduces the risk of further infection. Biological control [जैव नियंत्रण] : *Trichoderma [ट्राइकोडर्मा] spp.:* This genus of fungi is known for its ability to parasitize *C. papayae*, producing enzymes that degrade its cell walls. *Bacillus spp.:* Certain species of Bacillus bacteria, like *B. subtilis,* produce antibiotics that effectively suppress *C. papayae* growth. *Yeast-based biocontrol agents [जैव नियंत्रण कारक]:* Yeasts, like *Saccharomyces cerevisiae,* can suppress *C. papayae* by competing for nutrients and producing antifungal compounds. **Medium**: * Avoid overhead irrigation [ऊपर से सिंचाई], especially during periods of high humidity [आर्द्रता], as it promotes leaf wetness and favors disease [रोग] development. Instead, use drip irrigation [ड्रिप सिंचाई] or mulching [मल्चिंग] techniques to maintain soil moisture [मिट्टी की नमी] without creating favorable conditions for the pathogen [रोगजनक]. * Selective pruning [फ枝剪ाई] of infected leaves and branches helps to remove sources of inoculum and improve air circulation within the canopy [पर्णछाया]. By removing diseased tissues, pruning [फ枝剪ाई] creates a less conducive environment for the fungus to thrive and reduces the risk of further infection. Biological control [जैव नियंत्रण] : *Trichoderma [ट्राइकोडर्मा] spp.:* This genus of fungi is known for its ability to parasitize *C. papayae*, producing enzymes that degrade its cell walls. *Bacillus spp.:* Certain species of Bacillus bacteria, like *B. subtilis,* produce antibiotics that effectively suppress *C. papayae* growth. *Yeast-based biocontrol agents [जैव नियंत्रण कारक]:* Yeasts, like *Saccharomyces cerevisiae,* can suppress *C. papayae* by competing for nutrients and producing antifungal compounds. **High**: Chemical Control [रासायनिक नियंत्रण] : **1. Protectant Fungicides [फफूंदनाशी दवाएँ]:** These fungicides [फफूंदनाशी दवाएँ] are applied to plant surfaces, creating a protective barrier that prevents fungal spore [फफूंदी के बीजाणु] germination [अंकुरण] and penetration. Commonly used protectant fungicides [फफूंदनाशी दवाएँ] include: *Copper [तांबा]-based fungicides [फफूंदनाशी दवाएँ]:* Effective against a broad spectrum of fungal pathogens but can cause phytotoxicity [पौधों के लिए विषाक्त प्रभाव] and environmental concerns e.g. copper [तांबा] sulfate, copper [तांबा] hydroxide, copper [तांबा] oxychloride sulfate. *Mancozeb:* Offers a relatively affordable option with good control, but resistance development is a concern. **2. Systemic Fungicides [फफूंदनाशी दवाएँ]:** These fungicides [फफूंदनाशी दवाएँ] are absorbed by the plant and translocated throughout the system, offering protection against internal infection. Examples include: *Triazoles:* Effective against *Cercospora* but resistance development is common, necessitating careful rotation and application strategies. e.g. Tebuconazole, *Strobilurins:* Highly effective against *Cercospora* but resistance development is a significant concern e.g. Azoxystrobin's, Metiram, Pyraclostrobin. *Dithiocarbamates:* Offers broad-spectrum control but potential for adverse environmental impacts. e.g. Mancozeb, Thiram, Ziram ``` [tool:search_terms] No matching terms found for `కాండం తొలుచు పురుగు` [tool:search_terms] Matching Terms for `గోధుమ` Wheat -> गेहूं (gehu) [100%] | M13: 1 | N13: 1 | O13: Number are and names are not translated completly, and incompleteness in response | P13: Completed | Q13: 3 | R13: Accept with Minor Corrections | S13: The overall evaluation is correct and the core findings are valid. Minor 1-point score variances exist between stages, primarily in Accuracy/Completeness. These minor corrections do not impact the overall validity and can be accepted with minor updates. | T13: updated
A14: 10 | B14: 10-1 | C14: గోండియాలో ఆవు పొదుగు వాపితే చికిత్స ఏమిటి? | D14: ఆవు పొదుగు వాపు (Mastitis) అనేది పశువులలో వచ్చే సాధారణ సమస్య. దీని నివారణ మరియు చికిత్స కోసం ఈ క్రింది జాగ్రత్తలు తీసుకోండి: * **శుభ్రత:** పశువుల షెడ్డును ఎల్లప్పుడూ శుభ్రంగా మరియు పొడిగా ఉంచండి. * **పొదుగు సంరక్షణ:** పాలు పితికే ముందు ప్రతిరోజూ పొదుగును సబ్బు నీటితో శుభ్రం చేయండి. పాలు పితికిన తర్వాత పొదుగుకు మాస్టిలెప్ (Mastilep®) వంటి మందుల ఆయింట్‌మెంట్‌ను రాయండి. * **నివారణ చర్యలు:** పొదుగు ఆరోగ్యాన్ని కాపాడటానికి మరియు ఇన్ఫెక్షన్లను అరికట్టడానికి యాంటీసెప్టిక్ వాష్ లేదా అయోడోఫోర్ టీట్ డిప్స్ (Iodophor teat dips) ఉపయోగించండి. * **పాలు పితికిన తర్వాత:** పాలు పితికిన వెంటనే ఆవును ౧ గంట పాటు నిలబెట్టండి, తద్వారా పొదుగు రంధ్రాలు సరిగ్గా మూసుకుని దుమ్ము, ధూళి ద్వారా క్రిములు లోపలికి వెళ్లకుండా ఉంటాయి. **ముఖ్య గమనిక:** వాపు ఎక్కువగా ఉన్నా లేదా పాలు రంగు మారినా, వెంటనే స్థానిక పశువైద్యుడిని సంప్రదించి సరైన చికిత్స తీసుకోవడం ఉత్తమం. **మూలం: ఐ.సి.ఎ.ఆర్ (ICAR) వ్యవసాయ సలహాలు** మీ ఆవు పాలు పితికేటప్పుడు ఏవైనా మార్పులు (ఉదాహరణకు రంగు లేదా గడ్డలు) గమనించారా? | E14: 4 | F14: 1 | G14: 1 | H14: 1 | I14: 4 | J14: 4 | K14: 4 | L14: [tool:search_documents] > Search Results for `treatment for cow udder swelling mastitis` **ICAR Kharif Agro-Advisories for Farmers** ``` Ginger [अदरक] Cultivate suitable ginger [अदरक] varieties- Suprabha, Suruchi and Suravi with seed rate [बीज दर] of 1800-2000 kg/ha. Select high loamy land for cultivation. Raised bed [ऊँचा क्यारी] of size 1 m width, 15 cm height and of convenient length may be adopted along with making channels for draining excess rain water. Before sowing [बुवाई] dip rhizomes in a slurry [द्रव और उसमें निलंबित ठोस पदार्थों का मिश्रण] of 1 g Carbendazim, 3 g Mancozeb and 1 g Plantomycin for half an hour and dry in the shade. Banana [केला] Banana [केला] crop [फसल] should be planted during June with receipt of rain. Tissue culture [ऊतक संवर्धन] plants and high- density planting may be followed for banana [केला] cultivation for higher productivity. In bearing plants of coconut [नारियल], make circular pit of 30 cm deep 3 ft away from the trunk, apply 60 kg compost [कम्पोस्ट], 500 g urea [यूरिया], 1 kg SSP/300 g of DAP, 1 kg MOP and 200 g borax [बोरैक्स] per bearing plant in the pit and cover with soil [मिट्टी]. LIVESTOCK [पशुधन] Don't allow domestic animals to graze outside during 11 PM to 3 PM as ambient temperature [तापमान] remains high this time. Provide sufficient clean drinking water to cattle and keep their sheds clean. Provide vaccination at regular interval. Cultivate and 189 ICAR Kharif Agro-Advisory [कृषि सलाह] 2025 supplement azolla @ 1-1.5 kg in daily ration of cattle to reduce the feed cost by 20%. Provide supplementary feeding such as broken rice [चावल], paddy, cooked rice [चावल], azolla etc. to the backyard poultry [पोल्ट्री पालन] birds during continuous rain. It is preferable to expose the feed ingredient sacks/bags under sun every week to prevent the feeds getting more moisture. Wash the cattle shed with phenyl (dilution 1:20 ratio with water) and sprinkle bleaching powder around the shed at weekly intervals. Mastitis is a common problem in high yielding cows in rainy season. Keep the cattle shed clean and dry. Clean the udder in soap water daily before milking. Apply Mastilep® ointment over the udder after each milking. ``` ---- **ICAR Rabi Agro-Advisories for Farmers 2025** ``` Newborn calves, lambs, and kids are highly susceptible to cold, with calf mortality exceeding 30% in poorly managed herds. Colostrum feeding at 10% body weight within 1-2 hours of birth is critical. Navel disinfection with iodine must be immediate. Bedding should be thick and dry, with extra heating in snow-bound areas. Calf starter and hay should be introduced from 15 days, with green fodder [हरा चारा] after 3 months. Deworming should begin at 15 days, repeated at 30 days, and then at regular intervals. Diarrhoeic calves must continue milk feeding with ORS. Regular growth monitoring through weighing is advised. Pneumonia, mastitis, diarrhoea, foot rot, FMD, HS, PPR, and Swine Fever are major winter diseases. Vaccination must precede peak cold. Routine deworming and ectoparasite control using flumethrin pour-on, cypermethrin/deltamethrin spray, or dips are essential. Carcasses must be disposed by deep burial (4 feet) with lime [चूना] layering [स्तरीकरण]. Stressful operations like dehorning and castration should be avoided during extreme cold. Villages should keep veterinary kits and updated vet contact lists. Newly purchased animals must be quarantined for 21 days. Rotational grazing [चराई] reduces parasite [परजीवी] load. Accurate records of vaccination, deworming, treatments, and reproduction are vital for scientific herd management. Stronger surveillance and early disease [रोग] reporting ensure quick outbreak control. # Cattle and Buffalo Vaccinate against Foot and Mouth Disease [रोग] (Oct-Nov), Hemorrhagic Septicemia (Feb-Mar), and Brucella (female calves, 4-8 months). Newly calved cows need 1-1.5 kg additional concentrate plus mineral mixture. Mastitis can be prevented by antiseptic udder wash and iodophor teat dips. Weekly copper [तांबा] sulfate (5%) footbaths control foot rot. Cold stress [ठंड के कारण होने वाला तनाव] lowers fertility, so estrus must be closely monitored, ensure timely artificial insemination [कृत्रिम गर्भाधान], and pregnancies confirmed within 60-90 days. 99 ``` ---- **ICAR Kharif Agro-Advisories for Farmers** ``` Artificial Insemination [कृत्रिम गर्भाधान] (AI) should be continued in consultation with veterinary officer on door-to-door basis rather than direct visit to the dispensaries. To maintain productivity and improve immune status of animals, it is suggested for regular supplementation of mineral- 60g/ dayinadultdairyanimalsand 20-30ginsmallruminants. Also, administerdeworming medication. Oﬀer clean and cool water three times a day. In case of injury in lactating cows, apply Himex ointment. In case of temporary shortage of availability of green fodder [हरा चारा] or concentrate feed [संकेन्द्रित आहार] farmers can prepare home-made feed by using grain [अन्न] like wheat [गेहूं], maize [मक्का], wheat [गेहूं] bran, oilcakes and salt. They can also prepare silage [साइलेज] for their adult dairy [दुग्ध व्यवसाय] animals. Due to increased maximum temperatures, goats should be kept in shaded areas and given clean, fresh water three times daily. Vaccinate goats against PPR (Peste des Petits Ruminants), Contagious Pneumonia, and ETV (Enterotoxaemia). Also, implement control measures for ticks and lice. To control ectoparasites, apply Butox or Cleaner @ 2 ml/L of water over the animal's body, ensuring the mouth is covered during application. Use smoke in animal shelterstokeepawaymosquitoesandotherinsects. Chhattisgarh Poultry [पोल्ट्री पालन] ``` ---- **ICAR Rabi Agro-Advisories for Farmers 2025** ``` Clean and managed cattle shed gradually introducing fodder [चारा] and supplements after two weeks. Vaccinate against FMD, Brucellosis, and Theileriosis in risk areas, deworm before vaccination, and maintain udder hygiene to prevent mastitis. Feeding of green fodder [हरा चारा] to livestock [पशुधन] ## Goat Goats should be provided $1.5 - 2.5$ green fodder [हरा चारा], $200 - 300$ concentrate, and $15 - 20$ mineral mixture daily, with clean water always available. Sheds must be 3-3.5 feet high, dry, and well-ventilated, with $0.5 - 0.75$ for kids, 1-1.5 sq. m for adults, and 2-3 sq. m outdoor space. Vaccinate against PPR and goat pox, and deworm every 3-4 months. ``` ---- **ICAR Kharif Agro-Advisories for Farmers** ``` Artificial Insemination [कृत्रिम गर्भाधान] (AI) should be continued in consultation with veterinary officer on door-to-door basis rather than direct visit to the dispensaries. To maintain productivity and improve immune status of animals, it is suggested for regular supplementation of mineral- 60g/ day in adult dairy [दुग्ध व्यवसाय] animals and 20-30g in small ruminants. Also, administer deworming medication. Oﬀer clean and cool water three times a day. In case of injury in lactating cows, apply Himex ointment. In case of temporary shortage of availability of green fodder [हरा चारा] or concentrate feed [संकेन्द्रित आहार] farmers can prepare home-made feed by using grain [अन्न] like wheat [गेहूं], maize [मक्का], wheat [गेहूं] bran, oilcakes and salt. Theycanalsopreparesilagefortheiradultdairyanimals. Duetoincreasedmaximum temperatures, goats should be kept in shaded areas and given clean, fresh water three times daily. Vaccinate goats against PPR (Pestedes Petits Ruminants), Contagious Pneumonia, and ETV (Enterotoxaemia). Also, implement control measures for ticks and 137 ICAR Kharif Agro-Advisory [कृषि सलाह] 2025 lice. To control ectoparasites, apply Butox or Cleaner @ 2 ml/L of water over the animal's body, ensuring the mouth is covered during application. Use smoke in animal shelters to keepawaymosquitoesandotherinsects. Poultry [पोल्ट्री पालन] ``` ---- **ICAR Rabi Agro-Advisories for Farmers 2025** ``` Supplementation of Salt (NaCl) @ 30-50 g/day/animal for better milk yield [उत्पादन]. Supplementation of Sodium Bicarbonate (Baking soda) @ 30-50 g/day/animal for better milk fat yield [उत्पादन] and to avoid SARA. *Azolla* supplementation may be taken up @ 1-2 kg/dairy [दुग्ध व्यवसाय] cattle/day. If brewer's yeast or any other unconventional feed is added to the ration, farmers are advised to feed not more than 10% in the ration. TANUVAS Masti-guard may be used to prevent Mastitis and for clean milk production [दूध उत्पादन]. Farmers to utilize the validated EVM (Ethno Veterinary Medicine [पशुचिकित्सा उपचार]) practices. Avoid feeding fungus and mold-affected paddy straw to the cattle. Use potassium [पोटाश] permanganate in water for washing the udder before and after milking. Keep the cow in standing position for 1 hour immediately after milking for proper closing of the teat orifice to prevent entry of microbes from the dusty and muddy floor. Keep the animals inside the shelter during rainy and nighttime hours. ## Goat and Sheep Locally available feed materials may be effectively used for feeding and the same popularized. Hydroponic fodder [चारा] may be utilized wherever available. Before the onset of monsoon [मानसून], based on worm load by dung examination, deworming to be done with appropriate deworming medicine. New animals added to the herd should be quarantined for 25 days to assess the incidence of PPR or any other infection. 250-300 g of concentrate feed [संकेन्द्रित आहार] should be given to the pregnant ewes to avoid stillbirth or weak kids. Fodder [चारा] tree seedlings should be cultivated using the rainfall, and green &gt;&gt;&gt; 262 ``` ---- **ICAR Rabi Agro-Advisories for Farmers 2025** ``` To protect animals from the weather [मौसम] fluctuations, keep them in well-ventilated shelters that provide warm and dry conditions. Use thick bedding (straw, sawdust, dry grass) to insulate animals from cold floors. Avoid dampness and drafts, cover openings with gunny bags or plastic sheets. Ensure sunlight exposure during the day for warmth and hygiene. Restrict the movement of visitors to the livestock [पशुधन] farms and practice biosecurity measures [जैव सुरक्षा उपाय] in case of disease [रोग] outbreaks. Keep sufficient feed, fodder [चारा], and medicine in hand. Vaccinate animals against Foot and Mouth Disease [रोग] (Cows and buffaloes) and PPR (goats). Monitor for signs of pneumonia, diarrhoea, and frostbite, especially in young and aged animals. Except for pregnant animals, deworm all animals for external and internal parasites. Offer lukewarm water to prevent cold shock and ensure proper intake. Increase energy-rich feed (like grains, oil cakes) to meet higher metabolic needs. Feed roughages (hay, silage [साइलेज]) to maintain body temperature [तापमान] through rumination. Provide molasses and mineral mixtures to boost energy and immunity. Supplement with an herbal immune-boosting product in a ratio to boost immunity. Observe and detect oestrus and inseminate on time. Offer ample milk or electrolyte [इलेक्ट्रोलाइट] water to newborn calves to prevent dehydration [निर्जलीकरण] and death of neonatal stocks. Keep newborns and calves/kids/Lambs in warm pens. Use heat lamps or jackets for weak animals. Maintain clean, well-ventilated shelters with proper drainage to prevent diseases from high humidity [आर्द्रता] conditions. Ensure adequate space: Overcrowding causes stress and disease [रोग] outbreaks. All dead animals should be disposed of hygienically and should not be thrown in nearby drainage, water bodies, etc. Burial Pit should be of 8 × 9 feet. Sprinkling of disinfectants like bleaching powder, quick lime [चूना], etc., in the affected areas helps in reducing the spread of diseases. Clean, safe, hygienic water should be provided to the animals. Restrict the transportation [परिवहन] of animals to consumers' doorsteps for milking. # Dairy [दुग्ध व्यवसाय] ``` ---- **ICAR Kharif Agro-Advisories for Farmers** ``` Chilli [मिर्च] For chili cultivation, recommended varieties include GVC-101, Anand Jwala, and hybrid varieties. The seed rate [बीज दर] is 750 g/ha, with spacing [अंतर] of 60x60 cm. Apply a basal fertilizer [उर्वरक] of 50:50:50 (NPK) kg/ha. For plant protection [पौध संरक्षण], control Thrips [फूलकीड़े] with Neem powder/oil spray and use Spinosad for severe infestations. Manage Leaf Curl virus [पत्ती मुड़न वायरस] with Pyriproxyfen or Fenprofethin spray. Brinjal [बैंगन] For brinjal [बैंगन] cultivation, use recommended varieties: Gujarat Anand Oblong Brinjal [बैंगन] 2 and hybrid varieties. The seed rate [बीज दर] is 250-300 g/ha, with spacing [अंतर] of 90x60 cm. For nursery [नर्सरी] management, use Trichoderma [ट्राइकोडर्मा] virdi and water as needed. For plant protection [पौध संरक्षण], control Whitefly [सफेद मक्खी] with Neem powder/oil spray, and manage Little Leaf by removing aﬀected plants and applying Pyriproxyfen spray. To improve milk yield [उत्पादन] in lactating animals, formulate a proper feed rich in essential nutrients. Consider using Azolla as a green fodder [हरा चारा] replacement to enhance protein intake. During rainy seasons, keep livestock [पशुधन] indoors and ensure proper fodder [चारा] storage [भंडारण]. Vaccinate animals against FMD (Foot and Mouth Disease [रोग]) and Brucellosis, along with other necessary vaccines. Maintain clean and hygienic animal sheds to prevent mastitis. Deworm animals with Fenbendazole, and control ectoparasites using Deltamethrin or Amitraz. NORTH GUJARAT-KUTCHH This region of the state includes the regions of Banaskantha, Patan, Mehsana, Sabarkantha, Aravalli, and Gandhinagar. The local agricultural university is Sardarkrushinagar Dantiwara Agricultural University (S.K.Nagar, Banaskantha). The region receives rainfall between 700-1000 mm annually and is characterized by loamy sand soil [मिट्टी]. Groundnut [मूंगफली] ``` ---- **ICAR Kharif Agro-Advisories for Farmers** ``` ICAR Kharif Agro-Advisory [कृषि सलाह] 2025 Maintaining an emergency stock of dry fodder [सूखा चारा] and concentrates is crucial for ensuring uninterrupted animal nutrition [पशु पोषण] during unforeseen weather [मौसम] events such as heavy snowfall. Green ¹⁄ and 2⁄ dry fodder [सूखा चारा] should constitute the total fodder [चारा] requirement of the animal. Concentrate feed [संकेन्द्रित आहार], 1 kg per 2.5 liters of milk produced in cattle should be provided to fulfill their nutritional needs. Avoid sudden change in feed and fodder [आहार और चारा], change should be gradual so that animal can adopt to the new ration without experiencing any health issue. Commercially available mineral mixture at the rate of 60g per animal should be incorporated in the ration to meet the daily requirement of the minerals. However, it should be discontinued once pregnant animals are dried off, to reduce risk of milk fever post calving. A strategic deworming schedule should be followed to prevent development of anthelmintic résistance. This involves deworming animals based on parasite [परजीवी] risk and fecal egg counts rather than routine blanket treatments. Rotating between classes of anthelmintics and targeting high-risk animals helps preserve the efficacy of dewormers, ensuring long-term parasite [परजीवी] control and minimizing drug resistance in the herd. Follow proper biosecurity measures [जैव सुरक्षा उपाय] to prevent outbreak of any disease [रोग]. This is crucial for preventing the introduction and spread of infectious diseases within a herd. It includes controlling the movement of animals, people, and equipment; maintaining cleanliness and disinfection routines; quarantining new or sick animals; and regularly monitoring animal health [पशु स्वास्थ्य]. Use of corrosive chemicals for disinfection should be discouraged as it can increase the risk of lameness in animals. For prevention of mastitis, it is essential to use both pre- and post-milking teat dips. Consistent use of quality teat dips, along with proper milking hygiene, plays a key role in maintaining udder health and reducing mastitis incidence and ensuring production of clean and hygienic milk for human consumption. For prevention of malignant catarrhal fever sheep should never be cohoused with cattle. ``` ---- **ICAR Rabi Agro-Advisories for Farmers 2025** ``` During winter, adult animals and young stock should be provided with protective coverings such as blankets, gunny bags, or sacks to prevent heat loss. Rubbing animals and offering warm fluids, calcium [कैल्शियम] solutions, or liver tonics helps prevent hypothermia. Cold water baths should be avoided; animals can be cleaned with a cloth or soft brush. Calves, especially those fewer than three weeks old, require extra care with warm water baths, heat lamps, and blankets. Thick, dry straw or sawdust in resting areas insulates them, while additional milk or milk replacer compensates for energy used to maintain warmth. Prevent mastitis through complete milking, germicidal teat dips, and udder care. Winter is ideal for deworming, vaccination, and providing sunlight exercise to maintain health and productivity. ## Goat and Sheep Sheep and goats are highly sensitive to cold and damp conditions, making proper housing and dry bedding essential during winter. Each animal should have at least 1 m² floor space with non-slippery flooring, covered with hay, straw, or husk [भूसा] for insulation. Young lambs and kids should 300 ``` [tool:search_terms] No matching terms found for `ఆవు పొదుగు వాపు` | M14: 1 | N14: 1 | P14: Completed | Q14: 4 | R14: Accept | S14: The evaluator's assessment fully aligns with Stage 3 guidelines and tool output. Rubric scores assigned in earlier stages are consistent and accurate. No corrections or re-evaluations are required.
A15: 120 | B15: 120-1 | C15: అమరావతిలో ఆవు పొదుగు ఉబ్బి ఉంటే చికిత్స ఏమిటి? | D15: ఆవు పొదుగు ఉబ్బడం అనేది సాధారణంగా 'మాస్టిటిస్' (Mastitis) అనే వ్యాధి లక్షణం కావచ్చు. దీని నివారణ మరియు చికిత్స కోసం ఈ క్రింది జాగ్రత్తలు తీసుకోండి: * పొదుగును ప్రతిరోజూ పాలు పితికిన ముందు మరియు తర్వాత సబ్బు నీటితో లేదా పొటాషియం పర్మాంగనేట్ కలిపిన నీటితో శుభ్రంగా కడగండి. * పాలు పితికిన తర్వాత పొదుగుకు 'మాస్టిలెప్' (Mastilep®) వంటి ఆయింట్‌మెంట్లను రాయండి. * పశువుల షెడ్డును ఎల్లప్పుడూ శుభ్రంగా మరియు పొడిగా ఉంచండి. * పాలు పితికిన వెంటనే పశువును ౧ గంట పాటు నిలబెట్టండి, తద్వారా చనుమల రంధ్రాలు మూసుకుని బయట నుండి క్రిములు లోపలికి వెళ్లకుండా ఉంటాయి. **ముఖ్య గమనిక:** ఇది తీవ్రమైన ఇన్ఫెక్షన్ కావచ్చు, కాబట్టి వెంటనే సమీపంలోని పశువైద్యుడిని సంప్రదించి సరైన చికిత్స తీసుకోవడం ఉత్తమం. **మూలం: ఐ.సి.ఎ.ఆర్ (ICAR) వ్యవసాయ సలహాలు** మీ ఆవుకు జ్వరం లేదా పాలలో రంగు మార్పు వంటి ఇతర లక్షణాలు ఏమైనా ఉన్నాయా? | E15: 4 | F15: 1 | G15: 1 | H15: 1 | I15: 2 | J15: 3 | K15: 3 | L15: [tool:search_documents] > Search Results for `treatment for swollen udder in cow` **ICAR Kharif Agro-Advisories for Farmers** ``` Ginger [अदरक] Cultivate suitable ginger [अदरक] varieties- Suprabha, Suruchi and Suravi with seed rate [बीज दर] of 1800-2000 kg/ha. Select high loamy land for cultivation. Raised bed [ऊँचा क्यारी] of size 1 m width, 15 cm height and of convenient length may be adopted along with making channels for draining excess rain water. Before sowing [बुवाई] dip rhizomes in a slurry [द्रव और उसमें निलंबित ठोस पदार्थों का मिश्रण] of 1 g Carbendazim, 3 g Mancozeb and 1 g Plantomycin for half an hour and dry in the shade. Banana [केला] Banana [केला] crop [फसल] should be planted during June with receipt of rain. Tissue culture [ऊतक संवर्धन] plants and high- density planting may be followed for banana [केला] cultivation for higher productivity. In bearing plants of coconut [नारियल], make circular pit of 30 cm deep 3 ft away from the trunk, apply 60 kg compost [कम्पोस्ट], 500 g urea [यूरिया], 1 kg SSP/300 g of DAP, 1 kg MOP and 200 g borax [बोरैक्स] per bearing plant in the pit and cover with soil [मिट्टी]. LIVESTOCK [पशुधन] Don't allow domestic animals to graze outside during 11 PM to 3 PM as ambient temperature [तापमान] remains high this time. Provide sufficient clean drinking water to cattle and keep their sheds clean. Provide vaccination at regular interval. Cultivate and 189 ICAR Kharif Agro-Advisory [कृषि सलाह] 2025 supplement azolla @ 1-1.5 kg in daily ration of cattle to reduce the feed cost by 20%. Provide supplementary feeding such as broken rice [चावल], paddy, cooked rice [चावल], azolla etc. to the backyard poultry [पोल्ट्री पालन] birds during continuous rain. It is preferable to expose the feed ingredient sacks/bags under sun every week to prevent the feeds getting more moisture. Wash the cattle shed with phenyl (dilution 1:20 ratio with water) and sprinkle bleaching powder around the shed at weekly intervals. Mastitis is a common problem in high yielding cows in rainy season. Keep the cattle shed clean and dry. Clean the udder in soap water daily before milking. Apply Mastilep® ointment over the udder after each milking. ``` ---- **ICAR Rabi Agro-Advisories for Farmers 2025** ``` Supplementation of Salt (NaCl) @ 30-50 g/day/animal for better milk yield [उत्पादन]. Supplementation of Sodium Bicarbonate (Baking soda) @ 30-50 g/day/animal for better milk fat yield [उत्पादन] and to avoid SARA. *Azolla* supplementation may be taken up @ 1-2 kg/dairy [दुग्ध व्यवसाय] cattle/day. If brewer's yeast or any other unconventional feed is added to the ration, farmers are advised to feed not more than 10% in the ration. TANUVAS Masti-guard may be used to prevent Mastitis and for clean milk production [दूध उत्पादन]. Farmers to utilize the validated EVM (Ethno Veterinary Medicine [पशुचिकित्सा उपचार]) practices. Avoid feeding fungus and mold-affected paddy straw to the cattle. Use potassium [पोटाश] permanganate in water for washing the udder before and after milking. Keep the cow in standing position for 1 hour immediately after milking for proper closing of the teat orifice to prevent entry of microbes from the dusty and muddy floor. Keep the animals inside the shelter during rainy and nighttime hours. ## Goat and Sheep Locally available feed materials may be effectively used for feeding and the same popularized. Hydroponic fodder [चारा] may be utilized wherever available. Before the onset of monsoon [मानसून], based on worm load by dung examination, deworming to be done with appropriate deworming medicine. New animals added to the herd should be quarantined for 25 days to assess the incidence of PPR or any other infection. 250-300 g of concentrate feed [संकेन्द्रित आहार] should be given to the pregnant ewes to avoid stillbirth or weak kids. Fodder [चारा] tree seedlings should be cultivated using the rainfall, and green &gt;&gt;&gt; 262 ``` ---- **ICAR Rabi Agro-Advisories for Farmers 2025** ``` ICAR Rabi Agro-Advisory [कृषि सलाह] 2025 ## Fodder [चारा] rape Fodder [चारा] rape is a fast-growing winter fodder [चारा] ideal for semi-arid to temperate regions. Sowing [बुवाई] is done during the 1st fortnight of October, 2.4-2.8 kg seed [बीज]/acre in fine loam soil [मिट्टी]. Apply 28 kg urea [यूरिया] + 18 kg DAP + 7 kg MOP/acre (16:8:4 NPK) at 5-7 cm depth and needs 2-3 irrigations. Harvest [कटाई] 50-60 DAS for fodder [चारा]; for seed [बीज], harvest [कटाई] when pods turn straw-coloured. Average yield [उत्पादन] is 80-120 q/acre green fodder [हरा चारा]; 280-320 kg/acre seed [बीज]. ## Livestock [पशुधन] Provide dry, warm housing with proper ventilation and bedding for dairy [दुग्ध व्यवसाय] animals to protect them from cold stress [ठंड के कारण होने वाला तनाव]. Ensure balanced winter feeding with quality dry fodder [सूखा चारा], green fodder [हरा चारा], oil cakes, mineral mixture, and clean water. Maintain regular deworming and vaccinate against Foot and Mouth Disease [रोग] (FMD), Haemorrhagic Septicaemia (HS), etc. Practice udder hygiene and avoid washing animals during severe cold. Offer sun exposure during the day and protect newborn calves with warm bedding and coverings. For sheep and goats, keep shelters warm and dry, provide quality fodder [चारा], oil cakes, and minerals, ensure regular deworming and vaccinations against peste des petits ruminants (PPR), enterotoxaemia, and sheep pox, protect newborns from cold, and avoid grazing [चराई] during severe frost. ## Enterprises ### Mushroom ``` ---- **ICAR Kharif Agro-Advisories for Farmers** ``` Artificial Insemination [कृत्रिम गर्भाधान] (AI) should be continued in consultation with veterinary officer on door-to-door basis rather than direct visit to the dispensaries. To maintain productivity and improve immune status of animals, it is suggested for regular supplementation of mineral- 60g/ dayinadultdairyanimalsand 20-30ginsmallruminants. Also, administerdeworming medication. Oﬀer clean and cool water three times a day. In case of injury in lactating cows, apply Himex ointment. In case of temporary shortage of availability of green fodder [हरा चारा] or concentrate feed [संकेन्द्रित आहार] farmers can prepare home-made feed by using grain [अन्न] like wheat [गेहूं], maize [मक्का], wheat [गेहूं] bran, oilcakes and salt. They can also prepare silage [साइलेज] for their adult dairy [दुग्ध व्यवसाय] animals. Due to increased maximum temperatures, goats should be kept in shaded areas and given clean, fresh water three times daily. Vaccinate goats against PPR (Peste des Petits Ruminants), Contagious Pneumonia, and ETV (Enterotoxaemia). Also, implement control measures for ticks and lice. To control ectoparasites, apply Butox or Cleaner @ 2 ml/L of water over the animal's body, ensuring the mouth is covered during application. Use smoke in animal shelterstokeepawaymosquitoesandotherinsects. Chhattisgarh Poultry [पोल्ट्री पालन] ``` ---- **ICAR Rabi Agro-Advisories for Farmers 2025** ``` Newborn calves, lambs, and kids are highly susceptible to cold, with calf mortality exceeding 30% in poorly managed herds. Colostrum feeding at 10% body weight within 1-2 hours of birth is critical. Navel disinfection with iodine must be immediate. Bedding should be thick and dry, with extra heating in snow-bound areas. Calf starter and hay should be introduced from 15 days, with green fodder [हरा चारा] after 3 months. Deworming should begin at 15 days, repeated at 30 days, and then at regular intervals. Diarrhoeic calves must continue milk feeding with ORS. Regular growth monitoring through weighing is advised. Pneumonia, mastitis, diarrhoea, foot rot, FMD, HS, PPR, and Swine Fever are major winter diseases. Vaccination must precede peak cold. Routine deworming and ectoparasite control using flumethrin pour-on, cypermethrin/deltamethrin spray, or dips are essential. Carcasses must be disposed by deep burial (4 feet) with lime [चूना] layering [स्तरीकरण]. Stressful operations like dehorning and castration should be avoided during extreme cold. Villages should keep veterinary kits and updated vet contact lists. Newly purchased animals must be quarantined for 21 days. Rotational grazing [चराई] reduces parasite [परजीवी] load. Accurate records of vaccination, deworming, treatments, and reproduction are vital for scientific herd management. Stronger surveillance and early disease [रोग] reporting ensure quick outbreak control. # Cattle and Buffalo Vaccinate against Foot and Mouth Disease [रोग] (Oct-Nov), Hemorrhagic Septicemia (Feb-Mar), and Brucella (female calves, 4-8 months). Newly calved cows need 1-1.5 kg additional concentrate plus mineral mixture. Mastitis can be prevented by antiseptic udder wash and iodophor teat dips. Weekly copper [तांबा] sulfate (5%) footbaths control foot rot. Cold stress [ठंड के कारण होने वाला तनाव] lowers fertility, so estrus must be closely monitored, ensure timely artificial insemination [कृत्रिम गर्भाधान], and pregnancies confirmed within 60-90 days. 99 ``` ---- **ICAR Kharif Agro-Advisories for Farmers** ``` Artificial Insemination [कृत्रिम गर्भाधान] (AI) should be continued in consultation with veterinary officer on door-to-door basis rather than direct visit to the dispensaries. To maintain productivity and improve immune status of animals, it is suggested for regular supplementation of mineral- 60g/ day in adult dairy [दुग्ध व्यवसाय] animals and 20-30g in small ruminants. Also, administer deworming medication. Oﬀer clean and cool water three times a day. In case of injury in lactating cows, apply Himex ointment. In case of temporary shortage of availability of green fodder [हरा चारा] or concentrate feed [संकेन्द्रित आहार] farmers can prepare home-made feed by using grain [अन्न] like wheat [गेहूं], maize [मक्का], wheat [गेहूं] bran, oilcakes and salt. Theycanalsopreparesilagefortheiradultdairyanimals. Duetoincreasedmaximum temperatures, goats should be kept in shaded areas and given clean, fresh water three times daily. Vaccinate goats against PPR (Pestedes Petits Ruminants), Contagious Pneumonia, and ETV (Enterotoxaemia). Also, implement control measures for ticks and 137 ICAR Kharif Agro-Advisory [कृषि सलाह] 2025 lice. To control ectoparasites, apply Butox or Cleaner @ 2 ml/L of water over the animal's body, ensuring the mouth is covered during application. Use smoke in animal shelters to keepawaymosquitoesandotherinsects. Poultry [पोल्ट्री पालन] ``` ---- **ICAR Rabi Agro-Advisories for Farmers 2025** ``` Clean and managed cattle shed gradually introducing fodder [चारा] and supplements after two weeks. Vaccinate against FMD, Brucellosis, and Theileriosis in risk areas, deworm before vaccination, and maintain udder hygiene to prevent mastitis. Feeding of green fodder [हरा चारा] to livestock [पशुधन] ## Goat Goats should be provided $1.5 - 2.5$ green fodder [हरा चारा], $200 - 300$ concentrate, and $15 - 20$ mineral mixture daily, with clean water always available. Sheds must be 3-3.5 feet high, dry, and well-ventilated, with $0.5 - 0.75$ for kids, 1-1.5 sq. m for adults, and 2-3 sq. m outdoor space. Vaccinate against PPR and goat pox, and deworm every 3-4 months. ``` ---- **ICAR Rabi Agro-Advisories for Farmers 2025** ``` To protect animals from the weather [मौसम] fluctuations, keep them in well-ventilated shelters that provide warm and dry conditions. Use thick bedding (straw, sawdust, dry grass) to insulate animals from cold floors. Avoid dampness and drafts, cover openings with gunny bags or plastic sheets. Ensure sunlight exposure during the day for warmth and hygiene. Restrict the movement of visitors to the livestock [पशुधन] farms and practice biosecurity measures [जैव सुरक्षा उपाय] in case of disease [रोग] outbreaks. Keep sufficient feed, fodder [चारा], and medicine in hand. Vaccinate animals against Foot and Mouth Disease [रोग] (Cows and buffaloes) and PPR (goats). Monitor for signs of pneumonia, diarrhoea, and frostbite, especially in young and aged animals. Except for pregnant animals, deworm all animals for external and internal parasites. Offer lukewarm water to prevent cold shock and ensure proper intake. Increase energy-rich feed (like grains, oil cakes) to meet higher metabolic needs. Feed roughages (hay, silage [साइलेज]) to maintain body temperature [तापमान] through rumination. Provide molasses and mineral mixtures to boost energy and immunity. Supplement with an herbal immune-boosting product in a ratio to boost immunity. Observe and detect oestrus and inseminate on time. Offer ample milk or electrolyte [इलेक्ट्रोलाइट] water to newborn calves to prevent dehydration [निर्जलीकरण] and death of neonatal stocks. Keep newborns and calves/kids/Lambs in warm pens. Use heat lamps or jackets for weak animals. Maintain clean, well-ventilated shelters with proper drainage to prevent diseases from high humidity [आर्द्रता] conditions. Ensure adequate space: Overcrowding causes stress and disease [रोग] outbreaks. All dead animals should be disposed of hygienically and should not be thrown in nearby drainage, water bodies, etc. Burial Pit should be of 8 × 9 feet. Sprinkling of disinfectants like bleaching powder, quick lime [चूना], etc., in the affected areas helps in reducing the spread of diseases. Clean, safe, hygienic water should be provided to the animals. Restrict the transportation [परिवहन] of animals to consumers' doorsteps for milking. # Dairy [दुग्ध व्यवसाय] ``` ---- **ICAR Kharif Agro-Advisories for Farmers** ``` ICAR Kharif Agro-Advisory [कृषि सलाह] 2025 Maintaining an emergency stock of dry fodder [सूखा चारा] and concentrates is crucial for ensuring uninterrupted animal nutrition [पशु पोषण] during unforeseen weather [मौसम] events such as heavy snowfall. Green ¹⁄ and 2⁄ dry fodder [सूखा चारा] should constitute the total fodder [चारा] requirement of the animal. Concentrate feed [संकेन्द्रित आहार], 1 kg per 2.5 liters of milk produced in cattle should be provided to fulfill their nutritional needs. Avoid sudden change in feed and fodder [आहार और चारा], change should be gradual so that animal can adopt to the new ration without experiencing any health issue. Commercially available mineral mixture at the rate of 60g per animal should be incorporated in the ration to meet the daily requirement of the minerals. However, it should be discontinued once pregnant animals are dried off, to reduce risk of milk fever post calving. A strategic deworming schedule should be followed to prevent development of anthelmintic résistance. This involves deworming animals based on parasite [परजीवी] risk and fecal egg counts rather than routine blanket treatments. Rotating between classes of anthelmintics and targeting high-risk animals helps preserve the efficacy of dewormers, ensuring long-term parasite [परजीवी] control and minimizing drug resistance in the herd. Follow proper biosecurity measures [जैव सुरक्षा उपाय] to prevent outbreak of any disease [रोग]. This is crucial for preventing the introduction and spread of infectious diseases within a herd. It includes controlling the movement of animals, people, and equipment; maintaining cleanliness and disinfection routines; quarantining new or sick animals; and regularly monitoring animal health [पशु स्वास्थ्य]. Use of corrosive chemicals for disinfection should be discouraged as it can increase the risk of lameness in animals. For prevention of mastitis, it is essential to use both pre- and post-milking teat dips. Consistent use of quality teat dips, along with proper milking hygiene, plays a key role in maintaining udder health and reducing mastitis incidence and ensuring production of clean and hygienic milk for human consumption. For prevention of malignant catarrhal fever sheep should never be cohoused with cattle. ``` ---- **ICAR Rabi Agro-Advisories for Farmers 2025** ``` During winter, adult animals and young stock should be provided with protective coverings such as blankets, gunny bags, or sacks to prevent heat loss. Rubbing animals and offering warm fluids, calcium [कैल्शियम] solutions, or liver tonics helps prevent hypothermia. Cold water baths should be avoided; animals can be cleaned with a cloth or soft brush. Calves, especially those fewer than three weeks old, require extra care with warm water baths, heat lamps, and blankets. Thick, dry straw or sawdust in resting areas insulates them, while additional milk or milk replacer compensates for energy used to maintain warmth. Prevent mastitis through complete milking, germicidal teat dips, and udder care. Winter is ideal for deworming, vaccination, and providing sunlight exercise to maintain health and productivity. ## Goat and Sheep Sheep and goats are highly sensitive to cold and damp conditions, making proper housing and dry bedding essential during winter. Each animal should have at least 1 m² floor space with non-slippery flooring, covered with hay, straw, or husk [भूसा] for insulation. Young lambs and kids should 300 ``` | M15: 1 | N15: 1 | O15: Number are and names are not translated completly, and incompleteness in response | P15: Completed | Q15: 2 | R15: Needs Re-evaluation | S15: In QID 120-1, concerning cow udder swelling treatment in Amravati, the response infers mastitis without source backing and leaves numerical values untranslated. Stage 2 flipped Citation Accuracy to 0 due to untranslated numbers and ungrounded inference. This major Citation Accuracy flip requires a Score of 2 (Needs Re-evaluation). Re-evaluate Citation Accuracy and Translation Accuracy. | T15: updated
A16: 121 | B16: 121-1 | C16: కోజికోడ్ మండి‌లో ఆలుగడ్డల ప్రస్తుత మార్కెట్ ధరలు ఏమిటి? | D16: కోజికోడ్ మండిలో ఆలుగడ్డల ప్రస్తుత ధరలు ఇలా ఉన్నాయి: - **కోజికోడ్ ఏ.పి.ఎం.సి (Yard ౧):** మోడల్ ధర ₹౭,౮౨౦ ప్రతి క్వింటల్ (కనిష్ట: ₹౭,౪౮౦, గరిష్ట: ₹౮,౧౬౦). ఇది ౧౦ గంటల క్రితం నమోదైన ధర. - **కోజికోడ్ హోల్‌సేల్ హబ్:** మోడల్ ధర ₹౭,౫౮౫ ప్రతి క్వింటల్ (కనిష్ట: ₹౭,౧౦౬, గరిష్ట: ₹౮,౦౭౮). ఇది ౧౦ గంటల క్రితం నమోదైన ధర. **మూలం: మండి ధరలు** మీకు ఇతర పంటల ధరల గురించి తెలుసుకోవాలని ఉందా? | E16: 3 | F16: 1 | G16: 1 | H16: 1 | I16: 2 | J16: 3 | K16: 3 | L16: [tool:get_mandi_prices] **Mandi Price Discovery** [Today's Date: Monday, 25 May 2026] Commodity: Potato Market: Kozhikode APMC — Yard 1 (mock), Kozhikode, Kerala Price: Rs./Quintal 7820 (Min: 7480, Max: 8160) 10 hours ago --- Commodity: Potato Market: Kozhikode wholesale hub (mock), Kozhikode, Kerala Price: Rs./Quintal 7585 (Min: 7106, Max: 8078) 10 hours ago [tool:search_commodity] ### Commodity matches for `Potato` | Commodity | Matched Term (Score) | Code | |---|---|---| | **Potato** | potato (100%) | `24` | | **Chikoos(Sapota)** | sapota (80%) | `58` | | **Tomato** | tomato (80%) | `65` | | **Duster Beans** | Tomato (80%) | `135` | | **Sweet Potato** | sweet potato (75%) | `124` | [tool:search_commodity] ### Commodity matches for `ఆలుగడ్డ` | Commodity | Matched Term (Score) | Code | |---|---|---| | **Ginger Seed** | ఆలుగడ్డ బీజం (79%) | `481` | | **Egg** | గుడ్డ (76%) | `314` | [tool:forward_geocode] Kozhikode, Kerala, India (Latitude: 11.245, Longitude: 75.775) | M16: 1 | N16: 1 | O16: Number are and names are not translated completly, and incompleteness in response | P16: Completed | Q16: 2 | R16: Needs Re-evaluation | S16: In QID 121-1, for potato prices in Kozhikode mandi, Stage 2 flagged raw untranslated numerical figures that reduce readability. The resulting Citation Accuracy flip (1→0) between stages indicates an unverified evaluation. This scoring inconsistency requires a Score of 2 (Needs Re-evaluation). Re-evaluate Citation Accuracy and Translation Accuracy. | T16: updated
A17: 122 | B17: 122-1 | C17: గోండియా ప్రాంతంలో ద్రాక్షకు ఏ సేంద్రీయ ఎరువును ఉపయోగించాలి? | D17: గోండియా ప్రాంతంలో ద్రాక్ష సాగు కోసం ప్రత్యేకంగా సేంద్రీయ ఎరువుల వివరాలు అందుబాటులో లేవు, కానీ సాధారణంగా ద్రాక్ష తోటల ఆరోగ్యం కోసం ఈ క్రింది సూచనలు పాటించవచ్చు: * **సేంద్రీయ పదార్థాల వినియోగం:** మట్టి ఆరోగ్యాన్ని మరియు నీటి నిల్వ సామర్థ్యాన్ని పెంచడానికి బాగా కుళ్ళిన పశువుల ఎరువు (FYM) లేదా కంపోస్ట్ ఉపయోగించండి. * **జీవ నియంత్రణ:** మట్టిలోని హానికరమైన శిలీంధ్రాలను నివారించడానికి ట్రైకోడెర్మా (Trichoderma) వంటి జీవ నియంత్రకాలను ఉపయోగించడం మంచిది. * **పోషకాల నిర్వహణ:** ద్రాక్ష మొక్కలలో పొటాష్ (Potash) లోపాన్ని గమనించి, అవసరమైనప్పుడు తగిన ఎరువులను అందించండి. * **తోట నిర్వహణ:** కలుపు మొక్కలను మరియు వ్యర్థాలను తొలగించడం ద్వారా శిలీంధ్ర మరియు బాక్టీరియా వ్యాధుల ముప్పును తగ్గించవచ్చు. మరింత ఖచ్చితమైన ఎరువుల మోతాదు కోసం మీ ప్రాంతంలోని మట్టి పరీక్ష (Soil Test) చేయించి, దాని ఆధారంగా ఎరువులను వాడటం ఉత్తమం. **మూలం: ఐ.సి.ఎ.ఆర్ (ICAR) వ్యవసాయ సలహాలు** మీరు మీ తోట కోసం మట్టి ఆరోగ్య కార్డు (Soil Health Card) స్థితిని తనిఖీ చేయాలనుకుంటున్నారా? | E17: 3 | F17: 1 | G17: 1 | H17: 1 | I17: 4 | J17: 4 | K17: 4 | L17: [tool:search_documents] > Search Results for `organic fertilizers for grapes in Gondia region` **ICAR Kharif Agro-Advisories for Farmers** ``` Fertilizer Application [उर्वरक देना]: Grow green manure crops [हरित खाद फसलें] (Dhaincha, Sunhemp, Pillipesara and Cowpea [लोबिया]) as preceding crop [फसल] to Paddy and apply soil test [मृदा परीक्षण]-based fertilizers. The entire dose of phosphorus fertilizer [फॉस्फोरस उर्वरक] should be applied during the final puddling [कीचड़ाई] stage. In heavy soils, the full dose of potash fertilizer [उर्वरक] should be applied at the final puddling [कीचड़ाई]. In light [प्रकाश] soils, half the dose should be applied during puddling [कीचड़ाई] and the remaining half at the panicle initiation [गुच्छिका प्रारंभ] stage. Weed Control [खरपतवार नियंत्रण]: In wet direct-seeded rice [प्रत्यक्ष बुवाई विधि से धान की खेती] fields, within 3-5 days of sowing [बुवाई], apply Pyrazosulfuron-ethyl 10% WP @ 250 g/ha or use Pretilachlor + Safener 37% EW @ 1500 ml/ha mixed with 50 kg of dry sand and broadcast evenly over the field [खेत]. In transplanted paddy fields, within 3-5 days of planting, when the field [खेत] has shallow standing water, apply either Pyrazosulfuron-ethyl 10% WP @ 200 g/ha mixed with 50 kg sand, or Butachlor 50% EC @ 2.5-3.12 litres/ha, or Pretilachlor 50% EC 1000 ml/ha. If the field [खेत] has a heavy infestation of grassy, sedge and broadleaf weeds [खरपतवार], use Bensulfuron Methyl 0.6% + Pretilachlor 6.0% Granules [कणिका] @ 10 kg/ha mixed with 50 kg sand and broadcast evenly. At 20 days after transplanting [पुनः रोपाई], for grassy weed [घास जैसे खरपतवार] control, apply Cyhalofop-P-butyl 10% EC @ 1000 ml/ha. If weed infestation [खरपतवार का प्रकोप] is high, apply Bispyribac Sodium 10% SL @ 250 ml/ha or Triafamone + Ethoxysulfuron 30% WG at 225 g/ha in 500 liters of water. ``` ---- **ICAR Kharif Agro-Advisories for Farmers** ``` Maharashtra The Kharif season, stretching from June to October, is a crucial agricultural period for the state of Maharashtra, significantly influencing the livelihoods of millions of farmers. Characterized by the onset of the southwest monsoon [मानसून], this season supports the cultivation of key crops such as rice [चावल], cotton [कपास], soybeans, pulses, and millets. However, climate [जलवायु] variability, erratic rainfall, and changing weather [मौसम] patterns pose continuous challenges to sustainable agriculturalproduction. Inthelightofthesechallenges, the Kharif 2025 Agro-Advisoryaims to provide timely, region-specific, and science-based recommendations to empower farmerswiththeknowledgeneededtomakeinformeddecisions. REGIONAL ADVISORY Maharashtra is divided into several agroclimatic zones, each with unique characteristics influencing crop selection [फसल चयन], sowing [बुवाई] windows, and input management. The following region-wise advisories aim to support farmers with tailored recommendations for improved productivity and resilience. VIDARBHA REGION The Vidarbha region of Maharashtra is composed of Bhandara, Chandrapur, Gondia Gadchiroli, Nagpur, Amravati, Akola, Yavatmal, Buldhana, Wardha, Washim and possesses state agricultural university viz., Dr. Panjabrao Deshmukh Krishi Vidyapeeth, Akola. Soil Testing [मृदा परीक्षण] & Preparation (All Crops) Soil testing [मृदा परीक्षण] is crucial for effective fertilizer management [उर्वरक प्रबंधन], optimizing input use, and maintaining soil fertility [मृदा उर्वरता]. For proper soil sampling [मृदा नमूना लेना], the recommended depths are 15- 20 cm for crops like sorghum [ज्वार], rice [चावल], groundnut [मूंगफली], and wheat [गेहूं]; 30 cm for cotton [कपास], sugarcane [गन्ना], and banana [केला]; and 30 cm for fruit trees, sampled from a distance of 1-1.5 feet from the trunk. Additionally, applying decomposers to crop [फसल] residues like straw and leaves enhances organic matter content [जैविक पदार्थ की मात्रा], improves soil structure [मृदा संरचना], and boosts water retention [पानी धारण क्षमता], contributing to sustainable agricultural practices [कृषि पद्धतियाँ]. ICAR Kharif Agro-Advisory [कृषि सलाह] 2025 CEREALS CROPS Paddy ``` ---- **ICAR Kharif Agro-Advisories for Farmers** ``` Late Nursery [नर्सरी] Planting: Parthiva, Bapatla Masoori, Teja, Bhavapuri Sannalu, Maruteru Masoori. BPH-Prone Areas: Maruteru Samba & Maruteru Masoori, MTU 1271, Bapatla Masoori, BPT 2846, Parthiva. Saline Soils: Nellore Masoori, Panduranga, MCM Rice [चावल] 103. Late Planting: MTU 1293, NLR 3238, Nellore Masoori, Cotton [कपास] Dora Sannalu, Chandara. Scarce Rainfall Zone: Nellore Sona, Masoori, Siri, NLR 3238, Samba Masoori, BPT 2841, 2846, Varam, Maruteru Samba & Maruteru Masoori, MTU 1271, MCM Rice [चावल] 103, Nandyala Sona. Late Nursery [नर्सरी] Planting: Bapatla Masoori, Bhavapuri Sannalu, Maruteru Masoori. BPH-Prone Areas: Maruteru Samba & Masoori, MTU Rice [चावल] -1271, Bapatla Masoori, BPT Rice [चावल]- 2846, Parthiva, Nandyala Sona. Andhra Pradesh Late Planting: Samba Masoori, Nandyala Sannalu, MTU Rice [चावल]-1293, NLR Rice [चावल] -3238, Nellore Masoori, Cotton [कपास] Dora Sannalu, Chandra. Fertilizer Application [उर्वरक देना]: Grow green manure crops [हरित खाद फसलें] (Dhaincha, Sunhemp, Pillipesara and Cowpea [लोबिया]) as preceding crop [फसल] to Paddy and apply soil test [मृदा परीक्षण]-based fertilizers. The entire dose of phosphorus fertilizer [फॉस्फोरस उर्वरक] should be applied during the final puddling [कीचड़ाई] stage. In heavy soils, the full dose of potash fertilizer [उर्वरक] should be applied at the final puddling [कीचड़ाई]. In light [प्रकाश] soils, half the dose should be applied during puddling [कीचड़ाई] and the remaining half at the panicle initiation [गुच्छिका प्रारंभ] stage. ``` ---- **ICAR Kharif Agro-Advisories for Farmers** ``` Grapes [अंगूर] Maintain a well-aerated canopy [पर्णछाया] to reduce humidity [आर्द्रता] within the vineyard and improve air circulation. Monitor for any nutrient deficiencies, particularly potassium [पोटाश], and apply appropriate fertilizers as needed. Keep the orchard clean by removing weeds [खरपतवार] and debris to prevent fungal and bacterial diseases. Ensure proper drainage and prevent waterlogging [पानी भराव]. The vigorous varieties of grapes [अंगूर] the tendrils and the twins may be pruned. Management of April pruning [फ枝剪ाई] in grape orchard should be done as per availability of water. During rest period, provide only need based irrigation [सिंचाई] to protect the existing leaves from drying [सूखाना], and also contribute towards increasing the reserves of the vines [बेलें] through photosynthetic activity. Care should be taken to reduce/stop the water in case new growth is observed on the shoot. KHANDESH/ NORTHERN MAHARASHTRA This region of Maharashtra is comprised of Jalgaon, Dhule, Nandurbar, Nashik). Rainfall of the region is 600-900 mm and it has Medium to deep black soils. This region has state agricultural university viz., Mahatma Phule Krishi Vidyapeeth, Rahuri, Ahmednagar (M.S) COMMERCIAL CROPS Cotton [कपास] ``` ---- **ICAR Kharif Agro-Advisories for Farmers** ``` Mango [आम] Preferably Marathwada Keshar variety should be selected for plating in Marathwada region. Organic [जैविक] mulching [मल्चिंग] should be done and the orchard should be irrigated during early in the morning, at evening or during night hours. To protect the mango [आम] fruits from the incidence of fruit fly [फलों की मक्खी], install "Rakshak fruit fly trap [फलों की मक्खी का जाल]" developed by university @ 4 traps [फंदे] per hectare. Fallen fruits should be collected and destroyed to keep orchard clean. Fruit fly [फलों की मक्खी] lays its eggs in Advisory services for Mango [आम] fruit orchard visit the fruits below outer cover of the fruit when the fruit is about to mature. The larvae develop on the pulp of the fruit. Hence, the infested fruits should be destroyed. The soil [मिट्टी] should be ploughed below the tree. After harvesting of mango [आम], one spray of Hexaconazole fungicideshouldbetaken@ 10 ml/10 Lofwaterforpreventionofblight. Banana [केला] Sword suckers of 3-4 months age with 450 to 750 g should be used for plantation of Banana [केला]. For protection of banana [केला] orchard from hot air, make use of green net in southwest direction of orchard. Earthing up [मिट्टी चढ़ाना] should be done in banana [केला] orchard. Provide shade to newly planted or small plants to protect them from high temperature [तापमान]. Organic [जैविक] mulching [मल्चिंग] should be done in banana [केला] orchard. Irrigate banana [केला] orchard during early in the morning, at evening or during night time. ICAR Kharif Agro-Advisory [कृषि सलाह] 2025 Grapes [अंगूर] Management of April pruning [फ枝剪ाई] in grape orchard should be done as per availability of water. During rest period, provide only need based irrigation [सिंचाई] to protect the existing leaves from drying [सूखाना], and also contribute towards increasing the reserves of the vines [बेलें] through photosynthetic activity. Care should be taken to reduce/stop the water in case new growth is observed on the shoot. If rainfall exceeds 2.5 mm, no irrigation [सिंचाई] should be applied especially during rest period. Custard Apple [सीताफल] ``` ---- **ICAR Kharif Agro-Advisories for Farmers** ``` Pest [कीट] & Disease Management [रोग प्रबंधन]: Early shoot borer [शिखर छेदक कीट]: Remove and destroy infested shoots; apply Chlorantraniliprole or Carbofuran [कार्बोफ्यूरान] granules [कणिका] in affected furrows. Top shoot borer [शिखर छेदक कीट]/ White grub: Apply Trichoderma [ट्राइकोडर्मा] or Beauveria bassiana [ब्यूवेरिया बासियाना] in soil [मिट्टी] and spray Chlorpyrifos if needed. Maharashtra Redrot: Use resistant varieties [प्रतिरोधी किस्में] and avoid ratooning affected crops. First earthing up [मिट्टी चढ़ाना] at 45- 60 DAS; final at 90-120 DAS to provide support and prevent lodging [गिरना]. Mulch inter-row spaces with cane trash to conserve moisture and suppress weeds [खरपतवार]. Grow short-duration legumes(moong, urad) inearlystageforadditionalincomeandnitrogenfixation. FRUIT & VEGETABLE CROPS Citrus For new plantation of citrus (Sweet Orange [संतरा] and Lemon [नींबू]), well-drained soil [मिट्टी] with less than 10 % free lime [चूना] should be selected. Use quality and disease [रोग]-free planting material from registered nurseries for new plantation. Sweet Orange [संतरा] crop [फसल] should be planted at 6 x 6 m spacing [अंतर] accommodating 277 plants per hectare. Only one bahar either Ambiya or Mrig should be taken based on water availability for higher yield [उत्पादन] and more life of sweet orange [संतरा] orchard. Irrigation management [सिंचाई प्रबंधन] should be done in Ambia Bahar to citrus orchard. Take a spray of potassium [पोटाश] nitrate @ 15 gm per litre of water. Application of Bordo paste (1:1:10) should be done on tree trunk before onset of monsoon [मानसून] to protect the crop [फसल] from gummosis and dieback [शिखर मर]. Application of Trichoderma [ट्राइकोडर्मा] viride, Pseudomonas [स्यूडोमोनास एक सामान्य संक्रामक जीव] fluorescence, Glomas mycorrhiza [मायकोराइजा] @ 100 g each in 1 kg compost [कम्पोस्ट] with 200 g Ferrous Sulphate and Zinc Sulphate [जिंक सल्फेट] to each gummosis affected plant. For management of fruit sucking moth, adopt Integrated Pest Management [समेकित कीट प्रबंधन] practice which include, destruction of weed host, applying smoke, collection and destruction of fallen fruits, use of light trap [प्रकाश फंदा], use of poison baits, covering tree with nylon net of 0.5 mesh and spraying [छिड़काव] of Horticulture [उद्यानविद्या] Mineral Oil @ 500 ml/ ha, etc. ``` ---- **ICAR Rabi Agro-Advisories for Farmers 2025** ``` ICAR Rabi Agro-Advisory [कृषि सलाह] 2025 aquaculture [जलीय कृषि], particularly shrimp farming [कृषि करना], also plays a significant role in supporting coastal livelihoods. Sustainable fishing practices such as avoiding juvenile catch, observing closed seasons, and using recommended mesh sizes are essential to conserve marine resources [समुद्री संसाधन]. Farmers engaged in aquaculture [जलीय कृषि] should adopt proper pond preparation, seed [बीज] stocking at optimal densities, regular water quality monitoring, and balanced feeding to maximize yield [उत्पादन] and profitability. Strengthening fish value chains through hygienic handling, cold storage [शीतगृह], and cooperative marketing can further enhance income opportunities for coastal communities. # WESTERN MAHARASHTRA (DESH REGION) &amp; KHANDESH REGION The Western Maharashtra (Desh region), comprising Pune, Satara, Sangli, Kolhapur, and Solapur districts &amp; Khandesh region, comprising Nashik, Dhule, Ahmednagar, Jalgaon &amp; Nandurbar Districts, Western Maharashtra receives moderate rainfall ranging from 500-900 mm annually. The soils here are predominantly black to medium black and well-drained, making them suitable for both field [खेत] and horticultural crops. Major crops grown in this region include cereals like sorghum [ज्वार] and wheat [गेहूं]; pulses such as chickpea [चना] and oilseeds like safflower [कुसुम] and linseed [अलसी]. Sugarcane [गन्ना] is an important commercial crop [फसल] widely cultivated in this zone. The region also excels in horticulture [उद्यानविद्या], producing high-value fruit crops such as pomegranate [अनार], banana [केला], and grapes [अंगूर], along with vegetables like onion [प्याज], tomato [टमाटर], and brinjal [बैंगन]. ## Cereal [अनाज] crops ### Sorghum [ज्वार] ``` ---- **ICAR Kharif Agro-Advisories for Farmers** ``` Insect [कीट]-pest management [कीट प्रबंधन]: Do early sowing [बुवाई] to reduce damage by early shoot borer [शिखर छेदक कीट]. Use Tricho-cards for the control of borers. Do not plant sugarcane [गन्ना] for one year and three years for control of red rot and wilt [मुरझाने का रोग], respectively in diseased fields. To control red rot diseases, use seed [बीज] from absolutely disease [रोग]-free seed [बीज] plot. Rogue out and bury the diseased canes. Uproot the entire clumps and not merely the affected stalks. Do not ratoon the diseased crop [फसल]. FRUIT CROPS Kinnow To ameliorate zinc [जिंक] and manganese deficiency [मैंगनीज की कमी] in kinnow, spray the plants with zinc sulphate [जिंक सल्फेट] (4.7 g/litre of water) + manganese [मैंगनीज] sulphate (3.3 g/litre of water) during mid August. Foliar application [पत्तियों पर छिड़काव] should be given to the fully developed flushes. A gap of one week should be kept between the foliar application [पत्तियों पर छिड़काव] of Bordeaux mixture and zinc sulphate [जिंक सल्फेट] and manganese [मैंगनीज] sulphate solution. Manage fruit drop [फल झड़ना] by spraying [छिड़काव] GA (10 mg /litre of water) + Copper [तांबा] oxychloride 50 WP (3 g per litre of water) in August and September. Collect and destroy the mummified fruits on the trees as well as the fallen fruits by deep burying. Three foliar sprays of 1.0 % potassium [पोटाश] nitrate (10 g/litre of water) can be given at the end of May, June and July to improve fruit size and increase yield [उत्पादन]. Citrus Psylla [नींबू वर्गीय सायला] which is a vector for Citrus Greening disease [सिट्रस ग्रीनिंग रोग] can be managed by spraying [छिड़काव] 200 ml Crocodile/ Confidor 17.8 SL (imidacloprid) or 160 g Actara/ Dotara Pathological fruit drop [फल झड़ना] in kinnow Gummosis/foot rot in kinnow Scab [खुरड रोग] in kinnow Punjab ``` ---- **ICAR Kharif Agro-Advisories for Farmers** ``` Black gram [उड़द] The recommended seed rate [बीज दर] is 15-20 kg/ha with a spacing [अंतर] of 30×10 cm. Seeds should be treated with Trichoderma [ट्राइकोडर्मा] at 5 g/kg along with Rhizobium [राइजोबियम] and PSB at 25 g/kg each. Apply fertilizers at a rate of 20:40 kg N:P per hectare. Intercropping [अंतरफसल] with pigeon pea [अरहर] and other kharif crops [खरीफ फसलें] is advised for better resource utilization. Irrigation [सिंचाई] should be provided at critical stages such as flowering and pod [फली] filling to ensure healthy growth and yield [उत्पादन]. FRUIT & VEGETABLE CROPS Pomegranate [अनार] (Mrig Bahar) Pomegranate [अनार] cultivation during Mrig Bahar requires pruning [फ枝剪ाई] to remove diseased branches, followed by an application of 1% Bordeaux mix. Pre- flowering fertilization [फलधारण] includes 700 g urea [यूरिया], 1600 g SSP, and 400 g MOP per tree. Dusting with 4% copper [तांबा] dust or bleaching powder helps in disease [रोग] prevention. Regular pest control [कीट नियंत्रण] with Azadirachtin or alternate insecticides [कीटनाशक] every 15 days is crucial. At the fruiting stage, apply 500 g DAP + 100 g MOP per tree at the lemon [नींबू] size stage, and 200 g 19:19:19 + 100 g MOP at the guava [अमरूद] size stage. Maharashtra Grape After pruning [फ枝剪ाई], grapevines are treated with Hydrogen Cyanamide (30-40 ml/L) on the top 2-3 buds to encourage growth. GA sprays of 10 ppm are applied 17-18 days after pruning [फ枝剪ाई], followed by 15 ppm after 4-5 days. Mealybug [मैलिबग] control in September involves removing bark and spraying [छिड़काव] Methomyl 40 SP at 1 g/L Banana [केला] ``` ---- **ICAR Kharif Agro-Advisories for Farmers** ``` Onion [प्याज] (Kharif) For effective nursery [नर्सरी] preparation, raise beds enriched with FYM, copper [तांबा] oxychloride, and a balanced mixed fertilizer [उर्वरक]. Prior to sowing [बुवाई], treat seeds with Thiram or Carbendazim at 2-3g/kg to prevent fungal infections. Apply Basalin at 25ml per 10 L of water as a pre-emergence herbicide [अंकुरण पूर्व खरपतवारनाशी] for effective weed control [खरपतवार नियंत्रण]. At planting, use a fertilizer [उर्वरक] dose of 100:50:50 NPK, with 50:50:50 applied at sowing [बुवाई] and the remaining 50?N at 45 days after transplanting [पुनः रोपाई] (DAT). To manage fungal diseases, integrate Trichoderma [ट्राइकोडर्मा] along with regular fungicide [फफूंदनाशी] sprays every 10-15 days. For thrips [फूलकीड़े] control, install sticky traps [फंदे] and use Profenofos, Fipronil, or Spinosad as required based on pest [कीट] observation. KONKAN REGION Konkan Region of Maharashtra is comprised of Mumbai, Mumbai Suburban, Thane, Palghar, Raigad, Ratnagiri, Sindhudurg). The region has high rainfall (3000- 4000mm) and has Lateritic, acidic, high organic matter [जैविक पदार्थ]. This region possesses a state agricultural university viz., Dr. Balasaheb Sawant Konkan Krishi Vidyapeeth, Dapoli. CEREAL [अनाज] CROPS Rice [चावल] Rice [चावल] nursery [नर्सरी] sowing [बुवाई] should begin with the onset of monsoon [मानसून] showers, typically in the first to the second week of June. It is crucial to select suitable varieties like Ratnagiri-1, Karjat-3, Karjat-4, and Sahyadri based on local climatic conditions and market demand. For one hectare of the main field [खेत], approximately 60-75 kg of seed [बीज] is required, and a nursery [नर्सरी] area of around 1000 m² should be prepared. Soak rice [चावल] seeds in water for 24 hours, followed by incubation for 24-36 hours. Treat the seeds with fungicides [फफूंदनाशी दवाएँ] like Carbendazim (2g/kg seed [बीज]) or biocontrol agents [जैव नियंत्रण कारक] such as Trichoderma [ट्राइकोडर्मा] ``` [tool:search_terms] Matching Terms for `సేంద్రీయ ఎరువులు` Organic fertilization -> जैविक खाद (jaivik khaad) [93%] Organic produce -> जैविक उत्पादन (jaivik utpadan) [73%] Organic livestock farming -> जैविक पशुधन खेती (jaivik pashudhan kheti) [72%] Organic Seeds -> जैविक बीज (jaivik beej) [71%] Organic standards -> जैविक मानक (jaivik manak) [71%] [tool:search_terms] Matching Terms for `ద్రాక్ష` Grape Vine -> अंगूर की बेल (angoor ki bel) [100%] Grapes -> अंगूर (angoor) [100%] Raisin -> किशमिश (kishmish) [70%] | M17: 1 | N17: 1 | P17: Completed | Q17: 4 | R17: Accept | S17: The evaluator's assessment fully aligns with Stage 3 guidelines and tool output. Rubric scores assigned in earlier stages are consistent and accurate. No corrections or re-evaluations are required. | T17: updated
A18: 123 | B18: 123-1 | C18: కోజికోడ్‌లో యాపిల్స్‌కు ప్రస్తుత మార్కెట్ ధరలు ఎంత ఉన్నాయి? | D18: కోజికోడ్‌లోని మార్కెట్లలో యాపిల్ ధరలు ఈ క్రింది విధంగా ఉన్నాయి: * **కోజికోడ్ ఏ.పి.ఎం.సి — యార్డ్ ౧:** మోడల్ ధర ₹౫౦౬౨ ప్రతి క్వింటల్ (కనిష్ట: ₹౪౬౮౦, గరిష్ట: ₹౫౪౪౪) - ౧౦ గంటల క్రితం. * **కోజికోడ్ హోల్‌సేల్ హబ్:** మోడల్ ధర ₹౪౯౧౦ ప్రతి క్వింటల్ (కనిష్ట: ₹౪౪౪౬, గరిష్ట: ₹౫౩౮౯) - ౧౦ గంటల క్రితం. **మూలం: మండి ధరలు** మీకు వేరే పంట ధరల గురించి తెలుసుకోవాలనుందా? | E18: 1 | F18: 1 | G18: 1 | H18: 1 | I18: 1 | J18: 1 | K18: 1 | L18: [tool:get_mandi_prices] **Mandi Price Discovery** [Today's Date: Monday, 25 May 2026] Commodity: Apple Market: Kozhikode APMC — Yard 1 (mock), Kozhikode, Kerala Price: Rs./Quintal 5062 (Min: 4680, Max: 5444) 10 hours ago --- Commodity: Apple Market: Kozhikode wholesale hub (mock), Kozhikode, Kerala Price: Rs./Quintal 4910 (Min: 4446, Max: 5389) 10 hours ago [tool:forward_geocode] Kozhikode, Kerala, India (Latitude: 11.245, Longitude: 75.775) [tool:search_commodity] ### Commodity matches for `Apple` | Commodity | Matched Term (Score) | Code | |---|---|---| | **Apple** | apple (100%) | `17` | | **Pineapple** | pineapple (78%) | `21` | | **Coffee** | kappi (75%) | `41` | | **Ox** | kaale (75%) | `172` | | **Wood Apple** | wood apple (75%) | `428` | | M18: 1 | N18: 1 | O18: Number are and names are not translated completly, and incompleteness in response | P18: Completed | Q18: 1 | R18: Reject | S18: In QID 123-1, Stage 2 documented untranslated numerals and missing source details. The scoring diverges severely across Accuracy/Completeness, Translation Accuracy, Grammar & Fluency, Language Purity, and Citation Accuracy (1→0 flip). This level of multi-rubric inconsistency renders the review invalid, requiring a Score of 1 (Reject). Reject the review and conduct a full re-evaluation. | T18: updated
A19: 124 | B19: 124-1 | C19: కొచ్చి మార్కెట్‌లో ఆపిల్స్‌కు ప్రస్తుత మార్కెట్ ధరలు ఏమిటి? | D19: కొచ్చి మార్కెట్‌లో ఆపిల్ ధరలు ఈ విధంగా ఉన్నాయి: * **కొచ్చి ఏ.పి.ఎం.సి — యార్డ్ ౧:** మోడల్ ధర ₹౫౦౩౬ ప్రతి క్వింటల్ (కనిష్ట: ₹౪౭౮౦, గరిష్ట: ₹౫౨౯౨). ఇది ౧౦ గంటల క్రితం నమోదైన ధర. * **కొచ్చి హోల్ సేల్ హబ్:** మోడల్ ధర ₹౪౮౮౪ ప్రతి క్వింటల్ (కనిష్ట: ₹౪౫౪౧, గరిష్ట: ₹౫౨౩౯). ఇది ౧౦ గంటల క్రితం నమోదైన ధర. **మూలం: మండి ధరలు** మీకు ఇతర పంటల ధరల గురించి సమాచారం కావాలా? | E19: 3 | F19: 1 | G19: 1 | H19: 1 | I19: 1 | J19: 1 | K19: 3 | L19: [tool:get_mandi_prices] **Mandi Price Discovery** [Today's Date: Monday, 25 May 2026] Commodity: Apple Market: Kochi APMC — Yard 1 (mock), Ernakulam, Kerala Price: Rs./Quintal 5036 (Min: 4780, Max: 5292) 10 hours ago --- Commodity: Apple Market: Kochi wholesale hub (mock), Ernakulam, Kerala Price: Rs./Quintal 4884 (Min: 4541, Max: 5239) 10 hours ago [tool:search_commodity] ### Commodity matches for `Apple` | Commodity | Matched Term (Score) | Code | |---|---|---| | **Apple** | apple (100%) | `17` | | **Pineapple** | pineapple (78%) | `21` | | **Coffee** | kappi (75%) | `41` | | **Ox** | kaale (75%) | `172` | | **Wood Apple** | wood apple (75%) | `428` | [tool:forward_geocode] Kochi, Kerala, India (Latitude: 9.968, Longitude: 76.244) | M19: 1 | N19: 1 | O19: Number are and names are not translated completly, and incompleteness in response | P19: Completed | Q19: 1 | R19: Reject | S19: In QID 124-1, regarding Kochi apple market prices, Stage 2 noted raw untranslated numerical formatting that hinders readability. The resulting swing in Citation Accuracy (1→0) and multi-point drops in Translation Accuracy and Grammar reflect an unverified review. This uncorrected contradiction mandates a Score of 1 (Reject). Reject the evaluation and re-evaluate all formatting and grounding rubrics. | T19: updated
A20: 125 | B20: 125-1 | C20: పర్భణి ప్రాంతంలో జామ పంటకు నీటి నిర్వహణను ఎలా ప్రణాళిక చేయాలి? | D20: పర్భణి ప్రాంతంలో జామ పంటకు నీటి నిర్వహణ కోసం ఈ క్రింది ప్రణాళికను అనుసరించండి: * **ప్రారంభ దశ:** మొక్కలు నాటిన తర్వాత మొదటి ౨-౩ సంవత్సరాల వరకు క్రమం తప్పకుండా నీరు అందించాలి. వేసవి కాలంలో ప్రతి ౭-౧౦ రోజులకు ఒకసారి, శీతాకాలంలో ప్రతి ౧౫-౨౦ రోజులకు ఒకసారి నీరు పెట్టాలి. * **పంట దశ:** పండ్లు అభివృద్ధి చెందుతున్న దశలో తేలికపాటి నీటి సరఫరా (Light irrigation) చేయాలి. అయితే, పండ్లు పక్వానికి వచ్చే సమయంలో అధికంగా నీరు పెట్టవద్దు, దీనివల్ల పండ్లు పగిలే (Fruit cracking) అవకాశం ఉంటుంది. * **తేమ సంరక్షణ:** పొడి ప్రాంతాలలో నీటి అవసరాన్ని ౨౫-౩౦% తగ్గించుకోవడానికి మరియు కలుపు నివారణకు ప్లాస్టిక్ మల్చింగ్ లేదా ఎండుగడ్డితో మల్చింగ్ చేయండి. * **ముందస్తు జాగ్రత్తలు:** నీరు నిల్వ ఉండకుండా సరైన డ్రైనేజీ సౌకర్యం ఉండేలా చూసుకోండి, ఎందుకంటే నీటి నిల్వ వల్ల వేరు కుళ్లు మరియు ఇతర వ్యాధులు వచ్చే అవకాశం ఉంది. **మూలం: ఐ.సి.ఎ.ఆర్ (ICAR) వ్యవసాయ సలహాలు** మీరు జామ తోటలో ఎరువుల మోతాదు గురించి తెలుసుకోవాలనుకుంటున్నారా? | E20: 2 | F20: 1 | G20: 1 | H20: 1 | I20: 2 | J20: 3 | K20: 3 | L20: [tool:search_documents] > Search Results for `irrigation management for guava crop in Parbhani region` **ICAR Kharif Agro-Advisories for Farmers** ``` Irrigation [सिंचाई]: Generally, guava [अमरूद] is a rainfed crop [फसल], but where irrigation [सिंचाई] facilities are available, irrigation [सिंचाई] should be provided to improve yield [उत्पादन] and quality. After transplanting [पुनः रोपाई], continue irrigation [सिंचाई] regularly to reduce plant mortality. Irrigation [सिंचाई] is essential for initial 2-3 years, irrigate at every 7-10 days interval during summer and 15-20 days interval during winters. For winter crop [फसल], start irrigation [सिंचाई] from June month repeat as per requirement during rainy season. Intercultural Operations [अंतरशस्य क्रियाएँ]: After planting, keep removing the weeds [खरपतवार] by hoeing [निराई] until the crop [फसल] becomes strong. For the first three years except the cucurbitaceous vegetables, all types of crops like leguminous crops [दलहनी फसल], leafy vegetables, brinjal [बैंगन], chili, tomato [टमाटर], cabbage [पत्ता गोभी], etc. can be taken. Training and Pruning [फ枝剪ाई]: Mainly, there should not be any branch up to 90 cm from the ground, after this allow 3-4 branches to grow in four directions. When the plant is about 1.25 meters tall, the main branch should be cut to promote branching. Once new branches reach 50 cm, prune to maintain height and repeat this after 2 or 3 years. Remove suckers and water shoots regularly. Crop Management [फसल प्रबंधन] / Bahar Treatment: In guava [अमरूद] three flowering and fruiting seasons occur annually, First Rainy (Mrig bahar), second Autumn (Ambe bahar) and third Winter (Hast bahar). Although the rainy season crop [फसल] produces higher yields, the fruit quality is inferior, therefore, only one winter crop [फसल] per year should be taken. For this make a solution of 100-150 grams of urea [यूरिया] in one liter of water and spray it twice at an interval of 8-10 days at the time of fruit appearance in the month of April- May so that flowers and fruits fall. Mulching [मल्चिंग]: In dry areas, moisture can be conserved by covering the soil [मिट्टी] surface around the plants with plastic mulch [प्लास्टिक मल्चिंग] or hay straw. This reduces water requirement by 25-30 percent and helps in preventing weed growth. ``` ---- **ICAR Kharif Agro-Advisories for Farmers** ``` ENGINEERING Use sub-soiler for deep ploughing [गहरी जुताई]. Cultivate parallel to slope. Tools used are Paddy transplanter [धान रोपाई यंत्र], power weeder [निराई करने वाली मशीन], Cono weeder [निराई करने वाली मशीन]. Size of farm pond [कृषि तालाब]: 20x20x3 m per 2 ha. MARATHWADA REGION Marathwada region of Maharashtra is comprised of Aurangabad, Jalna, Beed, Latur, Osmanabad, Hingoli, Parbhani, Nanded. The region has moderate rainfall (600-800 mm) and has medium to deep black soils. This region possesses state agricultural university viz., Dr. Vasantrao Naik Marathwada Krishi Vidyapeeth, Parbhani. CEREALS CROPS Maize [मक्का] Maize [मक्का] should be sown at 75 x 20 cm or 60 x20 cm as per soil [मिट्टी] type by dibbling [छिद्र बोवाई विधि] method with first onset of monsoon [मानसून] after receiving 75-100 mm rainfall. Improved and high yielding notified varieties or research hybrids should be used for sowing [बुवाई] for achieving higher yield [उत्पादन]. Recommended dose of 100:75:75 kg NPK should be applied to maize [मक्का] out of which 50 % N and full P and K should be given at the time of ICAR Kharif Agro-Advisory [कृषि सलाह] 2025 Maize [मक्का] observation in field [खेत] COMMERCIAL CROPS Cotton [कपास] Cotton [कपास] should be sown after onset of monsoons or after 1³’ June only for effective management of pink bollworm [गुलाबी सुंडी]. Well decomposed FYMshouldbeappliedtocotton @ 10 ton/ha before sowing [बुवाई]. Recommended fertilizerdoseof120:60:60kgNPK/hashould beappliedtorainfedcottonoutofwhich 40% N & complete P & K should be applied as a basal dose [प्रारंभिक मात्रा (उर्वरक की)] at the time of sowing [बुवाई]. Remaining 30 % Nshouldbeappliedafter 30 DASand 30 % after 60 DAS. Use of high yielding, short ``` ---- **ICAR Kharif Agro-Advisories for Farmers** ``` Coconut [नारियल] The recommended variety is Tiptur Tall, with a spacing [अंतर] of 10 m × 10 m, planted during June-July with an average population of 100 palms per hectare. The fertilizer [उर्वरक] dose per 117 ICAR Kharif Agro-Advisory [कृषि सलाह] 2025 palm includes 500 g Nitrogen [नाइट्रोजन], 320 g Phosphorus [फॉस्फोरस], and 1200 g Potassium [पोटाश]. Cocoa is a common intercrop. Micronutrients [सूक्ष्म पोषक तत्व] like boron [बोरॉन] and zinc [जिंक] are applied. Drip irrigation [ड्रिप सिंचाई] is used. Weed management [खरपतवार प्रबंधन] is done by hand weeding [निराई]. Stem bleeding is managed by root feeding with Hexaconazole. Black-headed caterpillar is managed through the release of Goniozus nephantidis, a biological control agent [जैव नियंत्रण कारक]. Banana [केला] Elakki Banana [केला] and G9 are the popular varieties grown in karnataka, apply NPK at 400:240:500 kg/ha along with 40 tons of FYM per hectare before planting. The recommended spacing [अंतर] for Elakki Banana [केला] is 1.5 x 1.5 meters in a triangular shape, accommodating 5,120 plants per hectare, while other banana [केला] varieties should be spaced at ``` ---- **ICAR Rabi Agro-Advisories for Farmers 2025** ``` ICAR Rabi Agro-Advisory [कृषि सलाह] 2025 ## Dairy [दुग्ध व्यवसाय] animal In dairy [दुग्ध व्यवसाय] animals, protect cows and buffaloes from cold winds using tarpaulin or gunny bags, provide warm bedding for calves, supply balanced rations with sufficient fodder [चारा] and concentrates, and ensure timely vaccination against FMD and Lumpy Skin Disease [रोग]. Milking hygiene should be maintained for better milk quality ## Goat For goat farming [कृषि करना], protect kids from cold with straw bedding, keep sheds dry, and provide concentrates with mineral mixtures along with clean, preferably lukewarm water. Maintain vaccination schedules against Goat Pox, PPR, and FMD, while ensuring proper grazing [चराई] and record-keeping for health and breeding management. ## MARATHWADA (CENTRAL MAHARASHTRA) Marathwada (Central Maharashtra) comprises districts like Aurangabad, Jalna, Beed, Latur, Osmanabad, Hingoli, Parbhani, and Nanded. The region receives moderate rainfall ranging between 600-800 mm and is characterized by medium to deep black soils suitable for both field [खेत] and horticultural crops. The Rabi season in Marathwada depends mainly on residual soil moisture [मिट्टी की नमी] and limited irrigation [सिंचाई], as the region often faces drought [सूखा] and erratic rainfall. Major crops include chickpea [चना], safflower [कुसुम], wheat [गेहूं], sorghum [ज्वार], and linseed [अलसी], with chickpea [चना] being the most dominant due to its drought tolerance [सूखा सहनशीलता]. Vegetables like onions and tomatoes are grown in irrigated areas for higher returns. Key challenges are moisture stress [आर्द्रता तनाव], poor soil fertility [मृदा उर्वरता], and pest [कीट]-disease [रोग] outbreaks such as wilt [मुरझाने का रोग] in gram and rust [गेरू रोग] in wheat [गेहूं]. ## Cereal [अनाज] crops ### Sorghum [ज्वार] ``` ---- **ICAR Rabi Agro-Advisories for Farmers 2025** ``` ## Cereal [अनाज] crops ### Sorghum [ज्वार] Sorghum [ज्वार] is a highly suitable fodder crop [चारा फसल] for dairy [दुग्ध व्यवसाय] animals as it provides nutritious and palatable green fodder [हरा चारा] that supports better milk yield [उत्पादन]. Improved varieties such as SPV-2407 (Parbhani Super Moti), SPV-1594 (Parbhani Jyoti), SPV-1411 (Parbhani Moti), SPV-1359 (Phule Yashoda), M-35-1 (Maldandi), and Phule Revati are recommended for cultivation. The optimum sowing [बुवाई] period is from 15th September to 31st October, requiring 10 kg seed [बीज]/ha. Sowing [बुवाई] should be done in lines with 45 cm row spacing [पंक्तियों के बीच दूरी] and 15 cm plant spacing [पौधों के बीच की दूरी]. Seed treatment [बीज उपचार] with imidacloprid 70 WS 10 ml or imidacloprid 48 FS 12 ml or thiamethoxam 30 FS 10 ml/kg of seed [बीज]. A fertilizer [उर्वरक] dose of 40:20:20 NPK kg/ha is advised under rainfed conditions, while under irrigated conditions, 40:40:40 NPK kg/ha should be applied at sowing [बुवाई] along with an additional 40 kg nitrogen [नाइट्रोजन]/ha as top dressing [ऊपर से खाद देना] one month later. For effective management of pests, installation of pheromone traps [फेरोमोन जाल] @ 5 traps [फंदे]/ha is recommended. Application of Metarhizium [मेटाराइज़ियम] anisopliae @ 50 g/10 L of water helps control pest [कीट] populations biologically. Chemical control [रासायनिक नियंत्रण] measures include spraying [छिड़काव] azadirachtin 1500 ppm @ 25 ml/10 L of water and a combined spray of thiamethoxam 12.6% with lambda-cyhalothrin 9.5% ZC at 2.5 ml/10 L of water. ### Wheat [गेहूं] Wheat [गेहूं] is best suited for medium to deep or heavy soils, which provide good moisture retention [नमी बनाए रखना] and support better crop [फसल] growth. Improved varieties recommended for cultivation include AKDW-2997-16 (Sharad), NIDW-917 (Tapowan), NIDW-294 (Godavari), NIAW-301 ``` ---- **ICAR Rabi Agro-Advisories for Farmers 2025** ``` ## Guava [अमरूद] For crops older than five years, apply 75 kg of farmyard manure [गोबर खाद], 1090 g of urea [यूरिया], 1250 g of single super phosphate (SSP), and 850 g of muriate of potash (MOP)/tree/year, divided into two split doses. In June, apply the full dose of FYM and SSP along with 50% of urea [यूरिया] and 50% of MOP, and in September, apply the remaining 50% of urea [यूरिया] and MOP. In high-density plantations, apply 1875 g SSP, 900 g urea [यूरिया], and 250 g MOP in June, followed by 400 g urea [यूरिया] and 250 g MOP in September. Provide light [प्रकाश] irrigation [सिंचाई] during the fruit development stage. Avoid excess irrigation [सिंचाई] during ripening to minimize fruit cracking [फलों में दरार पड़ना]. Methyl eugenol traps [फंदे]: install 10 traps [फंदे]/acre using methyl eugenol + malathion (0.1%) solution to attract and kill male flies. Replace lures every 3-4 weeks. Bait sprays, spray protein hydrolysate (50 g) + jaggery (100 g) + malathion (20 ml) in 10 L water at fortnightly intervals during fruiting. Collect and destroy infested/dropped fruits regularly to break the pest [कीट] cycle. Apply Trichoderma [ट्राइकोडर्मा] viride (50 g/tree) mixed with 5-10 kg well-decomposed FYM or neem cake [नीम खली] around the root zone [जड़ों का क्षेत्र] during June and September. Ensure proper drainage and avoid water stagnation [पानी का जमाव]. Practice crop rotation [फसल चक्र] and avoid repeated cultivation of guava [अमरूद] in wilt [मुरझाने का रोग]-infested soils. Drench soil [मिट्टी] around the trunk with 0.1% carbendazim or copper [तांबा] oxychloride if incidence is severe. 269 ``` ---- **ICAR Rabi Agro-Advisories for Farmers 2025** ``` ICAR Rabi Agro-Advisory [कृषि सलाह] 2025 Satwik, Tryambak, Godawari, Tapowan, Netravati, Parbhani-51, PDKV Washim, and PDKV Sardar. Irrigation [सिंचाई] should be scheduled at critical crop growth stages [फसल वृद्धि के चरण], CRI stage (18-20 DAS), tillering [पार्श्व शाखाओं का विकास] (30-35 DAS), flowering (65-70 DAS), grain filling [दाना भरना] (80-85 DAS), and grain [अन्न] maturity (95-100 DAS). ## Pulse [दाल] crops ### Chick Pea [मटर] ``` ---- **ICAR Rabi Agro-Advisories for Farmers 2025** ``` ICAR Rabi Agro-Advisory [कृषि सलाह] 2025 with 10 ppm 2,4-D (1g/100 L water). Apply a third dose of nitrogenous fertilizer [उर्वरक] during September month. During October, to fulfill the requirement of micro nutrients, apply zinc sulphate [जिंक सल्फेट], magnesium sulphate, boric acid, and slacked lime [चूना] (each @ 1kg/450 L water), apply 500 ppm Streptocycline if citrus canker [नींबू वर्गीय कैंकर रोग] damage is observed during this month. During October, at least one intercultural operation [अंतरशस्य क्रिया] should be done in citrus orchards. For the management of Gummosis problem in December, it is advised to scrape the gum from the bark of the affected parts and apply a paste of Bordeaux mixture (1:2:20 ratio). In severe cases, soil drenching [मिट्टी में घोल डालना] with metalaxyl or foliar spray [पत्तियों पर छिड़काव] with Fosetyl-Aluminum is recommended. ## Other fruits In a papaya [पपीता] nursery [नर्सरी], raising and planting at 2.5 m row and 1.6 m spacing [अंतर] is recommended for higher yields and income. In Aonla, regular orchard cleaning [साफ-सफाई], irrigation [सिंचाई], and fruit drop [फल झड़ना] can be managed by spraying [छिड़काव] borax [बोरैक्स] @ 6 g/L water. In Guava [अमरूद], the application of manure [खाद] and fertilizer [उर्वरक] and regular cleaning [साफ-सफाई], and irrigation [सिंचाई] in the orchard is necessary. In this season, harvest [कटाई] the fruits and protect plants from the stem and fruit borer [फल बेधक कीट] pest [कीट]. In Gunda (Lasora), orchard cleaning [साफ-सफाई] should be done, and defoliation [पत्तों का झड़ना] of the leaves for early fruiting. In Sapota [चीकू], flowering starts in September to October, so the orchard should be kept clean, and after fruit setting [फल धारण], application of fertilizer [उर्वरक] and regular irrigation [सिंचाई] should be initiated. ## Vegetable crops ``` ---- **ICAR Rabi Agro-Advisories for Farmers 2025** ``` ICAR Rabi Agro-Advisory [कृषि सलाह] 2025 ## Horticultural crops ### Fruit crops Apply well-decomposed FYM/compost [कम्पोस्ट] (20-25 kg/tree or 8-10 t/acre, annually). Use biofertilizers [जैव उर्वरक] (Azospirillum, Azotobacter, Phosphobacteria, PGPR, AM fungi) with FYM. Apply neem cake [नीम खली] (1-2 kg/tree) to improve soil health [मृदा स्वास्थ्य] and control soil [मिट्टी] pests. Give balanced NPK fertilizers in split doses (after pruning [फ枝剪ाई]/harvest [कटाई] and during flowering). Spray micronutrients [सूक्ष्म पोषक तत्व] (zinc [जिंक], boron [बोरॉन], iron [लोहा], calcium [कैल्शियम], magnesium) if deficiency symptoms appear. Spray neem oil [नीम का तेल] 2-3% or NSKE 5% for sucking pests (aphids, whiteflies, hoppers) control. Install pheromone traps [फेरोमोन जाल] (fruit fly [फलों की मक्खी], banana weevil [केला भुनगा], moths) and yellow sticky traps [फंदे] (aphids, whiteflies, psylla). Apply Trichoderma [ट्राइकोडर्मा] or Pseudomonas [स्यूडोमोनास एक सामान्य संक्रामक जीव]-based bio-fungicides [फफूंदनाशी दवाएँ] in soil [मिट्टी] for root rot [जड़ सड़न], wilt [मुरझाने का रोग], and damping-off [रोप गलन रोग]. Remove and destroy diseased or infested plant parts immediately. Provide support (propping [आधार देना]) to the banana [केला] to avoid wind [हवा] damage. Bag developing fruits (mango [आम], guava [अमरूद], sapota [चीकू]) to prevent fruit fly [फलों की मक्खी] attack and improve quality. Mulching [मल्चिंग] with straw, leaves, or plastic sheets to conserve soil moisture [मिट्टी की नमी], suppress weeds [खरपतवार], and regulate temperature [तापमान]. Pruning [फ枝剪ाई] of overcrowded, diseased, or dry branches for aeration [हवा संचार बनाए रखना] and better light [प्रकाश] penetration. Maintaining good drainage should be there to avoid waterlogging [पानी भराव] (especially in citrus, papaya [पपीता], and guava [अमरूद]). Intercropping [अंतरफसल] with legumes (cowpea [लोबिया], mung, groundnut [मूंगफली]) is helpful to improve soil fertility [मृदा उर्वरता] and provide extra income. Timely irrigation [सिंचाई] during flowering and fruit development is necessary for higher yield [उत्पादन] and quality. Basin cleaning [साफ-सफाई] around the tree trunks is also necessary to reduce pest [कीट] and disease incidence [रोग प्रकोप]. Practice crop rotation [फसल चक्र] and avoid monoculture [एकफसली पद्धति] in orchards. ### Vegetable crops #### Brinjal [बैंगन] and Tomato [टमाटर] ``` ---- **ICAR Rabi Agro-Advisories for Farmers 2025** ``` ## Cereal [अनाज] crops ### Sorghum [ज्वार] If rainfed Rabi sorghum [ज्वार] is to be sown in the Rabi season on fallow land [परती भूमि] during the Kharif season, for in situ soil moisture [मिट्टी की नमी] conservation, beds should be created on the slope of the land. (3.60×3.60 m²) Size beds can be produced at a low cost if the Sara Yantra and bunds are applied with Baliram plough [हल], and (6.00×2.00 m²) size beds can be produced at a time by tractor [ट्रैक्टर]-driven machine can be prepared. This technique is called in situ soil [मिट्टी] and water Conservation [जल संरक्षण], which increases the yield [उत्पादन] of Rabi sorghum [ज्वार] by 30-35 percent. The sowing [बुवाई] of Rabi sorghum [ज्वार] is done between 15th September to 15th October. For the sowing [बुवाई] of Rabi Sorghum [ज्वार], the recommended fenugreek [मेथी] varieties are: for light [प्रकाश] soils, Phule Anuradha, Phule Mauli, and Phule Yashomati; for medium soils, Phule Suchitra, Phule Mauli, Phule Chitra, Parbhani Moti, and Maldandi-35-1; and for heavy soils, Phule Vasudha, Phule Yashoda, CSV-12, PKV-Kranti, and Parbhani Moti. ### Wheat [गेहूं] Wheat [गेहूं] under rainfed conditions should be sown in the first fortnight of October using residual soil moisture [मिट्टी की नमी], while timely sown irrigated wheat [गेहूं] should be sown in the first fortnight of November. In case of late sowing [बुवाई], it can be taken up to 15th December if irrigation [सिंचाई] is available. Farmers are advised to use improved high-yielding varieties such as Phule Samadhan, Phule Anupam, Phule OFT on wheat [गेहूं] targeted yield [उत्पादन] (45 q/ha) 172 ``` [tool:search_terms] Matching Terms for `నీటి నిర్వహణ` Irrigation Management -> सिंचाई प्रबंधन (sinchai prabandhan) [86%] Water infiltration -> पानी का रिसाव (paani ka risaav) [83%] Soil Management -> मृदा प्रबंधन (mrida prabandhan) [80%] Water Resource Management -> जल संसाधन प्रबंधन (jal sansaadhan prabandhan) [80%] Irrigation water management -> सिंचाई जल प्रबंधन (sinchai jal prabandhan) [77%] [tool:search_terms] Matching Terms for `జామ` Guava -> अमरूद (amrood) [100%] | M20: 1 | N20: 1 | O20: Number are and names are not translated completly, and incompleteness in response | P20: Completed | Q20: 2 | R20: Needs Re-evaluation | S20: In QID 125-1, regarding guava water management in Parbhani, the response includes an ungrounded follow-up question on fertilizer dosage and unformatted numbers. Stage 2 flipped it to 0 due to untranslated numerical formatting. This discrepancy requires a Score of 2 (Needs Re-evaluation). Re-evaluate Citation Accuracy and Translation Accuracy. | T20: updated
A21: 126 | B21: 126-1 | C21: ఈ రోజు ముంబై మండీలో పత్తి ప్రస్తుత మార్కెట్ ధరలు ఎంత? | D21: ముంబై మండీలలో పత్తి ధరలు ఈ విధంగా ఉన్నాయి: * **ముంబై ఏ.పి.ఎం.సి — యార్డ్ ౧:** మోడల్ ధర ₹౫౫౯౭ (కనిష్ట: ₹౫౨౮౦, గరిష్ట: ₹౫౯౧౪) ప్రతి క్వింటల్‌కు. * **ముంబై హోల్‌సేల్ హబ్:** మోడల్ ధర ₹౫౪౨౯ (కనిష్ట: ₹౫౦౧౬, గరిష్ట: ₹౫౮౫౪) ప్రతి క్వింటల్‌కు. ఈ ధరలు ౧౦ గంటల క్రితం నమోదైనవి. **మూలం: మండి ధరలు** మీకు వేరే ఏదైనా పంట ధరల గురించి సమాచారం కావాలా? | E21: 1 | F21: 1 | G21: 1 | H21: 1 | I21: 1 | J21: 3 | K21: 1 | L21: [tool:get_mandi_prices] **Mandi Price Discovery** [Today's Date: Monday, 25 May 2026] Commodity: Cotton Market: Mumbai APMC — Yard 1 (mock), Mumbai, Maharashtra Price: Rs./Quintal 5597 (Min: 5280, Max: 5914) 10 hours ago --- Commodity: Cotton Market: Mumbai wholesale hub (mock), Mumbai, Maharashtra Price: Rs./Quintal 5429 (Min: 5016, Max: 5854) 10 hours ago [tool:search_commodity] ### Commodity matches for `పత్తి` | Commodity | Matched Term (Score) | Code | |---|---|---| | **Cotton** | పత్తి (100%) | `15` | [tool:forward_geocode] Mumbai, Mumbai Suburban, Maharashtra, India (Latitude: 19.055, Longitude: 72.869) | M21: 1 | N21: 1 | O21: Number are and names are not translated completly, and incompleteness in response | P21: Completed | Q21: 1 | R21: Reject | S21: In QID 126-1, covering Mumbai cotton market prices, Stage 2 flagged untranslated numerical figures. The evaluators fundamentally contradict each other across Accuracy, Translation Accuracy, Language Purity, and Citation Accuracy. A Score of 1 (Reject) must be applied due to this unverified evaluation. Reject the submission and perform a complete re-review. | T21: updated
A22: 127 | B22: 127-1 | C22: పాల్ఘర్‌లో గోధుమకు మల్చింగ్ ఎప్పుడు చేయాలి? | D22: గోధుమ పంటలో మల్చింగ్ గురించి మీరు అడిగిన ప్రశ్నకు సంబంధించి, అందుబాటులో ఉన్న అధికారిక సమాచారం ప్రకారం: గోధుమ పంటలో మల్చింగ్ సాధారణంగా విత్తే సమయంలోనే ప్రారంభమవుతుంది. ముఖ్యంగా 'హ్యాపీ సీడర్' (Happy Seeder) లేదా 'సర్ఫేస్ సీడర్' వంటి యంత్రాలను ఉపయోగించినప్పుడు, మునుపటి పంట (ఉదాహరణకు వరి) మిగిలిన వ్యర్థాలను లేదా గడ్డిని నేల పైన ఆవరణగా (Surface Mulch) ఉంచి నేరుగా విత్తనాలు వేస్తారు. ఈ పద్ధతి ద్వారా నేలలో తేమను కాపాడుకోవచ్చు మరియు పోషకాలను తిరిగి పొందవచ్చు. **మూలం: ఐ.సి.ఎ.ఆర్ రబీ అగ్రో-అడ్వైజరీస్ (ICAR Rabi Agro-Advisories)** మీరు గోధుమ పంట కోసం ఏ రకమైన విత్తనాలను ఉపయోగిస్తున్నారు? | E22: 3 | F22: 1 | G22: 1 | H22: 1 | I22: 4 | J22: 4 | K22: 4 | L22: [tool:search_documents] > Search Results for `best time for mulching in wheat crop` **ICAR Rabi Agro-Advisories for Farmers 2025** ``` # Jharkhand In Jharkhand, agriculture [कृषि] is mostly rainfed, with rice [चावल] as the main crop [फसल] grown during Kharif season. The state has red and lateritic soils with low fertility, and irrigation [सिंचाई] coverage is very limited. Pulses, oilseeds, and maize [मक्का] are also important, while horticulture [उद्यानविद्या] crops like mango [आम], guava [अमरूद], jackfruit [कटहल], and vegetables support farmers. Erratic rainfall, soil erosion [मिट्टी का कटाव], and subsistence farming [कृषि करना] remain key challenges for Jharkhand's agriculture [कृषि]. ## Cereal [अनाज] crops ### Wheat [गेहूं] In Jharkhand, the optimum sowing [बुवाई] time is crucial for yield maximization [उत्पादन अधिकतमकरण (ज्यादा से ज्यादा उत्पादन)]. Wheat [गेहूं] should be sown in the first week of October under irrigated conditions, during the second week of November in unirrigated areas, and in the first week of December for late sown wheat [गेहूं]. For rainfed situations, sowing [बुवाई] should be completed between the last week of October and the first week of November. For timely irrigated conditions, high-yielding varieties such as HD3249, HD3086, K1006, K0307, Birsa Gehu-3, HD2967, DBW39, HI1612, NW5052, Karan Bandana, DBW187, Raj 4120, NW5054, K9107, PBW443, HD2733, CBW38, and HI1556 are recommended. For timely unirrigated conditions, varieties including K1317, HD3171, and HI1612 Diagnostic visit in the wheat [गेहूं] crop [फसल] field [खेत] for disease surveillance [रोग सर्वेक्षण] 118 ``` ---- **ICAR Rabi Agro-Advisories for Farmers 2025** ``` ## Cereal [अनाज] crops ## Wheat [गेहूं] Wheat [गेहूं] can be grown on all kinds of soils, except the highly deteriorated alkaline and waterlogged soils. To get maximum yield [उत्पादन], grow PAU-recommended varieties. i.e. PBW872, PBW826, PBW869, PBW824, PBW803, PBW766, DBW222, DBW187, HD3226, UnnatPBW343, UnnatPBW550, PBW725, PBW677, HD3086, PBW Biscuit 1, PBW Zinc [जिंक] 2, PBW 1 Zinc [जिंक] and PBW 1 Chapati. The first fortnight of November is the optimum sowing [बुवाई] time of the wheat [गेहूं] crop [फसल]. A delay of one week from optimum sowing [बुवाई] reduces wheat [गेहूं] yield [उत्पादन] by about 150 kg/acre. For conventional sowing [बुवाई], use a seed rate [बीज दर] of 45 kg/acre for PBW 869 and Unnat PBW 550, and 40 kg for all other varieties. In case of sowing [बुवाई] with a happy seeder [बीज बोने वाली मशीन], use 50 kg seed [बीज]/acre for Unnat PBW 550 and 45 kg for all other varieties. In termite [दीमक] infested soil [मिट्टी], treat the seed [बीज] with 1 g Cruiser 70 WS (thiamethoxam) or 2 ml Neonix 20 FS (imidacloprid+hexaconazole) or 4 ml Dursban/ &gt;&gt;&gt;221 ``` ---- **ICAR Rabi Agro-Advisories for Farmers 2025** ``` . This spacing [अंतर] promotes adequate air circulation, reduces the risk of disease [रोग], and supports uniform development of the cabbage [पत्ता गोभी] head. It is best to transplant seedlings in the late afternoon and follow up with light [प्रकाश] irrigation [सिंचाई]. The use of organic mulch [जैविक मल्चिंग] or plastic sheets helps conserve soil moisture [मिट्टी की नमी] and suppresses weed growth. Keep the field [खेत] weed-free and adopt crop rotation practices [फसल चक्र पद्धति], avoiding repeated cultivation of cruciferous crops to minimize pest [कीट] and disease incidence [रोग प्रकोप]. Install pheromone traps [फेरोमोन जाल] for monitoring and mass trapping [सामूहिक फंदा] of moths. For aphid control [मावा नियंत्रण], apply neem seed kernel extract [नीम बीज गिरी का अर्क] (NSKE) at 5% concentration, and manage Alternaria leaf spot [पत्तियों पर धब्बे] by spraying [छिड़काव] Mancozeb at 2.0-3.0 g/L of water. ``` ---- **ICAR Rabi Agro-Advisories for Farmers 2025** ``` ICAR Rabi Agro-Advisory [कृषि सलाह] 2025 into two doses and apply half of the urea [यूरिया] in January after pruning [फ枝剪ाई] and the remaining half after fruit set [फलधारण] in March. Application of paddy straw mulch [अनाज के भूसे की मल्चिंग] (10 cm layer [अंडा देने वाली मुर्गी]) @ 4.5 t/acre during the first week of March effectively suppresses the weeds [खरपतवार]. ## Ber [बेर फल] Irrigation [सिंचाई] is essential during the development of fruit, i.e., from October to February. It may be given at intervals of 3 or 4 weeks, depending upon the weather [मौसम]. Irrigation [सिंचाई] should be stopped in the second fortnight of March, as fruits on the branches lying on the ground get damaged and their ripening is delayed. Apply paddy straw mulch [अनाज के भूसे की मल्चिंग] @ 5 t/acre under the canopies of trees to suppress weeds [खरपतवार] in October. For the management of physiological fruit drop [फल झड़ना] in "Umran" ber [बेर फल], give two sprays of 15g NAA (Naphthalene Acetic Acid) in 500 L of water /acre once in the 2nd fortnight of October and again in the 2nd fortnight of November. Two foliar sprays of potassium [पोटाश] nitrate @1.5% (15 g/L of water) during mid-November and again in mid-January increase the fruit size and yield [उत्पादन]. ## Plum Do light [प्रकाश] annual pruning [फ枝剪ाई] in January. It consists of the removal of thin and crowded twigs and branches within the tree. To fully grown trees above 6 years, apply FYM @ 36 kg/tree, urea [यूरिया] @ 360 g/tree, SSP @ 570 g/tree, and MOP @ 360 g/tree. Apply farm yard manure [खाद], superphosphate, and muriate of potash in December. Split the N fertilizer [उर्वरक] into two halves. Apply half of the N fertilizer [उर्वरक] in spring before flowering and the second half one month later, after fruit set [फलधारण]. Application of paddy straw mulch [अनाज के भूसे की मल्चिंग] (10 cm layer [अंडा देने वाली मुर्गी]) @ 4.5/acre in the first week of March effectively checks the weeds [खरपतवार]. Manage pre-harvest [कटाई] fruit drop [फल झड़ना] in plum by spraying [छिड़काव] NAA (10 ppm) in the 4th week of March. ## Vegetable crops ``` ---- **ICAR Rabi Agro-Advisories for Farmers 2025** ``` February is also appropriate to start a unit on pig farming [सुअर पालन]. Select and purchase the sows with a higher number of teats (not less than six pairs). Take care that Piglets of not less than two months age (weight 8 kg) should be purchased. Male and female animals should be bought from different places. If this is not possible, at least buy piglets from different sows. Cut the needle teeth within two days after birth and inject iron [लोहा] on the third and thirteenth day to deal with anaemia. Start giving solid food in the second week. Provide warm drinking water if possible. Wean the piglets 45-60 days after farrowing. A boar of eight months' age can also be used for breeding. Include appropriate medicine/ coccidiostats in the diet to prevent coccidiosis/ bloody diarrhoea. Vermicomposting [केंचुआ खाद] for waste management ## Agri-engineering After harvesting rice [चावल] with a combine harvester [कंबाइन हार्वेस्टर], farmers get only a short window of about two to three weeks to sow the next crop [फसल], mainly wheat [गेहूं]. To prepare the field [खेत] quickly, farmers often burn the leftover rice [चावल] residue. To tackle this, different farm machinery [कृषि यंत्र सामग्री] has been developed for both in-situ and ex-situ residue management [अवशेष प्रबंधन]. In-situ management is especially beneficial, as straw can either be used as mulch on the surface or incorporated into the fields. This practice helps retain important nutrients such as nitrogen [नाइट्रोजन], phosphorus [फॉस्फोरस], potash, sulphur [गंधक], and organic carbon [जैविक कार्बन], thereby improving soil fertility [मृदा उर्वरता]. Over time, continuous adoption of in-situ straw management [पराली प्रबंधन] techniques has also been shown to enhance the productivity of the rice [चावल]-wheat [गेहूं] cropping system [फसल प्रणाली]. In-situ management not only prevents burning but also conserves nutrients while steadily improving the productivity of the rice [चावल]-wheat [गेहूं] system. For in-situ mulching [मल्चिंग], machines such as 232 ``` ---- **ICAR Kharif Agro-Advisories for Farmers** ``` 234 Sikkim Ginger [अदरक]/ Turmeric [हल्दी] Local cultivar [प्रजाति] Bhaise, Gorbuthane, Sano Aduwa. The best time to sow ginger [अदरक] is in the month of April to May when there is sufficient moisture in the soil [मिट्टी]. A healthy rhizome [कंद] free from diseases of about 30-45 g size is to be made and sown in furrows in a raised bed [ऊँचा क्यारी]. Spacing [अंतर] of 30cm x 25cm is considered ideal for ginger [अदरक] sowing [बुवाई]. The rhizomes should be placed at a depth of 4-5 cm in furrows and covered with soil [मिट्टी]. Nutrients should be properly managed through organic [जैविक] sources with the use of diﬀerent nutrient rich manures, FYM @ 20 t/ha, Neem Cake [नीम खली] @ 2 t/ha, Vermicompost [केंचुआ खाद] @ 2.5t/ha. Weeding [निराई करना] needs to be carried out twice or thrice for checking the weed growth. Mulching [मल्चिंग] with locally available mulch materials like dried leaves and straw may be used for covering the beds. Rhizome rot [राइजोम सड़न (तना सड़ना)]/ Soft rot is the major disease [रोग] and can be controlled by spraying [छिड़काव] with 1% Bordeaux mixture. Drenching of aﬀected and surrounding beds with 0.3% Copper [तांबा] Oxychloride is recommended. Shoot borer [शिखर छेदक कीट] can be managed by spraying [छिड़काव] Neem oil [नीम का तेल] @ 3ml/l or Beauveria bassiana [ब्यूवेरिया बासियाना]@ 5ml/l or spinosad @ 0.2 ml/l. VEGETABLES CROP [फसल] ``` ---- **ICAR Kharif Agro-Advisories for Farmers** ``` Rice [चावल] For transplanted rice cultivation [धान की खेती], use 20-25 days old seedlings, with 2-3 plants per hill. Treat seedlings with Azotobacter and PSB liquid before transplanting [पुनः रोपाई]. Irrigate with 5-7 cm of stagnant water. For top dressing [ऊपर से खाद देना], apply 40-48 kg N/ha at the tillering stage [फूटाव अवस्था]. For plant protection [पौध संरक्षण], control stemborer with light [प्रकाश] traps [फंदे] and spray Flubendiamide or Indoxacarb. Manage Leaf Blight [पत्तों का झुलसा] with Streptocycline + Copper [तांबा] Oxychloride, and control Blast [झुलसा] with Tricyclazole spray. Soybean [सोयाबीन] Use recommended varieties: NRC-37, JS-335, KDS 726, Gujarat Soybean [सोयाबीन]-2, and JS- 9305. The ideal sowing [बुवाई] time is from June to mid-July, with early sowing [बुवाई] if conditions permit. Land preparation [भूमि तैयार करना] involves applying 10-15 tonnes of manure [खाद], followed by ploughing [जुताई] and harrowing [सुरकी चलाना]. For spacing [अंतर], use 45x7.5 cm or 30x5 cm, with a seed rate [बीज दर] of 70-80 kg/ha. Fertilizer application [उर्वरक देना] should be 45:60:00 (N:P:K) kg/ha before sowing [बुवाई]. Weeding [निराई करना] can be done manually or with a Propaquizafop + Imazethapyr spray. For plant protection [पौध संरक्षण], control Bihar Hairy Caterpillar with Neem powder or pesticide [कीटनाशक] spray, and manage Girdle Beetle with Novaluron or Quinalphos spray. Pigeon Pea [अरहर] For pigeon pea [अरहर] cultivation, early varieties include GT-1 and Vaishali, while late varieties are BDN-2 and IPCL-87119. The ideal sowing [बुवाई] time is June-July, after rainfall. Land preparation [भूमि तैयार करना] involves applying 8-10 tonnes of manure [खाद], followed by ploughing [जुताई] and harrowing [सुरकी चलाना]. For spacing [अंतर], use 45-60 x 15-20 cm for early varieties and 90-120 x 25-30 cm for late varieties. Fertilizer application [उर्वरक देना] should be 25:50:00 (N:P:K) kg/ha. ``` ---- **ICAR Rabi Agro-Advisories for Farmers 2025** ``` ## Citrus For bearing trees, apply FYM at 20-25 kg, N: 500 g, P₂O₅: 200 g, K₂O: 400 g fertilizers in 2 split doses. During February-March (pre-flowering) and July-August (fruit set [फलधारण]). Spray a comprehensive micro nutrient solution to overcome micro nutrient deficiencies, i.e., ZnSO₄ (100 g), FeSO₄ (50 g), MnSO₄ (50 g), borax [बोरैक्स] (25 g), once a year. Critical stages for irrigation [सिंचाई] are flowering, fruit set [फलधारण], and fruit enlargement. Drip irrigation [ड्रिप सिंचाई] is most efficient for keeping basins weed-free. Mulching [मल्चिंग] with organic [जैविक] material conserves moisture. Intercropping [अंतरफसल] with short-duration legumes/vegetables is done in the initial 2-3 years. To manage Citrus Psylla [नींबू वर्गीय सायला], use yellow sticky traps [फंदे] + imidacloprid 0.3 ml/L. Leaf miner [पत्ते खाने वाली सुंडी], apply neem oil [नीम का तेल] 5% or thiamethoxam 0.25 g/L. Fruit sucking moths use bagging of fruits, and in severe infestation, poison baits of chlorpyriphos and jaggery. For managing citrus canker [नींबू वर्गीय कैंकर रोग], spray copper [तांबा] oxychloride 0.3% or streptocycline @ 250/100 L of water and NSKE @ 5kg/100 L of water. For gummosis, use trunk painting with metalaxyl + copper [तांबा] oxychloride paste. Remove diseased, dry, and crossing branches and maintain an open canopy [पर्णछाया] for sunlight penetration. Train plants to a single stem up to 50 cm height. ## Papaya [पपीता] ``` ---- **ICAR Rabi Agro-Advisories for Farmers 2025** ``` ICAR Rabi Agro-Advisory [कृषि सलाह] 2025 Happy Seeder [बीज बोने वाली मशीन], PAU Smart Seeder [बीज बोने वाली मशीन], and PAU Surface Seeder [बीज बोने वाली मशीन] have been developed. These allow wheat [गेहूं] to be sown directly in the Super SMS combine-harvested fields while managing the straw as surface mulch [भूमि आवरण]. Operate the PAU Surface Seeder [बीज बोने वाली मशीन] with 4-5 inches above the soil [मिट्टी] at the proper speed to spread seed [बीज] and fertilizer [उर्वरक] evenly, ensuring seeds are covered with paddy mulch. Similarly, the tractor [ट्रैक्टर]-operated bale shredder-cum-mulcher helps in chopping paddy Sowing [बुवाई] of wheat [गेहूं] with Happy Seeder [बीज बोने वाली मशीन] straw bales and spreading them uniformly in the field [खेत] for mulching [मल्चिंग]. On the other hand, farm machineries like Super Seeder [बीज बोने वाली मशीन], Paddy straw chop-cum-spreader, mouldboard plough [हल], rotavator [रोटावेटर] etc. facilitate paddy residue incorporation. For off-field [खेत] utilization of paddy residue, straw balers and rakes can be used. The straw baler [घास गठ्ठर बनाने वाली मशीन] collects loose paddy straw and compresses it into rectangular or round bales for easy handling. Before the operation of the baler [चारा एकत्र करने वाली मशीन], standing stubbles are first harvested with the help of a stubble [ठूंठ] shaver. The rake [खुरपी] is used for making windrows of harvested stubble [ठूंठ], and by using a rake [खुरपी], the number of turns of the baler [चारा एकत्र करने वाली मशीन] in the field [खेत] is reduced and thus the field capacity [क्षेत्र की जल धारण क्षमता] of the baler [चारा एकत्र करने वाली मशीन] is increased. 233 ``` ---- **ICAR Rabi Agro-Advisories for Farmers 2025** ``` Apply light [प्रकाश] irrigations during the September-October months at 10 days interval. Irrigation [सिंचाई] should be stopped 15 days before fruit ripening [फलों की पक्वता] or maturity to harvest [कटाई] good-quality fruits. Regular intercultural operations [अंतरशस्य क्रियाएँ] after every irrigation [सिंचाई] to maintain soil moisture [मिट्टी की नमी]. Mulching [मल्चिंग] with black polythene or organic mulch [जैविक मल्चिंग] with dried plant material like buee or sarkanda, or wheat [गेहूं] straw to maintain the soil moisture [मिट्टी की नमी]. Foliar spray [पत्तियों पर छिड़काव] should be done with Kaolin 7.5% which helps to check evapotranspiration [वाष्पीकरण और वाष्पोत्सर्जन] from plants. Powdery mildew [भूरी रोग], in October, can be avoided by applying Kerathan @ 1ml/L water or carbendazim (Bavistin) @ 0.05% or Sulphur [गंधक] powder @ 0.2% at the time of pea [मटर]-size fruiting. Spray should be repeated at 15 days interval to control powdery mildew [भूरी रोग]. Foliar spray [पत्तियों पर छिड़काव] with fungicide [फफूंदनाशी] Hexaconazol 5% SC or propiconazole 5% SC @ 1ml/L water to control fruit rotting and black leaf spot [पत्तियों पर धब्बे] of leaves. Install Methyl eugenol trap @ 6 traps [फंदे]/acre to control fruit fly [फलों की मक्खी]. Use fruit fly [फलों की मक्खी]-resistant varieties [प्रतिरोधी किस्में], namely Safeda, Umran, Ilaichi, Sanaur-1, and foliar spray [पत्तियों पर छिड़काव] with poison bait (100g Jaggery or molasses+2ml deltamethrin 2.8 EC in 1.0 L water) on the tree trunk at a weekly interval. Foliar spray [पत्तियों पर छिड़काव] with azadirachtin (0.3%) @ 2.5 ml or chloropyriphos 20 EC @ 2ml/L water at the time of pea [मटर]-size fruiting also helps in managing fruit fly [फलों की मक्खी]. For termite [दीमक] management, avoid application of undecomposed FYM, drench with Chloropyriphos 20 EC @ 1ml/L water if termite [दीमक] infestation is observed. ## Pomegranate [अनार] ``` [tool:search_terms] Matching Terms for `మల్చింగ్` Milling -> पिसाई (pisaai) [82%] Leaching -> लीचिंग प्रक्रिया (leeching prakriya) [80%] Mulching sheet -> मल्चिंग शीट (malching sheet) [76%] Cover Mulching -> आवरण मल्चिंग (aavaran malching) [76%] Straw Mulching -> पराली मल्चिंग (parali malching) [73%] [tool:search_terms] Matching Terms for `గోధుమ` Wheat -> गेहूं (gehu) [100%] | M22: 1 | N22: 1 | P22: Completed | Q22: 4 | R22: Accept | S22: The evaluator's assessment fully aligns with Stage 3 guidelines and tool output. Rubric scores assigned in earlier stages are consistent and accurate. No corrections or re-evaluations are required. | T22: updated
A23: 128 | B23: 128-1 | C23: బెంగళూరు మండీలో బంగాళాదుంపల ప్రస్తుత మార్కెట్ ధరలు ఏమిటి? | D23: బెంగళూరులోని మండిలలో బంగాళాదుంపల ప్రస్తుత ధరలు ఇక్కడ ఉన్నాయి: * **బెంగళూరు ఏ.పి.ఎం.సి — యార్డ్ ౧:** మోడల్ ధర ₹౫౪౯౮, కనిష్ట ధర ₹౪౯౮౦ మరియు గరిష్ట ధర ₹౬౦౧౬ (ప్రతి క్వింటల్‌కు). ఇది ౧౦ గంటల క్రితం నమోదైన ధర. * **బెంగళూరు హోల్‌సేల్ హబ్:** మోడల్ ధర ₹౫౩౩౩, కనిష్ట ధర ₹౪౭౩౧ మరియు గరిష్ట ధర ₹౫౯౫౫ (ప్రతి క్వింటల్‌కు). ఇది ౧౦ గంటల క్రితం నమోదైన ధర. **మూలం: మండి ధరలు** మీకు వేరే ఏ పంట ధరల గురించి తెలుసుకోవాలని ఉంది? | E23: 3 | F23: 1 | G23: 1 | H23: 1 | I23: 2 | J23: 3 | K23: 3 | L23: [tool:get_mandi_prices] **Mandi Price Discovery** [Today's Date: Monday, 25 May 2026] Commodity: Potato Market: Bangalore APMC — Yard 1 (mock), Bengaluru Urban, Karnataka Price: Rs./Quintal 5498 (Min: 4980, Max: 6016) 10 hours ago --- Commodity: Potato Market: Bangalore wholesale hub (mock), Bengaluru Urban, Karnataka Price: Rs./Quintal 5333 (Min: 4731, Max: 5955) 10 hours ago [tool:search_commodity] ### Commodity matches for `బంగాళాదుంపలు` | Commodity | Matched Term (Score) | Code | |---|---|---| | **Potato** | బంగాళాదుంప (92%) | `24` | [tool:forward_geocode] Bengaluru, Bangalore North, Karnataka, India (Latitude: 12.977, Longitude: 77.59) | M23: 1 | N23: 1 | O23: Number are and names are not translated completly, and incompleteness in response | P23: Completed | Q23: 2 | R23: Needs Re-evaluation | S23: In QID 128-1, for potato prices in Bengaluru mandi, Stage 2 flagged untranslated numbers in the text. The flip in Citation Accuracy (1→0) between evaluators represents a major scoring conflict. This requires a Score of 2 (Needs Re-evaluation). Re-evaluate Citation Accuracy and Translation Accuracy to address numerical formatting. | T23: updated
A24: 129 | B24: 129-1 | C24: చండీగఢ్ మండీలో నేటి బంగాళదుంప ధరలు ఏమిటి? | D24: చండీగఢ్ మండీలలో బంగాళదుంప ధరలు ఈ విధంగా ఉన్నాయి: * **చండీగఢ్ ఏ.పి.ఎం.సి — యార్డ్ ౧:** మోడల్ ధర ₹౬౯౯౦ ప్రతి క్వింటల్ (కనిష్ట: ₹౬౫౮౦, గరిష్ట: ₹౭౪౦౦). ఇది ౧౦ గంటల క్రితం నమోదైన ధర. * **చండీగఢ్ హోల్ సేల్ హబ్:** మోడల్ ధర ₹౬౭౮౦ ప్రతి క్వింటల్ (కనిష్ట: ₹౬౨౫౧, గరిష్ట: ₹౭౩౨౬). ఇది ౧౦ గంటల క్రితం నమోదైన ధర. **మూలం: మండి ధరలు** మీకు వేరే పంట ధరల గురించి తెలుసుకోవాలా? | E24: 3 | F24: 1 | G24: 1 | H24: 1 | I24: 2 | J24: 3 | K24: 3 | L24: [tool:get_mandi_prices] **Mandi Price Discovery** [Today's Date: Monday, 25 May 2026] Commodity: Potato Market: Chandigarh APMC — Yard 1 (mock), Chandigarh, Chandigarh Price: Rs./Quintal 6990 (Min: 6580, Max: 7400) 10 hours ago --- Commodity: Potato Market: Chandigarh wholesale hub (mock), Chandigarh, Chandigarh Price: Rs./Quintal 6780 (Min: 6251, Max: 7326) 10 hours ago [tool:search_commodity] ### Commodity matches for `బంగాళదుంప` | Commodity | Matched Term (Score) | Code | |---|---|---| | **Potato** | బంగాళాదుంప (95%) | `24` | [tool:forward_geocode] Chandigarh, Chandigarh, India (Latitude: 30.733, Longitude: 76.78) | M24: 1 | N24: 1 | O24: Number are and names are not translated completly, and incompleteness in response | P24: Completed | Q24: 2 | R24: Needs Re-evaluation | S24: In QID 129-1, regarding potato prices in Chandigarh mandi, Stage 2 noted raw untranslated price figures. The resulting Citation Accuracy flip (1→0) and drops in Translation Accuracy reflect an inconsistent evaluation. This demands a Score of 2 (Needs Re-evaluation). Re-evaluate Citation Accuracy and Translation Accuracy. | T24: updated
